Workbook
Name Slicer_Signed_Copy: #N/A
Name Slicer_Status: #N/A
Name Slicer_Work_Type: #N/A

Sheet Agreements
B1: Agreements
B2: Client | C2: Contact | D2: Line of Business | E2: Business | F2: Contract Type | G2: Work Type | H2: Date Signed | I2: Description | J2: Signed Copy | K2: DocuSign | L2: Effective Date | M2: Duration (Months) | N2: Expiration Date | O2: Days to Contract End | P2: General Liability Insurance | Q2: COI Requirement | R2: GL Aggregate Limits | S2: GL per Occurrence | T2: Workers Compensation | U2: Employers Liability | V2: Umbrella Aggregate | W2: Umbrella per Occurrence | X2: Cyber Aggregate | Y2: Cyber per Occurrence | Z2: Professional Liability (E&O) | AA2: Property in Transit | AB2: Employee Theft of Client Property | AC2: Products/Completed Operations | AD2: Personal & Advertising Injury | AE2: Bodily Injury/Property Damage | AF2: Fire Legal Liability Injury | AG2: Medical Payments | AH2: Auto Insurance Combined Single Limit (Hired) | AI2: Auto Insurance Combined Single Limit (Non-owned) | AJ2: Auto Insurance Combined Single Limit (Owned) | AK2: R.A.G. Status | AL2: Notes | AM2: Path | AN2: Yes | AO2: No
B3: ABC Fitness Solutions, LLC | C3: =IFERROR(VLOOKUP(B3,'QB Consolidated Contacts'!$A$1:$F$333,6),"-") -> Prakash Rikhilal | E3: VNA | F3: MSA | G3: Agreement | I3: Master Services Agreement | J3: Yes | L3: 44053 | M3: ON-GOING | N3: =IFERROR(EDATE(L3,M3),"") | O3: =IFERROR(N3-TODAY(),"") | P3: Yes | R3: $1M | S3: $1M | V3: - | X3: - | Y3: - | AJ3: $100K | AK3: =IF(AGREEMENTS[[#This Row],[Days to Contract End]]<=90,"R",IF(AND(AGREEMENTS[[#This Row],[Days to Contract End]]<180),"A","G")) -> G
B4: Accelario Software Inc. | C4: =IFERROR(VLOOKUP(B4,'QB Consolidated Contacts'!$A$1:$F$333,6),"-") -> Prakash Rikhilal | E4: VT | F4: VAR Agreement | G4: Partnership | H4: 45770 | I4: ACCELARIO - Partnership Distribution Agr w Viscosity - clean version - final.docx | J4: Yes | K4: Yes | N4: =IFERROR(EDATE(L4,M4),"") -> 0 | O4: =IFERROR(N4-TODAY(),"") -> -46093 | AK4: =IF(AGREEMENTS[[#This Row],[Days to Contract End]]<=90,"R",IF(AND(AGREEMENTS[[#This Row],[Days to Contract End]]<180),"A","G")) -> R
B5: ACGI Software | C5: =IFERROR(VLOOKUP(B5,'QB Consolidated Contacts'!$A$1:$F$333,6),"-") -> Kevin Hostintler | E5: VNA | F5: MSA | G5: Agreement | I5: Master Services Agreement | J5: No | L5: 43252 | M5: ON-GOING | N5: =IFERROR(EDATE(L5,M5),"") | O5: =IFERROR(N5-TODAY(),"") | P5: Yes | R5: $1M | S5: $1M | V5: - | X5: - | Y5: - | AJ5: $100K | AK5: =IF(AGREEMENTS[[#This Row],[Days to Contract End]]<=90,"R",IF(AND(AGREEMENTS[[#This Row],[Days to Contract End]]<180),"A","G")) -> G | AL5: Last billed in 2018
B6: AMDI | C6: =IFERROR(VLOOKUP(B6,'QB Consolidated Contacts'!$A$1:$F$333,6),"-") -> Christina Green | E6: VNA | F6: MSA | G6: Agreement | I6: AMDI-MSA-2024-4854-1967-0962-v6.1 EXECUTED VNA.pdf | J6: No | K6: No | N6: =IFERROR(EDATE(L6,M6),"") -> 0 | O6: =IFERROR(N6-TODAY(),"") -> -46093 | AK6: =IF(AGREEMENTS[[#This Row],[Days to Contract End]]<=90,"R",IF(AND(AGREEMENTS[[#This Row],[Days to Contract End]]<180),"A","G")) -> R
B7: American Heart Association, Inc. | C7: =IFERROR(VLOOKUP(B7,'QB Consolidated Contacts'!$A$1:$F$333,6),"-") -> Roger Santone | E7: VNA | F7: MSA | G7: Agreement | I7: Master Services Agreement | J7: Yes | L7: 42880 | M7: ON-GOING | N7: =IFERROR(EDATE(L7,M7),"") | O7: =IFERROR(N7-TODAY(),"") | P7: Yes | R7: $2M | S7: $1M | V7: $5M | X7: $6M | Y7: $1M | AJ7: $1M | AK7: =IF(AGREEMENTS[[#This Row],[Days to Contract End]]<=90,"R",IF(AND(AGREEMENTS[[#This Row],[Days to Contract End]]<180),"A","G")) -> G
B8: American Leather | C8: =IFERROR(VLOOKUP(B8,'QB Consolidated Contacts'!$A$1:$F$333,6),"-") -> Roger Santone | E8: VNA | F8: MSA | G8: Agreement | I8: VNA.MSA.AMERICAN_LEATHER.2023.docx | J8: Yes | K8: Yes | L8: 45139 | M8: ON-GOING | N8: =IFERROR(EDATE(L8,M8),"") | O8: =IFERROR(N8-TODAY(),"") | AK8: =IF(AGREEMENTS[[#This Row],[Days to Contract End]]<=90,"R",IF(AND(AGREEMENTS[[#This Row],[Days to Contract End]]<180),"A","G")) -> G
B9: American Unit | C9: =IFERROR(VLOOKUP(B9,'QB Consolidated Contacts'!$A$1:$F$333,6),"-") -> Roger Santone | E9: VNA | F9: NDA | G9: Agreement | I9: MNDA - DW 092124 American Unit (Fully executed).pdf | V9: =IFERROR(EDATE(T9,U9),"") -> 0 | W9: =IFERROR(V9-TODAY(),"") -> -46093 | X9: =IF(SOWS[[#This Row],[Days to Contract End]]<=90,"R",IF(AND(SOWS[[#This Row],[Days to Contract End]]<180),"A","G")) -> R | AK9: =IF(AGREEMENTS[[#This Row],[Days to Contract End]]<=90,"R",IF(AND(AGREEMENTS[[#This Row],[Days to Contract End]]<180),"A","G")) -> R
B10: Apex Capital Corp. | E10: VNA | F10: NDA | G10: Agreement | H10: 45660 | I10: VNA.MNDA.2023 - Apex Capital Corp - Accepted.docx | J10: Yes | K10: Yes | L10: 45656 | M10: 36 | N10: =IFERROR(EDATE(L10,M10),"") -> 46751 | O10: =IFERROR(N10-TODAY(),"") -> 658 | AK10: =IF(AGREEMENTS[[#This Row],[Days to Contract End]]<=90,"R",IF(AND(AGREEMENTS[[#This Row],[Days to Contract End]]<180),"A","G")) -> G
B11: Apex Capital Corp. | C11: =IFERROR(VLOOKUP(B11,'QB Consolidated Contacts'!$A$1:$F$333,6),"-") -> 0 | E11: VT | F11: MSA | G11: Agreement | H11: 46021 | I11: VNA.MSA.2023_-_Apex_Capital_Corp.docx | J11: Yes | K11: Yes | L11: 45656 | M11: ON-GOING | N11: =IFERROR(EDATE(L11,M11),"") | O11: =IFERROR(N11-TODAY(),"") | AK11: =IF(AGREEMENTS[[#This Row],[Days to Contract End]]<=90,"R",IF(AND(AGREEMENTS[[#This Row],[Days to Contract End]]<180),"A","G")) -> G
B12: Athenian Group, LLC | C12: =IFERROR(VLOOKUP(B12,'QB Consolidated Contacts'!$A$1:$F$333,6),"-") -> 0 | E12: VNA | F12: MSA | G12: Agreement | H12: 45034 | I12: VNA - MSA 2022 .VNA REVISED.20230329.docx | J12: Yes | L12: 45016 | M12: 36 | N12: =IFERROR(EDATE(L12,M12),"") -> 46112 | O12: =IFERROR(N12-TODAY(),"") -> 19 | AK12: =IF(AGREEMENTS[[#This Row],[Days to Contract End]]<=90,"R",IF(AND(AGREEMENTS[[#This Row],[Days to Contract End]]<180),"A","G")) -> R
B13: Athenian Group, LLC | C13: =IFERROR(VLOOKUP(B13,'QB Consolidated Contacts'!$A$1:$F$333,6),"-") -> 0 | E13: VNA | F13: NDA | G13: Agreement | H13: 44883 | I13: VNA -Athenian -MNDA November 2022.doc | J13: Yes | L13: 44883 | M13: 24 | N13: =IFERROR(EDATE(L13,M13),"") -> 45614 | O13: =IFERROR(N13-TODAY(),"") -> -479 | P13: No | AK13: =IF(AGREEMENTS[[#This Row],[Days to Contract End]]<=90,"R",IF(AND(AGREEMENTS[[#This Row],[Days to Contract End]]<180),"A","G")) -> R
B14: BMW | C14: =IFERROR(VLOOKUP(B14,'QB Consolidated Contacts'!$A$1:$F$333,6),"-") -> 0 | E14: VNA | F14: MSA | G14: Agreement | I14: Master Services Agreement | J14: No | N14: =IFERROR(EDATE(L14,M14),"") -> 0 | O14: =IFERROR(N14-TODAY(),"") -> -46093 | P14: Yes | R14: $5M | S14: $5M | T14: Statutory Limits | U14: $1M | AJ14: $1M | AK14: =IF(AGREEMENTS[[#This Row],[Days to Contract End]]<=90,"R",IF(AND(AGREEMENTS[[#This Row],[Days to Contract End]]<180),"A","G")) -> R | AL14: We assumed this client when we bought Sumner Technologies in 2018; I went through some of that stuff and can’t find anything.
B15: BMW | C15: =IFERROR(VLOOKUP(B15,'QB Consolidated Contacts'!$A$1:$F$333,6),"-") -> 0 | E15: VNA | F15: NDA | G15: Agreement | I15: Non-Disclosure Agreement | J15: No | N15: =IFERROR(EDATE(L15,M15),"") -> 0 | O15: =IFERROR(N15-TODAY(),"") -> -46093 | AK15: =IF(AGREEMENTS[[#This Row],[Days to Contract End]]<=90,"R",IF(AND(AGREEMENTS[[#This Row],[Days to Contract End]]<180),"A","G")) -> R
B16: CableOne | C16: =IFERROR(VLOOKUP(B16,'QB Consolidated Contacts'!$A$1:$F$333,6),"-") -> 0 | E16: VT | F16: MSA | G16: Agreement | I16: (SOW) Statement of Work with Cable One, Inc_ (667af9e7f9) (version 1) | J16: Yes | K16: No | L16: 45469 | N16: =IFERROR(EDATE(L16,M16),"") -> 45469 | O16: =IFERROR(N16-TODAY(),"") -> -624 | P16: - | Q16: Certificate Holder | R16: $2M | U16: $1M | Z16: $1M | AC16: S1M | AD16: S1M | AE16: $1M | AH16: $1M | AI16: $2M | AK16: =IF(AGREEMENTS[[#This Row],[Days to Contract End]]<=90,"R",IF(AND(AGREEMENTS[[#This Row],[Days to Contract End]]<180),"A","G")) -> R
B17: CACI | C17: =IFERROR(VLOOKUP(B17,'QB Consolidated Contacts'!$A$1:$F$333,6),"-") -> 0 | E17: VNA | F17: NDA | G17: Agreement | I17: CACI_Agreement.NDA.12022022 | J17: Yes | L17: 44897 | M17: 36 | N17: =IFERROR(EDATE(L17,M17),"") -> 45993 | O17: =IFERROR(N17-TODAY(),"") -> -100 | AK17: =IF(AGREEMENTS[[#This Row],[Days to Contract End]]<=90,"R",IF(AND(AGREEMENTS[[#This Row],[Days to Contract End]]<180),"A","G")) -> R
B18: CACI - LGS Labs | C18: =IFERROR(VLOOKUP(B18,'QB Consolidated Contacts'!$A$1:$F$333,6),"-") -> 0 | E18: VNA | F18: NDA | G18: Agreement | I18: Non-Disclosure Agreement | J18: Yes | L18: 44887 | M18: 36 | N18: =IFERROR(EDATE(L18,M18),"") -> 45983 | O18: =IFERROR(N18-TODAY(),"") -> -110 | P18: Yes | R18: $2M | S18: $1M | T18: $500K | AC18: $1M | AD18: $1M | AF18: $300K | AG18: $10K | AH18: $1M | AK18: =IF(AGREEMENTS[[#This Row],[Days to Contract End]]<=90,"R",IF(AND(AGREEMENTS[[#This Row],[Days to Contract End]]<180),"A","G")) -> R
B19: CACI - LGS Labs | C19: =IFERROR(VLOOKUP(B19,'QB Consolidated Contacts'!$A$1:$F$333,6),"-") -> 0 | F19: MSA | G19: Agreement | I19: Master Services Agreement | J19: No | L19: 26 | N19: =IFERROR(EDATE(L19,M19),"") -> 26 | O19: =IFERROR(N19-TODAY(),"") -> -46067 | AK19: =IF(AGREEMENTS[[#This Row],[Days to Contract End]]<=90,"R",IF(AND(AGREEMENTS[[#This Row],[Days to Contract End]]<180),"A","G")) -> R
B20: Captial Title of Texas | C20: =IFERROR(VLOOKUP(B20,'QB Consolidated Contacts'!$A$1:$F$333,6),"-") -> 0 | E20: VNA | F20: MSA | G20: Agreement | I20: Master Services Agreement | J20: Yes | L20: 44102 | M20: ON-GOING | N20: =IFERROR(EDATE(L20,M20),"") | O20: =IFERROR(N20-TODAY(),"") | P20: Yes | S20: S1M | AJ20: $100K | AK20: =IF(AGREEMENTS[[#This Row],[Days to Contract End]]<=90,"R",IF(AND(AGREEMENTS[[#This Row],[Days to Contract End]]<180),"A","G")) -> G
B21: Centene - [formerly Wellcare] - [formerly Meridian (Caidan)] | C21: =IFERROR(VLOOKUP(B21,'QB Consolidated Contacts'!$A$1:$F$333,6),"-") -> 0 | E21: VNA | F21: MSA | G21: Agreement | I21: PROC380 VISCOSITY NORTH AMERICA, MSA,AMD1_encrypted_.pdf | J21: Yes | K21: Yes | L21: 45491 | M21: 12 | N21: =IFERROR(EDATE(L21,M21),"")-10 -> 45846 | O21: =IFERROR(N21-TODAY(),"") -> -247 | AK21: =IF(AGREEMENTS[[#This Row],[Days to Contract End]]<=90,"R",IF(AND(AGREEMENTS[[#This Row],[Days to Contract End]]<180),"A","G")) -> R
B22: Civic Telehealth | C22: =IFERROR(VLOOKUP(B22,'QB Consolidated Contacts'!$A$1:$F$333,6),"-") -> 0 | E22: VNA | F22: NDA | G22: Agreement | I22: mNDA CTH Civic Telehealth.pdf | J22: Yes | K22: Yes | N22: =IFERROR(EDATE(L22,M22),"") -> 0 | O22: =IFERROR(N22-TODAY(),"") -> -46093 | AK22: =IF(AGREEMENTS[[#This Row],[Days to Contract End]]<=90,"R",IF(AND(AGREEMENTS[[#This Row],[Days to Contract End]]<180),"A","G")) -> R
B23: Clario | C23: =IFERROR(VLOOKUP(B23,'QB Consolidated Contacts'!$A$1:$F$333,6),"-") -> 0 | E23: VT | F23: MSA | G23: Agreement | I23: Master Services Agreement | J23: Yes | L23: 44869 | M23: 24 | N23: =IFERROR(EDATE(L23,M23),"") -> 45600 | O23: =IFERROR(N23-TODAY(),"") -> -493 | AK23: =IF(AGREEMENTS[[#This Row],[Days to Contract End]]<=90,"R",IF(AND(AGREEMENTS[[#This Row],[Days to Contract End]]<180),"A","G")) -> R | AL23: It appears that the redlines have not been resolved and there is no signed MSA currently in effect. Nonetheless, we do have an active PO.
B24: Clario | C24: =IFERROR(VLOOKUP(B24,'QB Consolidated Contacts'!$A$1:$F$333,6),"-") -> 0 | E24: VT | F24: NDA | G24: Agreement | I24: Non-Disclosure Agreement | J24: Yes | L24: 44778 | M24: =5*12 -> 60 | N24: =IFERROR(EDATE(L24,M24),"") -> 46604 | O24: =IFERROR(N24-TODAY(),"") -> 511 | AK24: =IF(AGREEMENTS[[#This Row],[Days to Contract End]]<=90,"R",IF(AND(AGREEMENTS[[#This Row],[Days to Contract End]]<180),"A","G")) -> G
B25: COE | C25: =IFERROR(VLOOKUP(B25,'QB Consolidated Contacts'!$A$1:$F$333,6),"-") -> 0 | E25: VNA | F25: MSA | G25: Agreement | I25: Master Services Agreement | J25: Yes | L25: 43089 | M25: ON-GOING | N25: =IFERROR(EDATE(L25,M25),"") | O25: =IFERROR(N25-TODAY(),"") | P25: Yes | R25: $1M | S25: $1M | V25: - | X25: - | Y25: - | AJ25: $100K | AK25: =IF(AGREEMENTS[[#This Row],[Days to Contract End]]<=90,"R",IF(AND(AGREEMENTS[[#This Row],[Days to Contract End]]<180),"A","G")) -> G
B26: College of American Pathologists (“CAP”) | C26: =IFERROR(VLOOKUP(B26,'QB Consolidated Contacts'!$A$1:$F$333,6),"-") -> 0 | F26: MSA | G26: Agreement | I26: PO 87781 Viscosity MASTER SERVICES AGREEMENT | N26: =IFERROR(EDATE(L26,M26),"") -> 0 | O26: =IFERROR(N26-TODAY(),"") -> -46093 | AK26: =IF(AGREEMENTS[[#This Row],[Days to Contract End]]<=90,"R",IF(AND(AGREEMENTS[[#This Row],[Days to Contract End]]<180),"A","G")) -> R
B27: Computex Technology Solutions | C27: =IFERROR(VLOOKUP(B27,'QB Consolidated Contacts'!$A$1:$F$333,6),"-") -> 0 | E27: VNA | F27: MSA | G27: Agreement | I27: Master Services Agreement | J27: Yes | L27: 44258 | M27: ON-GOING | N27: =IFERROR(EDATE(L27,M27),"") | O27: =IFERROR(N27-TODAY(),"") | P27: Yes | R27: $2M | S27: $1M | T27: $1M | V27: $5M | W27: $1M | Z27: $5M | AA27: $1M | AB27: $1M | AJ27: $1M | AK27: =IF(AGREEMENTS[[#This Row],[Days to Contract End]]<=90,"R",IF(AND(AGREEMENTS[[#This Row],[Days to Contract End]]<180),"A","G")) -> G
B28: Computex Technology Solutions | C28: =IFERROR(VLOOKUP(B28,'QB Consolidated Contacts'!$A$1:$F$333,6),"-") -> 0 | E28: VNA | F28: NDA | G28: Agreement | I28: Non-Disclosure Agreement | J28: Yes | L28: 44270 | M28: ON-GOING | N28: =IFERROR(EDATE(L28,M28),"") | O28: =IFERROR(N28-TODAY(),"") | P28: No | AK28: =IF(AGREEMENTS[[#This Row],[Days to Contract End]]<=90,"R",IF(AND(AGREEMENTS[[#This Row],[Days to Contract End]]<180),"A","G")) -> G | AL28: A Recipient’s duty to protect Confidential Information expires three (3) years from the date of any disclosure hereunder
B29: Cynet | C29: =IFERROR(VLOOKUP(B29,'QB Consolidated Contacts'!$A$1:$F$333,6),"-") -> 0 | N29: =IFERROR(EDATE(L29,M29),"") -> 0 | O29: =IFERROR(N29-TODAY(),"") -> -46093 | AK29: =IF(AGREEMENTS[[#This Row],[Days to Contract End]]<=90,"R",IF(AND(AGREEMENTS[[#This Row],[Days to Contract End]]<180),"A","G")) -> R
B30: Dominion Questar | C30: =IFERROR(VLOOKUP(B30,'QB Consolidated Contacts'!$A$1:$F$333,6),"-") -> 0 | E30: VNA | F30: Fifth Amendment Agreement | G30: Agreement | I30: New Agreement PO# 50104298; Old Agreement #6163-01A-57112 | J30: Yes | L30: 44779 | M30: ON-GOING | N30: =IFERROR(EDATE(L30,M30),"") | O30: =IFERROR(N30-TODAY(),"") | AK30: =IF(AGREEMENTS[[#This Row],[Days to Contract End]]<=90,"R",IF(AND(AGREEMENTS[[#This Row],[Days to Contract End]]<180),"A","G")) -> G
B31: Drill Tech Drilling & Shoring, Inc. | C31: =IFERROR(VLOOKUP(B31,'QB Consolidated Contacts'!$A$1:$F$333,6),"-") -> 0 | E31: VNA | F31: MSA | G31: Agreement | I31: VNA MSA (Drill Tech) - 07.18.2024.pdf | J31: Yes | K31: Yes | L31: 45491 | M31: ON-GOING | N31: =IFERROR(EDATE(L31,M31),"") | O31: =IFERROR(N31-TODAY(),"") | AK31: =IF(AGREEMENTS[[#This Row],[Days to Contract End]]<=90,"R",IF(AND(AGREEMENTS[[#This Row],[Days to Contract End]]<180),"A","G")) -> G
B32: Fleet Farm | C32: =IFERROR(VLOOKUP(B32,'QB Consolidated Contacts'!$A$1:$F$333,6),"-") -> 0 | E32: VT | F32: MSA | G32: Unknown | J32: No | N32: =IFERROR(EDATE(L32,M32),"") -> 0 | O32: =IFERROR(N32-TODAY(),"") -> -46093 | AK32: =IF(AGREEMENTS[[#This Row],[Days to Contract End]]<=90,"R",IF(AND(AGREEMENTS[[#This Row],[Days to Contract End]]<180),"A","G")) -> R
B33: Florida Realtors | C33: =IFERROR(VLOOKUP(B33,'QB Consolidated Contacts'!$A$1:$F$333,6),"-") -> 0 | E33: VT | F33: MSA | G33: Agreement | I33: Master Services Agreement | J33: Yes | L33: 44232 | M33: ON-GOING | N33: =IFERROR(EDATE(L33,M33),"") | O33: =IFERROR(N33-TODAY(),"") | P33: Yes | S33: $1M | AJ33: $100K | AK33: =IF(AGREEMENTS[[#This Row],[Days to Contract End]]<=90,"R",IF(AND(AGREEMENTS[[#This Row],[Days to Contract End]]<180),"A","G")) -> G
B34: Flowtrac | C34: =IFERROR(VLOOKUP(B34,'QB Consolidated Contacts'!$A$1:$F$333,6),"-") -> 0 | E34: VNA | F34: NDA | G34: Agreement | I34: Non-Disclosure Agreement | J34: Yes | K34: No | L34: 45061 | M34: 24 | N34: =IFERROR(EDATE(L34,M34),"") -> 45792 | O34: =IFERROR(N34-TODAY(),"") -> -301 | AK34: =IF(AGREEMENTS[[#This Row],[Days to Contract End]]<=90,"R",IF(AND(AGREEMENTS[[#This Row],[Days to Contract End]]<180),"A","G")) -> R
B35: FNF | C35: =IFERROR(VLOOKUP(B35,'QB Consolidated Contacts'!$A$1:$F$333,6),"-") -> 0 | E35: VNA | F35: MSA | G35: Agreement | I35: Master Services Agreement | J35: Yes | K35: Yes | L35: 43243 | M35: ON-GOING | N35: =IFERROR(EDATE(L35,M35),"") | O35: =IFERROR(N35-TODAY(),"") | AK35: =IF(AGREEMENTS[[#This Row],[Days to Contract End]]<=90,"R",IF(AND(AGREEMENTS[[#This Row],[Days to Contract End]]<180),"A","G")) -> G
B36: Follett Content Soultions LLC (SQL Server) | C36: =IFERROR(VLOOKUP(B36,'QB Consolidated Contacts'!$A$1:$F$333,6),"-") -> 0 | D36: Legal Agreement | E36: VT | F36: MBE_WBE Statement | G36: Agreement | I36: VT.MSA.Follett Content Solutions.27JAN2024 Follett Content Edits.FINAL.docx | J36: Yes | K36: Yes | L36: 45315 | M36: ON-GOING | N36: =IFERROR(EDATE(L36,M36),"") | O36: =IFERROR(N36-TODAY(),"") | S36: $1M | AJ36: $100k | AK36: =IF(AGREEMENTS[[#This Row],[Days to Contract End]]<=90,"R",IF(AND(AGREEMENTS[[#This Row],[Days to Contract End]]<180),"A","G")) -> G
B37: Follett Content Soultions LLC (SQL Server) | C37: =IFERROR(VLOOKUP(B37,'QB Consolidated Contacts'!$A$1:$F$333,6),"-") -> 0 | D37: Legal Agreement | E37: VT | F37: NDA | G37: Agreement | I37: VT.MNDA.Follett Content Solutions.24JAN2024 (002) Follett Comments FINAL.doc | J37: Yes | K37: Yes | L37: 45324 | M37: 24 | N37: =IFERROR(EDATE(L37,M37),"") -> 46055 | O37: =IFERROR(N37-TODAY(),"") -> -38 | AK37: =IF(AGREEMENTS[[#This Row],[Days to Contract End]]<=90,"R",IF(AND(AGREEMENTS[[#This Row],[Days to Contract End]]<180),"A","G")) -> R
B38: Follett School Solutions LLC (Oracle EBS) | C38: =IFERROR(VLOOKUP(B38,'QB Consolidated Contacts'!$A$1:$F$333,6),"-") -> 0 | D38: Legal Agreement | E38: VT | F38: MSA | G38: Agreement | I38: Master Services Agreement | J38: Yes | L38: 44732 | M38: ON-GOING | N38: =IFERROR(EDATE(L38,M38),"") | O38: =IFERROR(N38-TODAY(),"") | P38: Yes | S38: $1M | AJ38: $100K | AK38: =IF(AGREEMENTS[[#This Row],[Days to Contract End]]<=90,"R",IF(AND(AGREEMENTS[[#This Row],[Days to Contract End]]<180),"A","G")) -> G
B39: Follett School Solutions LLC (Oracle EBS) | C39: =IFERROR(VLOOKUP(B39,'QB Consolidated Contacts'!$A$1:$F$333,6),"-") -> 0 | D39: Legal Agreement | E39: VT | F39: NDA | G39: Agreement | I39: Non-Disclosure Agreement | J39: Yes | L39: 44749 | M39: 24 | N39: =IFERROR(EDATE(L39,M39),"") -> 45480 | O39: =IFERROR(N39-TODAY(),"") -> -613 | AK39: =IF(AGREEMENTS[[#This Row],[Days to Contract End]]<=90,"R",IF(AND(AGREEMENTS[[#This Row],[Days to Contract End]]<180),"A","G")) -> R
B40: Globalstar | C40: =IFERROR(VLOOKUP(B40,'QB Consolidated Contacts'!$A$1:$F$333,6),"-") -> 0 | E40: VNA | F40: MSA | G40: Agreement | I40: Master Services Agreement | J40: Yes | K40: Yes | L40: 45016 | M40: ON-GOING | N40: =IFERROR(EDATE(L40,M40),"") | O40: =IFERROR(N40-TODAY(),"") | AK40: =IF(AGREEMENTS[[#This Row],[Days to Contract End]]<=90,"R",IF(AND(AGREEMENTS[[#This Row],[Days to Contract End]]<180),"A","G")) -> G
B41: HCTRA | C41: =IFERROR(VLOOKUP(B41,'QB Consolidated Contacts'!$A$1:$F$333,6),"-") -> 0 | E41: VNA | F41: MSA | G41: Agreement | I41: Consulting Agreement | J41: Yes | L41: 43269 | M41: ON-GOING | N41: =IFERROR(EDATE(L41,M41),"") | O41: =IFERROR(N41-TODAY(),"") | AK41: =IF(AGREEMENTS[[#This Row],[Days to Contract End]]<=90,"R",IF(AND(AGREEMENTS[[#This Row],[Days to Contract End]]<180),"A","G")) -> G | AL41: Notwithstanding the foregoing, if this Agreement terminates or is terminated while one or more Project Addenda (as defined in paragraph 2 below) remain outstanding, the terms of this Agreement shall continue to govern each outstanding Project Addendum, and the entire Agreement shall be deemed finally terminated only upon termination of all outstanding Project Addenda, or completion of the work thereunder.
B42: HRL | C42: =IFERROR(VLOOKUP(B42,'QB Consolidated Contacts'!$A$1:$F$333,6),"-") -> 0 | E42: VNA | F42: CSA | G42: Agreement | I42: Signed | J42: Yes | L42: 44301 | M42: 12 | N42: =IFERROR(EDATE(L42,M42),"") -> 44666 | O42: =IFERROR(N42-TODAY(),"") -> -1427 | AK42: =IF(AGREEMENTS[[#This Row],[Days to Contract End]]<=90,"R",IF(AND(AGREEMENTS[[#This Row],[Days to Contract End]]<180),"A","G")) -> R
B43: IdenTrust | C43: =IFERROR(VLOOKUP(B43,'QB Consolidated Contacts'!$A$1:$F$333,6),"-") -> 0 | E43: VNA | F43: MSA | G43: Agreement | I43: Master Services Agreement | J43: Yes | K43: No | L43: 43301 | M43: ON-GOING | N43: =IFERROR(EDATE(L43,M43),"") | O43: =IFERROR(N43-TODAY(),"") | AK43: =IF(AGREEMENTS[[#This Row],[Days to Contract End]]<=90,"R",IF(AND(AGREEMENTS[[#This Row],[Days to Contract End]]<180),"A","G")) -> G
B44: InComm | C44: =IFERROR(VLOOKUP(B44,'QB Consolidated Contacts'!$A$1:$F$333,6),"-") -> 0 | F44: NDA | G44: Agreement | I44: 2021-04-13.Mutual Nondisclosure Agreement, Viscosity North America, Inc (1).pdf | J44: Yes | L44: 44299 | M44: 36 | N44: =IFERROR(EDATE(L44,M44),"") -> 45395 | O44: =IFERROR(N44-TODAY(),"") -> -698 | AK44: =IF(AGREEMENTS[[#This Row],[Days to Contract End]]<=90,"R",IF(AND(AGREEMENTS[[#This Row],[Days to Contract End]]<180),"A","G")) -> R
B45: InComm | C45: =IFERROR(VLOOKUP(B45,'QB Consolidated Contacts'!$A$1:$F$333,6),"-") -> 0 | E45: VT | F45: MSA | G45: Agreement | I45: 2021-05-10.Executed Viscosity MSA Agreement.pdf | J45: Yes | L45: 44326 | M45: 12 | N45: =IFERROR(EDATE(L45,M45),"") -> 44691 | O45: =IFERROR(N45-TODAY(),"") -> -1402 | AK45: =IF(AGREEMENTS[[#This Row],[Days to Contract End]]<=90,"R",IF(AND(AGREEMENTS[[#This Row],[Days to Contract End]]<180),"A","G")) -> R | AL45: Term. The Term of the Agreement is hereby extended for one (1) year beginning on May 10, 2021 and concluding on May 9, 2022 (“Term”). Thereafter, the Agreement may be extended by written agreement of the parties.
B46: Incorta | C46: =IFERROR(VLOOKUP(B46,'QB Consolidated Contacts'!$A$1:$F$333,6),"-") -> 0 | D46: Infrastructure | E46: VNA | F46: MCSA | G46: Agreement | I46: NCORTA.VNA.MCSA.2023.docx | J46: Yes | K46: Yes | L46: 45113 | N46: =IFERROR(EDATE(L46,M46),"") -> 45113 | O46: =IFERROR(N46-TODAY(),"") -> -980 | AK46: =IF(AGREEMENTS[[#This Row],[Days to Contract End]]<=90,"R",IF(AND(AGREEMENTS[[#This Row],[Days to Contract End]]<180),"A","G")) -> R
B47: Inficon | C47: =IFERROR(VLOOKUP(B47,'QB Consolidated Contacts'!$A$1:$F$333,6),"-") -> 0 | E47: VNA | F47: NDA | G47: Agreement | I47: Complete_with_DocuSign_INFICON_NDA_March_202 (1).pdf | N47: =IFERROR(EDATE(L47,M47),"") -> 0 | O47: =IFERROR(N47-TODAY(),"") -> -46093 | AK47: =IF(AGREEMENTS[[#This Row],[Days to Contract End]]<=90,"R",IF(AND(AGREEMENTS[[#This Row],[Days to Contract End]]<180),"A","G")) -> R
B48: IN-N-Out Burger | C48: =IFERROR(VLOOKUP(B48,'QB Consolidated Contacts'!$A$1:$F$333,6),"-") -> 0 | E48: VNA | F48: NDA | G48: Agreement | I48: Non-Disclosure Agreement | J48: No | N48: =IFERROR(EDATE(L48,M48),"") -> 0 | O48: =IFERROR(N48-TODAY(),"") -> -46093 | AK48: =IF(AGREEMENTS[[#This Row],[Days to Contract End]]<=90,"R",IF(AND(AGREEMENTS[[#This Row],[Days to Contract End]]<180),"A","G")) -> R
B49: InterMetro Industries Corporation | C49: =IFERROR(VLOOKUP(B49,'QB Consolidated Contacts'!$A$1:$F$333,6),"-") -> 0 | G49: Unknown | I49: Oracle BigCommerce Integration | J49: No | N49: =IFERROR(EDATE(L49,M49),"") -> 0 | O49: =IFERROR(N49-TODAY(),"") -> -46093 | R49: - | S49: - | V49: - | X49: - | Y49: - | AJ49: - | AK49: =IF(AGREEMENTS[[#This Row],[Days to Contract End]]<=90,"R",IF(AND(AGREEMENTS[[#This Row],[Days to Contract End]]<180),"A","G")) -> R
B50: IQNavigator | C50: =IFERROR(VLOOKUP(B50,'QB Consolidated Contacts'!$A$1:$F$333,6),"-") -> 0 | E50: VNA | F50: NDA | G50: Agreement | I50: Non-Disclosure Agreement | J50: Yes | L50: 43041 | M50: ON-GOING | N50: =IFERROR(EDATE(L50,M50),"") | O50: =IFERROR(N50-TODAY(),"") | AK50: =IF(AGREEMENTS[[#This Row],[Days to Contract End]]<=90,"R",IF(AND(AGREEMENTS[[#This Row],[Days to Contract End]]<180),"A","G")) -> G | AL50: Agreement prevails unless there is written agreement of both parties or 30 days prior written notice provided no outstanding business transactions
B51: IQNavigator | C51: =IFERROR(VLOOKUP(B51,'QB Consolidated Contacts'!$A$1:$F$333,6),"-") -> 0 | E51: VNA | F51: MSA | G51: Agreement | I51: Master Services Agreement | J51: Yes | L51: 43066 | M51: ON-GOING | N51: =IFERROR(EDATE(L51,M51),"") | O51: =IFERROR(N51-TODAY(),"") | AK51: =IF(AGREEMENTS[[#This Row],[Days to Contract End]]<=90,"R",IF(AND(AGREEMENTS[[#This Row],[Days to Contract End]]<180),"A","G")) -> G | AL51: Article 10 shall survive any termination or cancellation of this Agreement.
B52: Jiffy Lube | C52: =IFERROR(VLOOKUP(B52,'QB Consolidated Contacts'!$A$1:$F$333,6),"-") -> 0 | E52: VNA | F52: MSA | G52: Agreement | I52: Master Services Agreement | J52: No | L52: 44531 | M52: n/a | N52: =IFERROR(EDATE(L52,M52),"") | O52: =IFERROR(N52-TODAY(),"") | P52: Yes | S52: $1M | AJ52: $100K | AK52: =IF(AGREEMENTS[[#This Row],[Days to Contract End]]<=90,"R",IF(AND(AGREEMENTS[[#This Row],[Days to Contract End]]<180),"A","G")) -> G
B53: Just Born | C53: =IFERROR(VLOOKUP(B53,'QB Consolidated Contacts'!$A$1:$F$333,6),"-") -> 0 | D53: Infrastructure | E53: VNA | F53: MSA | G53: Agreement | I53: VNA.MSA.Just Born.June 2023.docx | J53: Yes | K53: Yes | L53: 45103 | M53: 12 | N53: =IFERROR(EDATE(L53,M53),"") -> 45469 | O53: =IFERROR(N53-TODAY(),"") -> -624 | AK53: =IF(AGREEMENTS[[#This Row],[Days to Contract End]]<=90,"R",IF(AND(AGREEMENTS[[#This Row],[Days to Contract End]]<180),"A","G")) -> R | AL53: Automatic Renewal after 12 months -
B54: Lamar Trailer | C54: =IFERROR(VLOOKUP(B54,'QB Consolidated Contacts'!$A$1:$F$333,6),"-") -> 0 | E54: VNA | F54: MSA | G54: Agreement | I54: LAMAR TRAILERS.VNA.MSA.2023.docx | J54: Yes | K54: Yes | L54: 45161 | M54: ON-GOING | N54: =IFERROR(EDATE(L54,M54),"") | O54: =IFERROR(N54-TODAY(),"") | AK54: =IF(AGREEMENTS[[#This Row],[Days to Contract End]]<=90,"R",IF(AND(AGREEMENTS[[#This Row],[Days to Contract End]]<180),"A","G")) -> G
B55: Lamar Trailer | C55: =IFERROR(VLOOKUP(B55,'QB Consolidated Contacts'!$A$1:$F$333,6),"-") -> 0 | E55: VNA | F55: NDA | G55: Agreement | I55: LAMAR TRAILERS.VNA.MNDA.2023.docx | J55: Yes | K55: Yes | L55: 45161 | M55: 24 | N55: =IFERROR(EDATE(L55,M55),"") -> 45892 | O55: =IFERROR(N55-TODAY(),"") -> -201 | AK55: =IF(AGREEMENTS[[#This Row],[Days to Contract End]]<=90,"R",IF(AND(AGREEMENTS[[#This Row],[Days to Contract End]]<180),"A","G")) -> R
B56: LGS Labs | C56: =IFERROR(VLOOKUP(B56,'QB Consolidated Contacts'!$A$1:$F$333,6),"-") -> 0 | E56: VNA | F56: NDA | G56: Agreement | I56: Non-Disclosure Agreement | J56: Yes | L56: 44887 | M56: 36 | N56: =IFERROR(EDATE(L56,M56),"") -> 45983 | O56: =IFERROR(N56-TODAY(),"") -> -110 | AK56: =IF(AGREEMENTS[[#This Row],[Days to Contract End]]<=90,"R",IF(AND(AGREEMENTS[[#This Row],[Days to Contract End]]<180),"A","G")) -> R
B57: Mainline - KLR Technology | C57: =IFERROR(VLOOKUP(B57,'QB Consolidated Contacts'!$A$1:$F$333,6),"-") -> 0 | G57: Unknown | J57: No | N57: =IFERROR(EDATE(L57,M57),"") -> 0 | O57: =IFERROR(N57-TODAY(),"") -> -46093 | AK57: =IF(AGREEMENTS[[#This Row],[Days to Contract End]]<=90,"R",IF(AND(AGREEMENTS[[#This Row],[Days to Contract End]]<180),"A","G")) -> R
B58: Medica | C58: =IFERROR(VLOOKUP(B58,'QB Consolidated Contacts'!$A$1:$F$333,6),"-") -> 0 | E58: VNA | F58: MSA | G58: Agreement | I58: 2024 05 22 Viscosity MSA.pdf | J58: Yes | K58: Yes | L58: 45434 | M58: ON-GOING | N58: =IFERROR(EDATE(L58,M58),"") | O58: =IFERROR(N58-TODAY(),"") | P58: Yes | R58: $2M | U58: $2M | X58: $3M | Y58: $3M | Z58: $3M | AH58: $2M | AI58: $2M | AJ58: $2M | AK58: =IF(AGREEMENTS[[#This Row],[Days to Contract End]]<=90,"R",IF(AND(AGREEMENTS[[#This Row],[Days to Contract End]]<180),"A","G")) -> G
B59: Merit Energy | C59: =IFERROR(VLOOKUP(B59,'QB Consolidated Contacts'!$A$1:$F$333,6),"-") -> 0 | F59: MSA | J59: No | N59: =IFERROR(EDATE(L59,M59),"") -> 0 | O59: =IFERROR(N59-TODAY(),"") -> -46093 | AK59: =IF(AGREEMENTS[[#This Row],[Days to Contract End]]<=90,"R",IF(AND(AGREEMENTS[[#This Row],[Days to Contract End]]<180),"A","G")) -> R
B60: Merit Medical Systems | C60: VNA | D60: Infrastructure | E60: SOW | F60: MSA | G60: Agreement | I60: Signed MSA for Oracle Security Assessment | J60: Yes | K60: No | N60: - | Q60: - | R60: - | S60: - | AK60: =IF(AGREEMENTS[[#This Row],[Days to Contract End]]<=90,"R",IF(AND(AGREEMENTS[[#This Row],[Days to Contract End]]<180),"A","G")) -> R
B61: Morris-Shea Bridge Company Inc. | C61: =IFERROR(VLOOKUP(B61,'QB Consolidated Contacts'!$A$1:$F$333,6),"-") -> 0 | E61: VNA | F61: NDA | G61: Agreement | I61: NDA Signed | J61: Yes | L61: 42411 | M61: 24 | N61: =IFERROR(EDATE(L61,M61),"") -> 43142 | O61: =IFERROR(N61-TODAY(),"") -> -2951 | AK61: =IF(AGREEMENTS[[#This Row],[Days to Contract End]]<=90,"R",IF(AND(AGREEMENTS[[#This Row],[Days to Contract End]]<180),"A","G")) -> R
B62: Morris-Shea Bridge Company Inc. | C62: =IFERROR(VLOOKUP(B62,'QB Consolidated Contacts'!$A$1:$F$333,6),"-") -> 0 | E62: VNA | F62: MSA | G62: Agreement | I62: Master Services Agreement | J62: No | N62: =IFERROR(EDATE(L62,M62),"") -> 0 | O62: =IFERROR(N62-TODAY(),"") -> -46093 | AK62: =IF(AGREEMENTS[[#This Row],[Days to Contract End]]<=90,"R",IF(AND(AGREEMENTS[[#This Row],[Days to Contract End]]<180),"A","G")) -> R
B63: Morris-Shea Bridge Company Inc. | C63: =IFERROR(VLOOKUP(B63,'QB Consolidated Contacts'!$A$1:$F$333,6),"-") -> 0 | G63: Unknown | I63: MSB - Reboot Project 2022 | J63: No | N63: =IFERROR(EDATE(L63,M63),"") -> 0 | O63: =IFERROR(N63-TODAY(),"") -> -46093 | R63: - | S63: - | V63: - | X63: - | Y63: - | AJ63: - | AK63: =IF(AGREEMENTS[[#This Row],[Days to Contract End]]<=90,"R",IF(AND(AGREEMENTS[[#This Row],[Days to Contract End]]<180),"A","G")) -> R | AL63: Restart of project/direction change
B64: MountainWest Pipleline, LLC | C64: =IFERROR(VLOOKUP(B64,'QB Consolidated Contacts'!$A$1:$F$333,6),"-") -> 0 | E64: VNA | F64: MSA | G64: Agreement | I64: Master Services Agreement | J64: Yes | K64: Yes | L64: 44927 | M64: ON-GOING | N64: =IFERROR(EDATE(L64,M64),"") | O64: =IFERROR(N64-TODAY(),"") | P64: Yes | R64: $1M | S64: $100K | AK64: =IF(AGREEMENTS[[#This Row],[Days to Contract End]]<=90,"R",IF(AND(AGREEMENTS[[#This Row],[Days to Contract End]]<180),"A","G")) -> G
B65: MountainWest Pipleline, LLC | C65: =IFERROR(VLOOKUP(B65,'QB Consolidated Contacts'!$A$1:$F$333,6),"-") -> 0 | E65: VNA | F65: NDA | G65: Agreement | I65: VNA -MNDA .MountainWest November 2022 | J65: Yes | K65: Yes | N65: =IFERROR(EDATE(L65,M65),"") -> 0 | O65: =IFERROR(N65-TODAY(),"") -> -46093 | AK65: =IF(AGREEMENTS[[#This Row],[Days to Contract End]]<=90,"R",IF(AND(AGREEMENTS[[#This Row],[Days to Contract End]]<180),"A","G")) -> R
B66: National Mango Board | C66: =IFERROR(VLOOKUP(B66,'QB Consolidated Contacts'!$A$1:$F$333,6),"-") -> 0 | E66: VT | F66: CSA | G66: Agreement | I66: MANGO VOLUME & INVENTORY SYSTEM CONSULTANT AGREEMENT | J66: Yes | K66: Yes | L66: 45031 | M66: ON-GOING | N66: =IFERROR(EDATE(L66,M66),"") | O66: =IFERROR(N66-TODAY(),"") | P66: Yes | R66: $1M | S66: $100K | AK66: =IF(AGREEMENTS[[#This Row],[Days to Contract End]]<=90,"R",IF(AND(AGREEMENTS[[#This Row],[Days to Contract End]]<180),"A","G")) -> G
B67: Nationwide Mutal Insurance Company | C67: =IFERROR(VLOOKUP(#REF!,'QB Consolidated Contacts'!$A$1:$F$333,6),"-") -> - | D67: Infrastructure | E67: VNA | F67: Limited Services Agreement | G67: Agreement | I67: Limited Services Agreement FINAL 20230519.docx | J67: Yes | K67: Yes | L67: 45071 | N67: 45291 | O67: =IFERROR(N67-TODAY(),"") -> -802 | AK67: =IF(AGREEMENTS[[#This Row],[Days to Contract End]]<=90,"R",IF(AND(AGREEMENTS[[#This Row],[Days to Contract End]]<180),"A","G")) -> R
B68: Neiman Marcus | C68: =IFERROR(VLOOKUP(B68,'QB Consolidated Contacts'!$A$1:$F$333,6),"-") -> 0 | E68: VT | F68: MSA | G68: Agreement | I68: Master Services Agreement | J68: Yes | L68: 44713 | M68: ON-GOING | N68: =IFERROR(EDATE(L68,M68),"") | O68: =IFERROR(N68-TODAY(),"") | R68: $2M | S68: $1M | AK68: =IF(AGREEMENTS[[#This Row],[Days to Contract End]]<=90,"R",IF(AND(AGREEMENTS[[#This Row],[Days to Contract End]]<180),"A","G")) -> G
B69: Neiman Marcus | C69: =IFERROR(VLOOKUP(B69,'QB Consolidated Contacts'!$A$1:$F$333,6),"-") -> 0 | E69: VNA | F69: NDA | G69: Agreement | I69: Non-Disclosure Agreement | J69: Yes | L69: 43003 | M69: ON-GOING | N69: =IFERROR(EDATE(L69,M69),"") | O69: =IFERROR(N69-TODAY(),"") | AK69: =IF(AGREEMENTS[[#This Row],[Days to Contract End]]<=90,"R",IF(AND(AGREEMENTS[[#This Row],[Days to Contract End]]<180),"A","G")) -> G
B70: NeoSystems LLC | C70: =IFERROR(VLOOKUP(B70,'QB Consolidated Contacts'!$A$1:$F$333,6),"-") -> 0 | E70: VNA | F70: MSA | G70: Agreement | I70: Master Services Agreement | J70: Yes | K70: No | L70: 43240 | M70: ON-GOING | N70: =IFERROR(EDATE(L70,M70),"") | O70: =IFERROR(N70-TODAY(),"") | P70: Yes | R70: $1M | S70: $100K | AK70: =IF(AGREEMENTS[[#This Row],[Days to Contract End]]<=90,"R",IF(AND(AGREEMENTS[[#This Row],[Days to Contract End]]<180),"A","G")) -> G
B71: NGCIS - Natural Gas Compression Systems, INC. | C71: =IFERROR(VLOOKUP(B71,'QB Consolidated Contacts'!$A$1:$F$333,6),"-") -> 0 | D71: Development | E71: VNA | F71: MSA | G71: Professional Services | I71: VNA MSA - Originally included in Enterprise Assest Management SOW | J71: Yes | K71: Yes | L71: 45125 | N71: =IFERROR(EDATE(L71,M71),"") -> 45125 | O71: =IFERROR(N71-TODAY(),"") -> -968 | AK71: =IF(AGREEMENTS[[#This Row],[Days to Contract End]]<=90,"R",IF(AND(AGREEMENTS[[#This Row],[Days to Contract End]]<180),"A","G")) -> R | AL71: MSA and SOW signed under one document in DocuSign
B72: PathAI/Poplar Healthcare | C72: =IFERROR(VLOOKUP(B72,'QB Consolidated Contacts'!$A$1:$F$333,6),"-") -> 0 | E72: VNA | F72: MSA | G72: Agreement | I72: Master Services Agreement | J72: Yes | L72: 44701 | M72: ON-GOING | N72: =IFERROR(EDATE(L72,M72),"") | O72: =IFERROR(N72-TODAY(),"") | AK72: =IF(AGREEMENTS[[#This Row],[Days to Contract End]]<=90,"R",IF(AND(AGREEMENTS[[#This Row],[Days to Contract End]]<180),"A","G")) -> G
B73: PathAI/Poplar Healthcare | C73: =IFERROR(VLOOKUP(B73,'QB Consolidated Contacts'!$A$1:$F$333,6),"-") -> 0 | E73: VNA | F73: MSA | G73: Agreement | I73: MSA-VNA.Poplar.2022.FINAL.docx | J73: Yes | K73: Yes | L73: 44701 | M73: ON-GOING | N73: =IFERROR(EDATE(L73,M73),"") | O73: =IFERROR(N73-TODAY(),"") | P73: Yes | R73: $1M | S73: $100K | AK73: =IF(AGREEMENTS[[#This Row],[Days to Contract End]]<=90,"R",IF(AND(AGREEMENTS[[#This Row],[Days to Contract End]]<180),"A","G")) -> G
B74: PathAI/Poplar Healthcare | C74: =IFERROR(VLOOKUP(B74,'QB Consolidated Contacts'!$A$1:$F$333,6),"-") -> 0 | E74: VNA | F74: HIPAA | G74: Agreement | I74: Business Associate Agreement | J74: Yes | K74: Yes | L74: N/A | M74: ON-GOING | N74: =IFERROR(EDATE(L74,M74),"") | O74: =IFERROR(N74-TODAY(),"") | AK74: =IF(AGREEMENTS[[#This Row],[Days to Contract End]]<=90,"R",IF(AND(AGREEMENTS[[#This Row],[Days to Contract End]]<180),"A","G")) -> G
B75: Paychex | C75: =IFERROR(VLOOKUP(B75,'QB Consolidated Contacts'!$A$1:$F$333,6),"-") -> 0 | E75: VNA | F75: NDA | G75: Agreement | I75: Paychex mNDA Signed.pdf | J75: Yes | K75: No | L75: 43843 | M75: ON-GOING | N75: =IFERROR(EDATE(L75,M75),"") | O75: =IFERROR(N75-TODAY(),"") | AK75: =IF(AGREEMENTS[[#This Row],[Days to Contract End]]<=90,"R",IF(AND(AGREEMENTS[[#This Row],[Days to Contract End]]<180),"A","G")) -> G
B76: Paychex | C76: =IFERROR(VLOOKUP(B76,'QB Consolidated Contacts'!$A$1:$F$333,6),"-") -> 0 | E76: VNA | F76: MSA | G76: Agreement | I76: CNTR0030595 Viscosity Professional Services Agreement _LNP_PCXPSI_FINAL signed.pdf | J76: Yes | K76: No | L76: 43860 | M76: ON-GOING | N76: =IFERROR(EDATE(L76,M76),"") | O76: =IFERROR(N76-TODAY(),"") | AK76: =IF(AGREEMENTS[[#This Row],[Days to Contract End]]<=90,"R",IF(AND(AGREEMENTS[[#This Row],[Days to Contract End]]<180),"A","G")) -> G
B77: Photon Leap Technologies, LLC | C77: =IFERROR(VLOOKUP(B77,'QB Consolidated Contacts'!$A$1:$F$333,6),"-") -> 0 | E77: VNA | F77: NDA | G77: Agreement | H77: 45821 | I77: NDA VISCOSITY AND PHOTON LEAP CK | J77: Yes | K77: Yes | N77: =IFERROR(EDATE(L77,M77),"") -> 0 | O77: =IFERROR(N77-TODAY(),"") -> -46093 | AK77: =IF(AGREEMENTS[[#This Row],[Days to Contract End]]<=90,"R",IF(AND(AGREEMENTS[[#This Row],[Days to Contract End]]<180),"A","G")) -> R
B78: Power Design | C78: =IFERROR(VLOOKUP(B78,'QB Consolidated Contacts'!$A$1:$F$333,6),"-") -> 0 | E78: VNA | F78: NDA | G78: Agreement | I78: Signed | J78: Yes | L78: 44825 | M78: ON-GOING | N78: =IFERROR(EDATE(L78,M78),"") | O78: =IFERROR(N78-TODAY(),"") | P78: No | AK78: =IF(AGREEMENTS[[#This Row],[Days to Contract End]]<=90,"R",IF(AND(AGREEMENTS[[#This Row],[Days to Contract End]]<180),"A","G")) -> G
B79: Prestolite Electric Inc. | C79: =IFERROR(VLOOKUP(B79,'QB Consolidated Contacts'!$A$1:$F$333,6),"-") -> 0 | E79: VT | G79: Unknown | J79: No | N79: =IFERROR(EDATE(L79,M79),"") -> 0 | O79: =IFERROR(N79-TODAY(),"") -> -46093 | AK79: =IF(AGREEMENTS[[#This Row],[Days to Contract End]]<=90,"R",IF(AND(AGREEMENTS[[#This Row],[Days to Contract End]]<180),"A","G")) -> R
B80: PruTech (FDNY) | C80: =IFERROR(VLOOKUP(B80,'QB Consolidated Contacts'!$A$1:$F$333,6),"-") -> 0 | E80: VNA | F80: MSA | N80: =IFERROR(EDATE(L80,M80),"") -> 0 | O80: =IFERROR(N80-TODAY(),"") -> -46093 | AK80: =IF(AGREEMENTS[[#This Row],[Days to Contract End]]<=90,"R",IF(AND(AGREEMENTS[[#This Row],[Days to Contract End]]<180),"A","G")) -> R
B81: Quest | C81: =IFERROR(VLOOKUP(B81,'QB Consolidated Contacts'!$A$1:$F$333,6),"-") -> 0 | E81: VNA | F81: MSA | G81: Agreement | I81: Subcontractor Agreement | J81: No | N81: =IFERROR(EDATE(L81,M81),"") -> 0 | O81: =IFERROR(N81-TODAY(),"") -> -46093 | AK81: =IF(AGREEMENTS[[#This Row],[Days to Contract End]]<=90,"R",IF(AND(AGREEMENTS[[#This Row],[Days to Contract End]]<180),"A","G")) -> R
B82: Quest - San Diego County Sheriffs Department | C82: =IFERROR(VLOOKUP(B82,'QB Consolidated Contacts'!$A$1:$F$333,6),"-") -> 0 | G82: Unknown | I82: SAN DIEGO COUNTY SHERIFFS DEPARTMENT | J82: No | N82: =IFERROR(EDATE(L82,M82),"") -> 0 | O82: =IFERROR(N82-TODAY(),"") -> -46093 | R82: - | S82: - | V82: - | X82: - | Y82: - | AJ82: - | AK82: =IF(AGREEMENTS[[#This Row],[Days to Contract End]]<=90,"R",IF(AND(AGREEMENTS[[#This Row],[Days to Contract End]]<180),"A","G")) -> R | AL82: Viscosity will provide technical direction, roadmap and implementation expertise for Inovio/Nab SharePlex implementation to set up replication between the data centers in an active/activeconfiguration
B83: R&L Carriers | C83: =IFERROR(VLOOKUP(B83,'QB Consolidated Contacts'!$A$1:$F$333,6),"-") -> 0 | E83: VNA | F83: MSA | G83: Agreement | H83: 44994 | I83: Viscosity Master Services Agreement.FINAL.docx.pdf | J83: Yes | L83: 44973 | M83: ON-GOING | N83: =IFERROR(EDATE(L83,M83),"") | O83: =IFERROR(N83-TODAY(),"") | AK83: =IF(AGREEMENTS[[#This Row],[Days to Contract End]]<=90,"R",IF(AND(AGREEMENTS[[#This Row],[Days to Contract End]]<180),"A","G")) -> G
B84: R&L Carriers | C84: =IFERROR(VLOOKUP(B84,'QB Consolidated Contacts'!$A$1:$F$333,6),"-") -> 0 | E84: VNA | F84: NDA | G84: Agreement | I84: Mutual NDA for Oracle DB Health Check _ViscosityNA | J84: No | L84: 44935 | M84: n/a | N84: =IFERROR(EDATE(L84,M84),"") | O84: =IFERROR(N84-TODAY(),"") | AK84: =IF(AGREEMENTS[[#This Row],[Days to Contract End]]<=90,"R",IF(AND(AGREEMENTS[[#This Row],[Days to Contract End]]<180),"A","G")) -> G
B85: Record Deposition Service (RDS) | C85: =IFERROR(VLOOKUP(B85,'QB Consolidated Contacts'!$A$1:$F$333,6),"-") -> 0 | F85: NDA | G85: Agreement | I85: Non-Disclosure Agreement | J85: Yes | L85: 43431 | M85: ON-GOING | N85: =IFERROR(EDATE(L85,M85),"") | O85: =IFERROR(N85-TODAY(),"") | AK85: =IF(AGREEMENTS[[#This Row],[Days to Contract End]]<=90,"R",IF(AND(AGREEMENTS[[#This Row],[Days to Contract End]]<180),"A","G")) -> G
B86: Record Deposition Service (RDS) | C86: =IFERROR(VLOOKUP(B86,'QB Consolidated Contacts'!$A$1:$F$333,6),"-") -> 0 | E86: VNA | F86: MSA | G86: Agreement | I86: Master Services Agreement | J86: Yes | L86: 43435 | M86: ON-GOING | N86: =IFERROR(EDATE(L86,M86),"") | O86: =IFERROR(N86-TODAY(),"") | AK86: =IF(AGREEMENTS[[#This Row],[Days to Contract End]]<=90,"R",IF(AND(AGREEMENTS[[#This Row],[Days to Contract End]]<180),"A","G")) -> G
B87: Region 10 | C87: =IFERROR(VLOOKUP(B87,'QB Consolidated Contacts'!$A$1:$F$333,6),"-") -> 0 | G87: Professional Services | I87: Applicant Tracking System | N87: =IFERROR(EDATE(L87,M87),"") -> 0 | O87: =IFERROR(N87-TODAY(),"") -> -46093 | AK87: =IF(AGREEMENTS[[#This Row],[Days to Contract End]]<=90,"R",IF(AND(AGREEMENTS[[#This Row],[Days to Contract End]]<180),"A","G")) -> R
B88: Region 10 | C88: =IFERROR(VLOOKUP(B88,'QB Consolidated Contacts'!$A$1:$F$333,6),"-") -> 0 | G88: Professional Services | I88: Oracle Cloud Infrastructure- Infrastructure Support and Maintenance | N88: =IFERROR(EDATE(L88,M88),"") -> 0 | O88: =IFERROR(N88-TODAY(),"") -> -46093 | AK88: =IF(AGREEMENTS[[#This Row],[Days to Contract End]]<=90,"R",IF(AND(AGREEMENTS[[#This Row],[Days to Contract End]]<180),"A","G")) -> R
B89: RIA - Nationwide | C89: =IFERROR(VLOOKUP(B89,'QB Consolidated Contacts'!$A$1:$F$333,6),"-") -> 0 | E89: VNA | F89: Limited Services Agreement | G89: Agreement | I89: Limited Services Agreement | J89: Yes | K89: Yes | L89: 44986 | M89: 9 | N89: =IFERROR(EOMONTH(L89,M89),"") -> 45291 | O89: =IFERROR(N89-TODAY(),"") -> -802 | P89: Yes | AK89: =IF(AGREEMENTS[[#This Row],[Days to Contract End]]<=90,"R",IF(AND(AGREEMENTS[[#This Row],[Days to Contract End]]<180),"A","G")) -> R
B90: Sanofi | C90: =IFERROR(VLOOKUP(B90,'QB Consolidated Contacts'!$A$1:$F$333,6),"-") -> 0 | E90: VNA | F90: NDA | G90: Agreement | I90: Non-Disclosure Agreement | J90: Yes | L90: 44966 | N90: =IFERROR(EDATE(L90,M90),"") -> 44966 | O90: =IFERROR(N90-TODAY(),"") -> -1127 | AK90: =IF(AGREEMENTS[[#This Row],[Days to Contract End]]<=90,"R",IF(AND(AGREEMENTS[[#This Row],[Days to Contract End]]<180),"A","G")) -> R
B91: Saracen Energy | C91: =IFERROR(VLOOKUP(B91,'QB Consolidated Contacts'!$A$1:$F$333,6),"-") -> 0 | E91: VT | F91: MSA | G91: Agreement | I91: Master Services Agreement | J91: Yes | L91: 44866 | M91: ON-GOING | N91: =IFERROR(EDATE(L91,M91),"") | O91: =IFERROR(N91-TODAY(),"") | P91: Yes | AK91: =IF(AGREEMENTS[[#This Row],[Days to Contract End]]<=90,"R",IF(AND(AGREEMENTS[[#This Row],[Days to Contract End]]<180),"A","G")) -> G
B92: Saracen Energy | C92: =IFERROR(VLOOKUP(B92,'QB Consolidated Contacts'!$A$1:$F$333,6),"-") -> 0 | E92: VT | F92: NDA | G92: Agreement | I92: Non-Disclosure Agreement | J92: Yes | L92: 44867 | M92: 24 | N92: =IFERROR(EDATE(L92,M92),"") -> 45598 | O92: =IFERROR(N92-TODAY(),"") -> -495 | AK92: =IF(AGREEMENTS[[#This Row],[Days to Contract End]]<=90,"R",IF(AND(AGREEMENTS[[#This Row],[Days to Contract End]]<180),"A","G")) -> R
B93: Savantage Financial Services, Inc. d.b.a. Savantage Solutions | C93: =IFERROR(VLOOKUP(B93,'QB Consolidated Contacts'!$A$1:$F$333,6),"-") -> 0 | E93: VNA | F93: MSA | G93: Agreement | I93: 1.0_Master_Services_Agreement-_v5.1_Execution_2025_03_30 | J93: Yes | K93: Yes | L93: 45748 | N93: =IFERROR(EDATE(L93,M93),"") -> 45748 | O93: =IFERROR(N93-TODAY(),"") -> -345 | AK93: =IF(AGREEMENTS[[#This Row],[Days to Contract End]]<=90,"R",IF(AND(AGREEMENTS[[#This Row],[Days to Contract End]]<180),"A","G")) -> R
B94: Savantage Financial Services, Inc. d.b.a. Savantage Solutions | C94: =IFERROR(VLOOKUP(B94,'QB Consolidated Contacts'!$A$1:$F$333,6),"-") -> 0 | E94: VNA | F94: Addendum | G94: Sales & Use Tax Addendum | H94: 45748 | I94: 2.1 VNA_Sales_Tax Addendum_v5.1 Execution 2025 03 30 | J94: Yes | K94: Yes | N94: =IFERROR(EDATE(L94,M94),"") -> 0 | O94: =IFERROR(N94-TODAY(),"") -> -46093 | AK94: =IF(AGREEMENTS[[#This Row],[Days to Contract End]]<=90,"R",IF(AND(AGREEMENTS[[#This Row],[Days to Contract End]]<180),"A","G")) -> R
B95: Sherwin Williams | C95: =IFERROR(VLOOKUP(B95,'QB Consolidated Contacts'!$A$1:$F$333,6),"-") -> 0 | E95: VNA | F95: NDA | G95: Agreement | I95: Non-Disclosure Agreement | J95: Yes | L95: 43613 | M95: ON-GOING | N95: =IFERROR(EDATE(L95,M95),"") | O95: =IFERROR(N95-TODAY(),"") | AK95: =IF(AGREEMENTS[[#This Row],[Days to Contract End]]<=90,"R",IF(AND(AGREEMENTS[[#This Row],[Days to Contract End]]<180),"A","G")) -> G
B96: Sherwin Williams | C96: =IFERROR(VLOOKUP(B96,'QB Consolidated Contacts'!$A$1:$F$333,6),"-") -> 0 | E96: VNA | F96: MSA | G96: Agreement | I96: Master Services Agreement | J96: No | N96: =IFERROR(EDATE(L96,M96),"") -> 0 | O96: =IFERROR(N96-TODAY(),"") -> -46093 | AK96: =IF(AGREEMENTS[[#This Row],[Days to Contract End]]<=90,"R",IF(AND(AGREEMENTS[[#This Row],[Days to Contract End]]<180),"A","G")) -> R
B97: SHI International Corp. | C97: =IFERROR(VLOOKUP(B97,'QB Consolidated Contacts'!$A$1:$F$333,6),"-") -> 0 | E97: VNA | F97: NDA | G97: Partnership | I97: SHI US Mutual Non Disclosure Agreement - 26FEB2025 1 | J97: Yes | K97: Yes | L97: 45665 | M97: 24 | N97: =IFERROR(EDATE(L97,M97),"") -> 46395 | O97: =IFERROR(N97-TODAY(),"") -> 302 | AK97: =IF(AGREEMENTS[[#This Row],[Days to Contract End]]<=90,"R",IF(AND(AGREEMENTS[[#This Row],[Days to Contract End]]<180),"A","G")) -> G
B98: SICE | C98: =IFERROR(VLOOKUP(B98,'QB Consolidated Contacts'!$A$1:$F$333,6),"-") -> 0 | E98: VNA | F98: MSA | G98: Agreement | H98: 45709 | I98: VNA_MSA_SICE_13FEB2025 | J98: Yes | K98: Yes | L98: 45694 | M98: ON-GOING | N98: =IFERROR(EDATE(L98,M98),"") | O98: =IFERROR(N98-TODAY(),"") | AK98: =IF(AGREEMENTS[[#This Row],[Days to Contract End]]<=90,"R",IF(AND(AGREEMENTS[[#This Row],[Days to Contract End]]<180),"A","G")) -> G
B99: SICE | C99: =IFERROR(VLOOKUP(B99,'QB Consolidated Contacts'!$A$1:$F$333,6),"-") -> 0 | E99: VNA | F99: NDA | G99: Agreement | H99: 45709 | I99: NDA_US_SICE_VNA_10FEB2025 | J99: Yes | K99: Yes | L99: 45699 | M99: 60 | N99: =IFERROR(EDATE(L99,M99),"") -> 47525 | O99: =IFERROR(N99-TODAY(),"") -> 1432 | AK99: =IF(AGREEMENTS[[#This Row],[Days to Contract End]]<=90,"R",IF(AND(AGREEMENTS[[#This Row],[Days to Contract End]]<180),"A","G")) -> G
B100: Solix | C100: =IFERROR(VLOOKUP(B100,'QB Consolidated Contacts'!$A$1:$F$333,6),"-") -> 0 | D100: Infrastructure | E100: VT | F100: NDA | G100: Agreement | I100: SOLIX Mutual NDA-2023.pdf | J100: Yes | K100: Yes | L100: 45080 | M100: ON-GOING | N100: =IFERROR(EDATE(L100,M100),"") | O100: =IFERROR(N100-TODAY(),"") | AK100: =IF(AGREEMENTS[[#This Row],[Days to Contract End]]<=90,"R",IF(AND(AGREEMENTS[[#This Row],[Days to Contract End]]<180),"A","G")) -> G
...

Sheet Partnerships - Referrals and Re
A1: Partnership - Referrals and Resell
A2: Company Name | B2: Referral or Resell | C2: Initial Contact Date | D2: Last Engagement Date | E2: Agreement | F2: Notes
A3: Accelario | B3: Referral | E3: ACCELARIO - Partnership Distribution Agr - Redlines 11Sept2024.docx | F3: Redlined new contract with DW's responses - pending approval to be sent.
A4: Accelario | E4: ACCELARIO - Partnership Distribution Agr w Viscosity - clean version - final.docx
A5: Confluent | B5: Resell | C5: 06.09.2023 | D5: 06.09.2023 | E5: Pending Viscosity Response | F5: Accepted - pending Partner Agreement acceptance
A6: Cynet | B6: Referral | C6: 05.24.2023 | D6: 05.31.2023 | E6: Pending Viscosity Response | F6: Meeting scheduled for 06.13.2023
A7: Solix | B7: Referral | D7: 06.12.2023 | E7: Pending Viscosity Response | F7: CK made edits on the attached link
A8: Solix | B8: Referral | D8: 06.12.2023 | E8: NDA_DocuSign executed 06.03.2023
A9: Databricks
A10: Microsoft
A11: Oracle
A12: Silk | E12: Silk_Mutual NDA_VNA_final.docx
A13: KeyTech
A14: AVNET

Sheet Statements of Work
B1: Statements of Work
B2: Company | C2: Client | D2: Business Line | E2: Contract Type | F2: Work Type | G2: Date Signed | H2: Effective Date | I2: Contract Name/Document Link | J2: Project Contact | K2: Signed Copy | L2: DocuSign | M2: Status | N2: Requires PO | O2: PO # | P2: Cycle | Q2: Payment Terms | R2: Monthly Budget | S2: Total Budget | T2: Block Of Hours | U2: Duration (Months) | V2: Expiration Date | W2: Days to Contract End | X2: R.A.G. Status | Y2: Discription of Project | AA2: Yes | AB2: No
B3: VNA | C3: ABC Fitness Solutions, LLC | D3: Infrastructure | E3: SOW | F3: Professional Services | G3: 44979 | I3: ABC.India Offshore DBA SOW.20230217.docx | J3: =IFERROR(VLOOKUP(Agreements!B123,'QB Consolidated Contacts'!$A$1:$F$333,6),"-") -> - | V3: =IFERROR(EDATE(Agreements!U123,Agreements!V123),"") -> 0 | W3: =IFERROR(Agreements!W123-TODAY(),"") -> -46093 | X3: =IF(SOWS[[#This Row],[Days to Contract End]]<=90,"R",IF(AND(SOWS[[#This Row],[Days to Contract End]]<180),"A","G")) -> R
B4: VNA | C4: ABC Fitness Solutions, LLC | D4: Infrastructure | E4: SOW | F4: Professional Services | H4: 44586 | I4: ABC-Fitness BI - Azure DevOps Integration | J4: =IFERROR(VLOOKUP(C4,'QB Consolidated Contacts'!$A$1:$F$333,6),"-") -> Prakash Rikhilal | K4: Yes | M4: Unknown | N4: Yes | P4: Block of Hours | S4: 229600 | T4: 1312 | U4: ON-GOING | V4: =IFERROR(EDATE(H4,U4),"") | W4: =IFERROR(V4-TODAY(),"") | X4: =IF(SOWS[[#This Row],[Days to Contract End]]<=90,"R",IF(AND(SOWS[[#This Row],[Days to Contract End]]<180),"A","G")) -> G
B5: VNA | C5: ABC Fitness Solutions, LLC | D5: Infrastructure | E5: SOW | F5: Professional Services | H5: 44621 | I5: ABC - Professional Services | J5: =IFERROR(VLOOKUP(C5,'QB Consolidated Contacts'!$A$1:$F$333,6),"-") -> Prakash Rikhilal | K5: Yes | M5: Unknown | N5: Yes | O5: PO23-29200 | P5: Block of Hours | S5: 91000 | T5: 520 | U5: ON-GOING | V5: =IFERROR(EDATE(H5,U5),"") | W5: =IFERROR(V5-TODAY(),"") | X5: =IF(SOWS[[#This Row],[Days to Contract End]]<=90,"R",IF(AND(SOWS[[#This Row],[Days to Contract End]]<180),"A","G")) -> G
B6: VNA | C6: ABC Fitness Solutions, LLC | D6: Infrastructure | E6: SOW | F6: Professional Services | G6: 45069 | H6: 45063 | I6: VNA.ABC_DBA Professional Services_SoW_May 2023.docx | J6: =IFERROR(VLOOKUP(C6,'QB Consolidated Contacts'!$A$1:$F$333,6),"-") -> Prakash Rikhilal | K6: Yes | L6: Yes | M6: Unknown | T6: 60/week | U6: ON-GOING | V6: =IFERROR(EDATE(H6,U6),"") | W6: =IFERROR(V6-TODAY(),"") | X6: =IF(SOWS[[#This Row],[Days to Contract End]]<=90,"R",IF(AND(SOWS[[#This Row],[Days to Contract End]]<180),"A","G")) -> G
B7: VNA | C7: ABC Fitness Solutions, LLC | D7: Infrastructure | E7: SOW | F7: Professional Services | H7: 45214 | I7: VNA.ABC_Professional Services_SoW_Q4 2023.docx | J7: =IFERROR(VLOOKUP(C7,'QB Consolidated Contacts'!$A$1:$F$333,6),"-") -> Prakash Rikhilal | K7: Yes | L7: Yes | M7: Unknown | N7: Yes | T7: =332+24 -> 356 | U7: TBD | V7: =IFERROR(EDATE(H7,U7),"") | W7: =IFERROR(V7-TODAY(),"") | X7: =IF(SOWS[[#This Row],[Days to Contract End]]<=90,"R",IF(AND(SOWS[[#This Row],[Days to Contract End]]<180),"A","G")) -> G
B8: VT | C8: ABC Fitness Solutions, LLC | D8: Infrastructure | E8: SOW | F8: Managed Services | H8: 44739 | I8: Offshore - Monitoring & Support | J8: =IFERROR(VLOOKUP(C8,'QB Consolidated Contacts'!$A$1:$F$333,6),"-") -> Prakash Rikhilal | K8: Yes | M8: Unknown | N8: Yes | P8: Monthly | R8: 13410 | S8: =SOWS[[#This Row],[Monthly Budget]]*12 -> 160920 | T8: =106+106+10 -> 222 | U8: 12 | V8: =IFERROR(EDATE(H8,U8),"") -> 45104 | W8: =IFERROR(V8-TODAY(),"") -> -989 | X8: =IF(SOWS[[#This Row],[Days to Contract End]]<=90,"R",IF(AND(SOWS[[#This Row],[Days to Contract End]]<180),"A","G")) -> R
B9: VNA | C9: ABC Fitness Solutions, LLC | D9: Infrastructure | E9: SOW | F9: Managed Services | H9: 44972 | I9: Offshore - DBA Support | J9: =IFERROR(VLOOKUP(C9,'QB Consolidated Contacts'!$A$1:$F$333,6),"-") -> Prakash Rikhilal | K9: Yes | M9: Unknown | N9: Yes | P9: Block of Hours | R9: 9000 | S9: =SOWS[[#This Row],[Monthly Budget]]*12 -> 108000 | T9: 40 hrs/week | U9: 12 | V9: =IFERROR(EDATE(H9,U9),"") -> 45337 | W9: =IFERROR(V9-TODAY(),"") -> -756 | X9: =IF(SOWS[[#This Row],[Days to Contract End]]<=90,"R",IF(AND(SOWS[[#This Row],[Days to Contract End]]<180),"A","G")) -> R
B10: VNA | C10: ABC Fitness Solutions, LLC | D10: Infrastructure | E10: SOW | F10: Managed Services | H10: 45108 | I10: VNA.ABC.Managed Services SoW.EDW Monitoring.Offshore.2023July.docx | J10: =IFERROR(VLOOKUP(C10,'QB Consolidated Contacts'!$A$1:$F$333,6),"-") -> Prakash Rikhilal | K10: Yes | L10: Yes | M10: Unknown | N10: Yes | O10: PO22-24864 | U10: 6 | V10: =IFERROR(EDATE(H10,U10),"") -> 45292 | W10: =IFERROR(V10-TODAY(),"") -> -801 | X10: =IF(SOWS[[#This Row],[Days to Contract End]]<=90,"R",IF(AND(SOWS[[#This Row],[Days to Contract End]]<180),"A","G")) -> R
B11: VNA | C11: ABC Fitness Solutions, LLC | D11: Infrastructure | E11: SOW | F11: Assessment | I11: VNA.ABC.PF-Get Well-Insights Assessment.SoW.2024Sep.docx | J11: =IFERROR(VLOOKUP(Agreements!B133,'QB Consolidated Contacts'!$A$1:$F$333,6),"-") -> - | V11: =IFERROR(EDATE(Agreements!U133,Agreements!V133),"") -> 0 | W11: =IFERROR(Agreements!W133-TODAY(),"") -> -46093 | X11: =IF(SOWS[[#This Row],[Days to Contract End]]<=90,"R",IF(AND(SOWS[[#This Row],[Days to Contract End]]<180),"A","G")) -> R
B12: VNA | C12: ABC Fitness Solutions, LLC | D12: Infrastructure | E12: SOW | F12: Managed Services | H12: 45292 | I12: VNA.ABC.Professional Services.SoW.2024Jan-Jun.docx | J12: =IFERROR(VLOOKUP(C12,'QB Consolidated Contacts'!$A$1:$F$333,6),"-") -> Prakash Rikhilal | K12: Yes | L12: Yes | M12: Unknown | U12: TBD | V12: 45658 | W12: =IFERROR(V12-TODAY(),"") -> -435 | X12: =IF(SOWS[[#This Row],[Days to Contract End]]<=90,"R",IF(AND(SOWS[[#This Row],[Days to Contract End]]<180),"A","G")) -> R
B13: VNA | C13: ABC Fitness Solutions, LLC | D13: Infrastructure | E13: SOW | F13: Managed Services | I13: VNA.ABC.Support Services SoW.EDW Monitoring.Offshore.2024Jan-Jun.docx | J13: =IFERROR(VLOOKUP(Agreements!B134,'QB Consolidated Contacts'!$A$1:$F$333,6),"-") -> - | V13: =IFERROR(EDATE(Agreements!U134,Agreements!V134),"") -> 0 | W13: =IFERROR(Agreements!W134-TODAY(),"") -> -46093 | X13: =IF(SOWS[[#This Row],[Days to Contract End]]<=90,"R",IF(AND(SOWS[[#This Row],[Days to Contract End]]<180),"A","G")) -> R
B14: VNA | C14: ABC Fitness Solutions, LLC | D14: Infrastructure | E14: SOW | F14: Professional Services | I14: VNA.ABC.Professional Services.SoW.2024Jun-Dec | J14: =IFERROR(VLOOKUP(Agreements!B135,'QB Consolidated Contacts'!$A$1:$F$333,6),"-") -> - | V14: =IFERROR(EDATE(Agreements!U135,Agreements!V135),"") -> 0 | W14: =IFERROR(Agreements!W135-TODAY(),"") -> -46093 | X14: =IF(SOWS[[#This Row],[Days to Contract End]]<=90,"R",IF(AND(SOWS[[#This Row],[Days to Contract End]]<180),"A","G")) -> R
B15: VNA | C15: ABC Fitness Solutions, LLC | D15: Infrastructure | E15: SOW | F15: Professional Services | I15: VNA.ABC.Professional Services.SoW.2024Jan-Jun.docx | J15: =IFERROR(VLOOKUP(Agreements!B135,'QB Consolidated Contacts'!$A$1:$F$333,6),"-") -> - | V15: =IFERROR(EDATE(Agreements!U135,Agreements!V135),"") -> 0 | W15: =IFERROR(Agreements!W135-TODAY(),"") -> -46093 | X15: =IF(SOWS[[#This Row],[Days to Contract End]]<=90,"R",IF(AND(SOWS[[#This Row],[Days to Contract End]]<180),"A","G")) -> R
B16: VNA | C16: ABC Fitness Solutions, LLC | D16: Infrastructure | E16: SOW | F16: Managed Services | H16: 45751 | I16: VNA.ABC.Support Services SoW.EDW Monitoring.Offshore.2025Apr-Jun.docx | J16: =IFERROR(VLOOKUP(Agreements!B139,'QB Consolidated Contacts'!$A$1:$F$333,6),"-") -> - | K16: Yes | L16: Yes | V16: =IFERROR(EDATE(Agreements!U139,Agreements!V139),"") -> 0 | W16: =IFERROR(Agreements!W139-TODAY(),"") -> -46093 | X16: =IF(SOWS[[#This Row],[Days to Contract End]]<=90,"R",IF(AND(SOWS[[#This Row],[Days to Contract End]]<180),"A","G")) -> R
B17: VNA | C17: ABC Fitness Solutions, LLC | D17: Infrastructure | E17: SOW | F17: Managed Services | I17: VNA.ABC.Support Services SoW.EDW Monitoring.Offshore.2025Jan-Mar.v2.docx | J17: =IFERROR(VLOOKUP(Agreements!B138,'QB Consolidated Contacts'!$A$1:$F$333,6),"-") -> - | K17: Yes | L17: Yes | V17: =IFERROR(EDATE(Agreements!U138,Agreements!V138),"") -> 0 | W17: =IFERROR(Agreements!W138-TODAY(),"") -> -46093 | X17: =IF(SOWS[[#This Row],[Days to Contract End]]<=90,"R",IF(AND(SOWS[[#This Row],[Days to Contract End]]<180),"A","G")) -> R
B18: VNA | C18: ABC Fitness Solutions, LLC | D18: Infrastructure | E18: SOW | F18: Professional Services | I18: VNA.ABC.Support Services SoW.Offshore DBA.2024Mar-Dec.docx | J18: =IFERROR(VLOOKUP(Agreements!B136,'QB Consolidated Contacts'!$A$1:$F$333,6),"-") -> - | V18: =IFERROR(EDATE(Agreements!U136,Agreements!V136),"") -> 0 | W18: =IFERROR(Agreements!W136-TODAY(),"") -> -46093 | X18: =IF(SOWS[[#This Row],[Days to Contract End]]<=90,"R",IF(AND(SOWS[[#This Row],[Days to Contract End]]<180),"A","G")) -> R
B19: VNA | C19: ABC Fitness Solutions, LLC | D19: Infrastructure | E19: SOW | F19: Managed Services | H19: 45292 | I19: VNA.ABC.Support Services SoW.EDW Monitoring.Offshore.2024Jan-Jun.docx | J19: =IFERROR(VLOOKUP(C19,'QB Consolidated Contacts'!$A$1:$F$333,6),"-") -> Prakash Rikhilal | K19: Yes | L19: Yes | M19: Unknown | U19: TBD | V19: 45657 | W19: =IFERROR(V19-TODAY(),"") -> -436 | X19: =IF(SOWS[[#This Row],[Days to Contract End]]<=90,"R",IF(AND(SOWS[[#This Row],[Days to Contract End]]<180),"A","G")) -> R
B20: VNA | C20: ABC Fitness Solutions, LLC | D20: Infrastructure | E20: SOW | F20: Managed Services | H20: 45352 | I20: VNA.ABC.Support Services SoW.Offshore DBA.2024Mar-Dec.docx | J20: =IFERROR(VLOOKUP(C20,'QB Consolidated Contacts'!$A$1:$F$333,6),"-") -> Prakash Rikhilal | K20: Yes | L20: Yes | M20: Unknown | U20: 10 | V20: 45657 | W20: =IFERROR(V20-TODAY(),"") -> -436 | X20: =IF(SOWS[[#This Row],[Days to Contract End]]<=90,"R",IF(AND(SOWS[[#This Row],[Days to Contract End]]<180),"A","G")) -> R
B21: VNA | C21: ABC Fitness Solutions, LLC | D21: Infrastructure | E21: SOW | F21: Managed Services | H21: 45474 | I21: VNA.ABC.Support Services SoW.EDW Monitoring.Offshore.2024Jul-Dec.docx.pdf | J21: =IFERROR(VLOOKUP(C21,'QB Consolidated Contacts'!$A$1:$F$333,6),"-") -> Prakash Rikhilal | K21: Yes | L21: Yes | M21: Unknown | N21: Need PO | U21: 6 | V21: =IFERROR(EDATE(H21,U21),"") -> 45658 | W21: =IFERROR(V21-TODAY(),"") -> -435 | X21: =IF(SOWS[[#This Row],[Days to Contract End]]<=90,"R",IF(AND(SOWS[[#This Row],[Days to Contract End]]<180),"A","G")) -> R
B22: VNA | C22: ABC Fitness Solutions, LLC | D22: Infrastructure | E22: SOW | I22: ExaCC DB Migration-Optimization-Support | J22: =IFERROR(VLOOKUP(C22,'QB Consolidated Contacts'!$A$1:$F$333,6),"-") -> Prakash Rikhilal | K22: Yes | L22: Yes | V22: =IFERROR(EDATE(Agreements!U122,Agreements!V122),"") -> 0 | W22: =IFERROR(Agreements!W122-TODAY(),"") -> -46093 | X22: =IF(SOWS[[#This Row],[Days to Contract End]]<=90,"R",IF(AND(SOWS[[#This Row],[Days to Contract End]]<180),"A","G")) -> R
B23: VNA | C23: ABC Fitness Solutions, LLC | D23: Infrastructure | E23: SOW | F23: Professional Services | G23: 45845 | I23: VNA.ABC.Azure Data Monitoring & Dashboard.SoW.May 2025 | J23: =IFERROR(VLOOKUP(Agreements!B122,'QB Consolidated Contacts'!$A$1:$F$333,6),"-") -> - | K23: Yes | L23: Yes | V23: =IFERROR(EDATE(Agreements!U122,Agreements!V122),"") -> 0 | W23: =IFERROR(Agreements!W122-TODAY(),"") -> -46093 | X23: =IF(SOWS[[#This Row],[Days to Contract End]]<=90,"R",IF(AND(SOWS[[#This Row],[Days to Contract End]]<180),"A","G")) -> R
B24: VNA | C24: ABC Fitness Solutions, LLC | D24: Infrastructure | E24: SOW | F24: Professional Services | G24: 45838 | I24: VNA.ABC.Professional Services.SoW.2025Jul-Dec | J24: =IFERROR(VLOOKUP(Agreements!B313,'QB Consolidated Contacts'!$A$1:$F$333,6),"-") -> - | V24: =IFERROR(EDATE(Agreements!U313,Agreements!V313),"") -> 0 | W24: =IFERROR(Agreements!W313-TODAY(),"") -> -46093 | X24: =IF(SOWS[[#This Row],[Days to Contract End]]<=90,"R",IF(AND(SOWS[[#This Row],[Days to Contract End]]<180),"A","G")) -> R
B25: VNA | C25: ACGI Software | D25: Infrastructure | E25: SOW | F25: Managed Services | H25: 44713 | I25: On Demand Consulting - Signed | J25: =IFERROR(VLOOKUP(C25,'QB Consolidated Contacts'!$A$1:$F$333,6),"-") -> Kevin Hostintler | K25: Yes | M25: Inactive | P25: - | T25: 135/hour | U25: ON-GOING | V25: =IFERROR(EDATE(H25,U25),"") | W25: =IFERROR(V25-TODAY(),"") | X25: =IF(SOWS[[#This Row],[Days to Contract End]]<=90,"R",IF(AND(SOWS[[#This Row],[Days to Contract End]]<180),"A","G")) -> G
B26: VNA | C26: Airport Terminal Services | D26: Infrastructure | E26: SOW | F26: Managed Services | H26: 43466 | I26: Oracle ERP Managed Services | J26: =IFERROR(VLOOKUP(C26,'QB Consolidated Contacts'!$A$1:$F$333,6),"-") -> Christina Green | K26: Yes | M26: Inactive | P26: Monthly | R26: 4500 | T26: 30 | U26: ON-GOING | V26: =IFERROR(EDATE(H26,U26),"") | W26: =IFERROR(V26-TODAY(),"") | X26: =IF(SOWS[[#This Row],[Days to Contract End]]<=90,"R",IF(AND(SOWS[[#This Row],[Days to Contract End]]<180),"A","G")) -> G
B27: VNA | C27: AMDI | D27: Development | E27: SOW | F27: Professional Services | H27: 45412 | I27: VNA SOW AMDI OEPortal Fully executed.pdf | J27: Gabriela Codina | K27: Yes | L27: Yes | M27: Active | U27: 16 | V27: =IFERROR(EDATE(H27,U27)+1,"") -> 45900 | W27: =IFERROR(V27-TODAY(),"") -> -193 | X27: =IF(SOWS[[#This Row],[Days to Contract End]]<=90,"R",IF(AND(SOWS[[#This Row],[Days to Contract End]]<180),"A","G")) -> R
C28: AMDI | J28: =IFERROR(VLOOKUP(Agreements!B138,'QB Consolidated Contacts'!$A$1:$F$333,6),"-") -> - | V28: =IFERROR(EDATE(Agreements!U138,Agreements!V138),"") -> 0 | W28: =IFERROR(Agreements!W138-TODAY(),"") -> -46093 | X28: =IF(SOWS[[#This Row],[Days to Contract End]]<=90,"R",IF(AND(SOWS[[#This Row],[Days to Contract End]]<180),"A","G")) -> R
C29: AMDI | J29: =IFERROR(VLOOKUP(Agreements!B138,'QB Consolidated Contacts'!$A$1:$F$333,6),"-") -> - | V29: =IFERROR(EDATE(Agreements!U138,Agreements!V138),"") -> 0 | W29: =IFERROR(Agreements!W138-TODAY(),"") -> -46093 | X29: =IF(SOWS[[#This Row],[Days to Contract End]]<=90,"R",IF(AND(SOWS[[#This Row],[Days to Contract End]]<180),"A","G")) -> R
B30: VNA | C30: American Heart Association, Inc. | D30: Infrastructure | E30: SOW | F30: Managed Services | H30: 44743 | I30: DBA Managed Services | J30: =IFERROR(VLOOKUP(C30,'QB Consolidated Contacts'!$A$1:$F$333,6),"-") -> Roger Santone | K30: Yes | M30: Expired | P30: Monthly | R30: 5000 | S30: =SOWS[[#This Row],[Monthly Budget]]*12 -> 60000 | T30: 30 | U30: 11 | V30: =IFERROR(EOMONTH(H30,U30),"") -> 45107 | W30: =IFERROR(V30-TODAY(),"") -> -986 | X30: =IF(SOWS[[#This Row],[Days to Contract End]]<=90,"R",IF(AND(SOWS[[#This Row],[Days to Contract End]]<180),"A","G")) -> R
B31: VNA | C31: AMERICAN LEATHER HOLDINGS, LLC | D31: Development | E31: SOW | F31: Managed Services | I31: SOW-VNA.AL_-EBS_WebServices.Remote_Support_Services.20240823.EXECUTED | J31: =IFERROR(VLOOKUP(Agreements!B144,'QB Consolidated Contacts'!$A$1:$F$333,6),"-") -> - | K31: Yes | L31: Yes | V31: =IFERROR(EDATE(Agreements!U144,Agreements!V144),"") -> 0 | W31: =IFERROR(Agreements!W144-TODAY(),"") -> -46093 | X31: =IF(SOWS[[#This Row],[Days to Contract End]]<=90,"R",IF(AND(SOWS[[#This Row],[Days to Contract End]]<180),"A","G")) -> R
B32: VNA | C32: AMERICAN LEATHER HOLDINGS, LLC | D32: Development | E32: Change Order | F32: Professional Services | I32: ALO_B2B_Portal-_Enhancements__BRD_V2.0.EXECUTED | J32: =IFERROR(VLOOKUP(Agreements!B144,'QB Consolidated Contacts'!$A$1:$F$333,6),"-") -> - | K32: Yes | L32: Yes | V32: =IFERROR(EDATE(Agreements!U144,Agreements!V144),"") -> 0 | W32: =IFERROR(Agreements!W144-TODAY(),"") -> -46093 | X32: =IF(SOWS[[#This Row],[Days to Contract End]]<=90,"R",IF(AND(SOWS[[#This Row],[Days to Contract End]]<180),"A","G")) -> R
B33: VNA | C33: AMERICAN LEATHER HOLDINGS, LLC | D33: Development | E33: SOW | F33: Managed Services | I33: SOW.AMERICAN LEATHER.VNA SWATCH MANAGED SERVICES.APR2024.docx | J33: =IFERROR(VLOOKUP(Agreements!B144,'QB Consolidated Contacts'!$A$1:$F$333,6),"-") -> - | K33: Yes | L33: Yes | V33: =IFERROR(EDATE(Agreements!U144,Agreements!V144),"") -> 0 | W33: =IFERROR(Agreements!W144-TODAY(),"") -> -46093 | X33: =IF(SOWS[[#This Row],[Days to Contract End]]<=90,"R",IF(AND(SOWS[[#This Row],[Days to Contract End]]<180),"A","G")) -> R
B34: VNA | C34: AMERICAN LEATHER HOLDINGS, LLC | D34: Development | E34: Change Order | F34: Professional Services | H34: 45636 | I34: CO.AL.LEE.00001.DB2WebservicesDec2024.docx | J34: =IFERROR(VLOOKUP(Agreements!B141,'QB Consolidated Contacts'!$A$1:$F$333,6),"-") -> - | K34: Yes | L34: Yes | M34: Unknown | T34: 80 | U34: 12 | V34: =IFERROR(EDATE(Agreements!U141,Agreements!V141),"") -> 0 | W34: =IFERROR(Agreements!W141-TODAY(),"") -> -46093 | X34: =IF(SOWS[[#This Row],[Days to Contract End]]<=90,"R",IF(AND(SOWS[[#This Row],[Days to Contract End]]<180),"A","G")) -> R
B35: VNA | C35: AMERICAN LEATHER HOLDINGS, LLC | D35: Development | E35: Change Order | F35: Professional Services | H35: 45506 | I35: CO.AL.EBSWS.00002.Swatch-User Portal Integration.V2 | J35: =IFERROR(VLOOKUP(Agreements!B141,'QB Consolidated Contacts'!$A$1:$F$333,6),"-") -> - | M35: Unknown | V35: =IFERROR(EDATE(Agreements!U141,Agreements!V141),"") -> 0 | W35: =IFERROR(Agreements!W141-TODAY(),"") -> -46093 | X35: =IF(SOWS[[#This Row],[Days to Contract End]]<=90,"R",IF(AND(SOWS[[#This Row],[Days to Contract End]]<180),"A","G")) -> R
B36: VNA | C36: AMERICAN LEATHER HOLDINGS, LLC | D36: Development | E36: SOW | F36: Professional Services | H36: 45118 | I36: APEX Staff Augmentation- Transfer Views from Oracle to Alternative Data Store | J36: =IFERROR(VLOOKUP(C36,'QB Consolidated Contacts'!$A$1:$F$333,6),"-") -> Roger Santone | K36: Yes | L36: Yes | M36: Active | T36: 80 | U36: TBD | V36: =IFERROR(EDATE(H36,U36),"") | W36: =IFERROR(V36-TODAY(),"") | X36: =IF(SOWS[[#This Row],[Days to Contract End]]<=90,"R",IF(AND(SOWS[[#This Row],[Days to Contract End]]<180),"A","G")) -> G
B37: VT | C37: AMERICAN LEATHER HOLDINGS, LLC | D37: Development | E37: SOW | F37: Managed Services | G37: 45699 | I37: SOW-VT.AL -Lee WebServices.Remote Support Services.2025.docx | J37: =IFERROR(VLOOKUP(Agreements!B141,'QB Consolidated Contacts'!$A$1:$F$333,6),"-") -> - | K37: Yes | L37: Yes | M37: Unknown | U37: 12 | V37: =IFERROR(EDATE(Agreements!U141,Agreements!V141),"") -> 0 | W37: =IFERROR(Agreements!W141-TODAY(),"") -> -46093 | X37: =IF(SOWS[[#This Row],[Days to Contract End]]<=90,"R",IF(AND(SOWS[[#This Row],[Days to Contract End]]<180),"A","G")) -> R
B38: VNA | C38: AMERICAN LEATHER HOLDINGS, LLC | D38: Development | E38: SOW | F38: Professional Services | H38: 45160 | I38: SOW.American_Leather.Web_Services.SOW.ORACLE_EBS.AUG2023.docx | J38: =IFERROR(VLOOKUP(C38,'QB Consolidated Contacts'!$A$1:$F$333,6),"-") -> Roger Santone | K38: Yes | L38: Yes | M38: Active | U38: TBD | V38: =IFERROR(EDATE(H38,U38),"") | W38: =IFERROR(V38-TODAY(),"") | X38: =IF(SOWS[[#This Row],[Days to Contract End]]<=90,"R",IF(AND(SOWS[[#This Row],[Days to Contract End]]<180),"A","G")) -> G
B39: VT | C39: AMERICAN LEATHER HOLDINGS, LLC | D39: Development | E39: SOW | F39: Professional Services | H39: ** | I39: SOW-VT.AL -EBS WebServices.Remote Support Services.20240823.REISSUE.docx | J39: =IFERROR(VLOOKUP(Agreements!B141,'QB Consolidated Contacts'!$A$1:$F$333,6),"-") -> - | K39: Yes | L39: Yes | M39: Unknown | U39: 36 | V39: =IFERROR(EDATE(Agreements!U141,Agreements!V141),"") -> 0 | W39: =IFERROR(Agreements!W141-TODAY(),"") -> -46093 | X39: =IF(SOWS[[#This Row],[Days to Contract End]]<=90,"R",IF(AND(SOWS[[#This Row],[Days to Contract End]]<180),"A","G")) -> R
B40: VNA | C40: AMERICAN LEATHER HOLDINGS, LLC | D40: Development | E40: Change Order | F40: Professional Services | H40: 45523 | I40: ALO_B2B_Portal-_Enhancements__BRD_V2.0.EXECUTED.pdf | J40: =IFERROR(VLOOKUP(C40,'QB Consolidated Contacts'!$A$1:$F$333,6),"-") -> Roger Santone | K40: Yes | L40: Yes | M40: Active | P40: Block of Hours | S40: 21000 | T40: 120 | U40: TBD | V40: =IFERROR(EDATE(H40,U40),"") | W40: =IFERROR(V40-TODAY(),"") | X40: =IF(SOWS[[#This Row],[Days to Contract End]]<=90,"R",IF(AND(SOWS[[#This Row],[Days to Contract End]]<180),"A","G")) -> G
B41: VNA | C41: AMERICAN LEATHER HOLDINGS, LLC | D41: Development | E41: SOW | F41: Professional Services | H41: 45536 | I41: SOW-VT.AL -EBS WebServices.Remote Support Services.20240823.REISSUE.docx.pdf | J41: =IFERROR(VLOOKUP(C41,'QB Consolidated Contacts'!$A$1:$F$333,6),"-") -> Roger Santone | K41: Yes | L41: Yes | M41: Active | N41: Yes | P41: Monthly | U41: 36 | V41: =IFERROR(EDATE(H41,U41),"") -> 46631 | W41: =IFERROR(V41-TODAY(),"") -> 538 | X41: =IF(SOWS[[#This Row],[Days to Contract End]]<=90,"R",IF(AND(SOWS[[#This Row],[Days to Contract End]]<180),"A","G")) -> G
B42: VNA | C42: AMERICAN LEATHER HOLDINGS, LLC | D42: Development | E42: SOW | F42: Professional Services | H42: *** | I42: SOW.American Leather.Swatch Enhancements.MVP.wPM.20240802.docx.pdf | J42: =IFERROR(VLOOKUP(C42,'QB Consolidated Contacts'!$A$1:$F$333,6),"-") -> Roger Santone | K42: Yes | L42: Yes | M42: Active | V42: =IFERROR(EDATE(H42,U42),"") | W42: =IFERROR(V42-TODAY(),"") | X42: =IF(SOWS[[#This Row],[Days to Contract End]]<=90,"R",IF(AND(SOWS[[#This Row],[Days to Contract End]]<180),"A","G")) -> G
B43: VNA | C43: AMERICAN LEATHER HOLDINGS, LLC | D43: Development | E43: SOW | F43: Professional Services | H43: 45033 | I43: SOW.AMERICAN LEATHER.VNA STAFF AUGUMENTATION.APR2023.docx | J43: =IFERROR(VLOOKUP(C43,'QB Consolidated Contacts'!$A$1:$F$333,6),"-") -> Roger Santone | K43: Yes | L43: Yes | M43: Active | P43: Monthly | Q43: - | R43: 12250 | S43: =SOWS[[#This Row],[Monthly Budget]]*12 -> 147000 | T43: =16*12 -> 192 | U43: 12 | V43: =IFERROR(EDATE(H43,U43),"") -> 45399 | W43: =IFERROR(V43-TODAY(),"") -> -694 | X43: =IF(SOWS[[#This Row],[Days to Contract End]]<=90,"R",IF(AND(SOWS[[#This Row],[Days to Contract End]]<180),"A","G")) -> R
B44: VNA | C44: AMERICAN LEATHER HOLDINGS, LLC | D44: Development | E44: SOW | F44: Professional Services | H44: 45152 | I44: SOW_HRMS_and_Financial_Archiving..Executed | J44: =IFERROR(VLOOKUP(C44,'QB Consolidated Contacts'!$A$1:$F$333,6),"-") -> Roger Santone | K44: Yes | L44: Yes | M44: Active | N44: Yes | U44: TBD | V44: 45535 | W44: =IFERROR(V44-TODAY(),"") -> -558 | X44: =IF(SOWS[[#This Row],[Days to Contract End]]<=90,"R",IF(AND(SOWS[[#This Row],[Days to Contract End]]<180),"A","G")) -> R
B45: VNA | C45: AMERICAN LEATHER HOLDINGS, LLC | D45: Development | E45: SOW | F45: Professional Services | H45: 45152 | I45: Records Management and Archive | J45: =IFERROR(VLOOKUP(C45,'QB Consolidated Contacts'!$A$1:$F$333,6),"-") -> Roger Santone | K45: Yes | L45: Yes | M45: Active | U45: TBD | V45: 45657 | W45: =IFERROR(V45-TODAY(),"") -> -436 | X45: =IF(SOWS[[#This Row],[Days to Contract End]]<=90,"R",IF(AND(SOWS[[#This Row],[Days to Contract End]]<180),"A","G")) -> R
B46: VNA | C46: AMERICAN LEATHER HOLDINGS, LLC | D46: Development | E46: SOW | F46: Professional Services | H46: 45511 | I46: VNA-AL-AP Invoice Automation Services-SOW-v2.docx | J46: =IFERROR(VLOOKUP(C46,'QB Consolidated Contacts'!$A$1:$F$333,6),"-") -> Roger Santone | K46: Yes | L46: Yes | M46: Active | U46: TBD | V46: 45657 | W46: =IFERROR(V46-TODAY(),"") -> -436 | X46: =IF(SOWS[[#This Row],[Days to Contract End]]<=90,"R",IF(AND(SOWS[[#This Row],[Days to Contract End]]<180),"A","G")) -> R
B47: VNA | C47: AMERICAN LEATHER HOLDINGS, LLC | D47: Development | E47: SOW | F47: Managed Services | H47: 45399 | I47: SOW.AMERICAN LEATHER.VNA SWATCH MANAGED SERVICES.APR2024.docx.pdf | J47: Paul?? | K47: Yes | L47: Yes | M47: Active | U47: 12 | V47: =IFERROR(EDATE(H47,U47),"")+13 -> 45777 | W47: =IFERROR(V47-TODAY(),"") -> -316 | X47: =IF(SOWS[[#This Row],[Days to Contract End]]<=90,"R",IF(AND(SOWS[[#This Row],[Days to Contract End]]<180),"A","G")) -> R
C48: AMERICAN LEATHER HOLDINGS, LLC | E48: SOW | F48: Professional Services | H48: 45160 | I48: SOW.American_Leather.Web_Services.SOW.ORACLE_EBS.AUG2023 | J48: =IFERROR(VLOOKUP(C48,'QB Consolidated Contacts'!$A$1:$F$333,6),"-") -> Roger Santone | K48: Yes | L48: Yes | M48: Active | V48: =IFERROR(EDATE(H48,U48),"") -> 45160 | W48: =IFERROR(V48-TODAY(),"") -> -933 | X48: =IF(SOWS[[#This Row],[Days to Contract End]]<=90,"R",IF(AND(SOWS[[#This Row],[Days to Contract End]]<180),"A","G")) -> R
B49: VT | C49: AMERICAN LEATHER HOLDINGS, LLC | D49: Infrastructure | E49: SOW | F49: Managed Services | G49: 45802 | H49: 45778 | I49: SOW.AMERICAN LEATHER.VT SWATCH REMOTE SERVICES.MAY2025 | J49: =IFERROR(VLOOKUP(Agreements!B190,'QB Consolidated Contacts'!$A$1:$F$333,6),"-") -> - | K49: Yes | L49: Yes | V49: =IFERROR(EDATE(H49,U49),"") -> 45778 | W49: =IFERROR(V49-TODAY(),"") -> -315 | X49: =IF(SOWS[[#This Row],[Days to Contract End]]<=90,"R",IF(AND(SOWS[[#This Row],[Days to Contract End]]<180),"A","G")) -> R
B50: VT | C50: AMERICAN LEATHER HOLDINGS, LLC | D50: Project Management | E50: SOW | F50: Professional Services | H50: 45634 | I50: ecommerce program manager support SOW signed 9 December 2023 | J50: =IFERROR(VLOOKUP(C50,'QB Consolidated Contacts'!$A$1:$F$333,6),"-") -> Roger Santone | K50: Yes | L50: Yes | M50: Active | U50: TBD | V50: 45382 | W50: =IFERROR(V50-TODAY(),"") -> -711 | X50: =IF(SOWS[[#This Row],[Days to Contract End]]<=90,"R",IF(AND(SOWS[[#This Row],[Days to Contract End]]<180),"A","G")) -> R
B51: VNA | C51: Apex Capital Corp. | D51: Infrastructure | E51: SOW | F51: Professional Services | G51: 45660 | H51: 45658 | I51: VNA SOW - Apex Capital Corp - DB Modernization.20241230_FINAL.docx | J51: =IFERROR(VLOOKUP(Agreements!B112,'QB Consolidated Contacts'!$A$1:$F$333,6),"-") -> 0 | K51: Yes | L51: Yes | U51: 3 | V51: =IFERROR(EDATE(H51,U51),"") -> 45748 | W51: =IFERROR(V51-TODAY(),"") -> -345 | X51: =IF(SOWS[[#This Row],[Days to Contract End]]<=90,"R",IF(AND(SOWS[[#This Row],[Days to Contract End]]<180),"A","G")) -> R
B52: VNA | C52: AssetWorks | D52: Infrastructure | E52: SOW | F52: Professional Services | H52: 45036 | I52: Asset Works Database and AOP Assessment SOW | J52: =IFERROR(VLOOKUP(C52,'QB Consolidated Contacts'!$A$1:$F$333,6),"-") -> 0 | K52: No | M52: Pending | V52: =IFERROR(EDATE(H52,U52),"") -> 45036 | W52: =IFERROR(V52-TODAY(),"") -> -1057 | X52: =IF(SOWS[[#This Row],[Days to Contract End]]<=90,"R",IF(AND(SOWS[[#This Row],[Days to Contract End]]<180),"A","G")) -> R
B53: VNA | C53: Athenian Group, LLC - LA Metro | D53: Development | E53: SOW | F53: Professional Services | H53: 45012 | I53: Data Input/Automation POV | J53: =IFERROR(VLOOKUP(C53,'QB Consolidated Contacts'!$A$1:$F$333,6),"-") -> 0 | K53: Yes | M53: Expired | U53: 2 | V53: =IFERROR(EDATE(H53,U53),"") -> 45073 | W53: =IFERROR(V53-TODAY(),"") -> -1020 | X53: =IF(SOWS[[#This Row],[Days to Contract End]]<=90,"R",IF(AND(SOWS[[#This Row],[Days to Contract End]]<180),"A","G")) -> R
C54: BDO-Harris County | J54: =IFERROR(VLOOKUP(Agreements!B274,'QB Consolidated Contacts'!$A$1:$F$333,6),"-") -> - | V54: =IFERROR(EDATE(Agreements!U274,Agreements!V274),"") -> 0 | W54: =IFERROR(V54-TODAY(),"") -> -46093 | X54: =IF(SOWS[[#This Row],[Days to Contract End]]<=90,"R",IF(AND(SOWS[[#This Row],[Days to Contract End]]<180),"A","G")) -> R
B55: VNA | C55: BMW | E55: PO | F55: Professional Services | I55: Sql/Apex Training.2022 | J55: =IFERROR(VLOOKUP(C55,'QB Consolidated Contacts'!$A$1:$F$333,6),"-") -> 0 | K55: No | M55: Inactive | O55: F3RKHXJ | V55: =IFERROR(EDATE(H55,U55),"") -> 0 | W55: =IFERROR(V55-TODAY(),"") -> -46093 | X55: =IF(SOWS[[#This Row],[Days to Contract End]]<=90,"R",IF(AND(SOWS[[#This Row],[Days to Contract End]]<180),"A","G")) -> R
B56: VNA | C56: Bot Construction Limited | D56: Infrastructure | E56: SOW | F56: Professional Services | H56: 44835 | I56: Oracle Apex Timekeeping | J56: =IFERROR(VLOOKUP(C56,'QB Consolidated Contacts'!$A$1:$F$333,6),"-") -> 0 | K56: No | M56: Unknown | P56: Monthly | T56: 100 | U56: 24 | V56: =IFERROR(EDATE(H56,U56),"") -> 45566 | W56: =IFERROR(V56-TODAY(),"") -> -527 | X56: =IF(SOWS[[#This Row],[Days to Contract End]]<=90,"R",IF(AND(SOWS[[#This Row],[Days to Contract End]]<180),"A","G")) -> R
B57: VT | C57: CableOne | D57: Infrastructure | E57: SOW | F57: Retainer | H57: 45495 | I57: (SOW) Statement of Work with Cable One, Inc_ (667af9e7f9) (version 1) | J57: =IFERROR(VLOOKUP(C57,'QB Consolidated Contacts'!$A$1:$F$333,6),"-") -> 0 | K57: Yes | L57: No | M57: Pending | U57: ON-GOING | V57: =IFERROR(EDATE(H57,U57),"") | W57: =IFERROR(V57-TODAY(),"") | X57: =IF(SOWS[[#This Row],[Days to Contract End]]<=90,"R",IF(AND(SOWS[[#This Row],[Days to Contract End]]<180),"A","G")) -> G
B58: VNA | C58: CACI - LGS Labs | D58: Development | E58: SOW | F58: Professional Services | H58: 44901 | I58: KURT Statement of Work | J58: =IFERROR(VLOOKUP(C58,'QB Consolidated Contacts'!$A$1:$F$333,6),"-") -> 0 | K58: Yes | M58: Expired | U58: 12 | V58: =IFERROR(EDATE(H58,U58),"") -> 45266 | W58: =IFERROR(V58-TODAY(),"") -> -827 | X58: =IF(SOWS[[#This Row],[Days to Contract End]]<=90,"R",IF(AND(SOWS[[#This Row],[Days to Contract End]]<180),"A","G")) -> R
B59: VNA | C59: CACI - LGS Labs | D59: Development | E59: SOW | F59: Professional Services | H59: 44907 | I59: KURT Migration to AWS - 2nd Run | J59: =IFERROR(VLOOKUP(C59,'QB Consolidated Contacts'!$A$1:$F$333,6),"-") -> 0 | K59: Yes | M59: Expired | U59: 12 | V59: =IFERROR(EDATE(H59,U59),"") -> 45272 | W59: =IFERROR(V59-TODAY(),"") -> -821 | X59: =IF(SOWS[[#This Row],[Days to Contract End]]<=90,"R",IF(AND(SOWS[[#This Row],[Days to Contract End]]<180),"A","G")) -> R | Y59: Optional Year 1 (if excersised) 12 December 2023 – 11 December 2024
B60: VNA | C60: CACI - LGS Labs | D60: Development | E60: SOW | F60: Assessment | H60: 44901 | I60: Support LGS Labs’ Kinetic User Repair Tracker KURT database | J60: =IFERROR(VLOOKUP(C60,'QB Consolidated Contacts'!$A$1:$F$333,6),"-") -> 0 | K60: Yes | M60: Unknown | P60: Monthly | T60: 1120 | U60: 24 | V60: =IFERROR(EDATE(H60,U60),"") -> 45632 | W60: =IFERROR(V60-TODAY(),"") -> -461 | X60: =IF(SOWS[[#This Row],[Days to Contract End]]<=90,"R",IF(AND(SOWS[[#This Row],[Days to Contract End]]<180),"A","G")) -> R
C61: CACI - LGS Labs | F61: Unknown | I61: LGS Innovations SOW.docx | J61: =IFERROR(VLOOKUP(C61,'QB Consolidated Contacts'!$A$1:$F$333,6),"-") -> 0 | K61: No | L61: No | M61: Unknown | V61: =IFERROR(EDATE(H61,U61),"") -> 0 | W61: =IFERROR(V61-TODAY(),"") -> -46093 | X61: =IF(SOWS[[#This Row],[Days to Contract End]]<=90,"R",IF(AND(SOWS[[#This Row],[Days to Contract End]]<180),"A","G")) -> R
B62: VNA | C62: Captial Title of Texas | D62: Development | E62: SOW | F62: Managed Services | H62: 44645 | I62: CRM SQL Server Migration | J62: =IFERROR(VLOOKUP(C62,'QB Consolidated Contacts'!$A$1:$F$333,6),"-") -> 0 | K62: Yes | M62: Expired | T62: 48 | U62: 12 | V62: =IFERROR(EDATE(H62,U62),"") -> 45010 | W62: =IFERROR(V62-TODAY(),"") -> -1083 | X62: =IF(SOWS[[#This Row],[Days to Contract End]]<=90,"R",IF(AND(SOWS[[#This Row],[Days to Contract End]]<180),"A","G")) -> R
B63: VNA | C63: Captial Title of Texas | D63: Development | E63: SOW | F63: Managed Services | H63: 44136 | I63: Capital Sales CRM | J63: =IFERROR(VLOOKUP(C63,'QB Consolidated Contacts'!$A$1:$F$333,6),"-") -> 0 | K63: Yes | M63: Inactive | U63: ON-GOING | V63: =IFERROR(EDATE(H63,U63),"") | W63: =IFERROR(V63-TODAY(),"") | X63: =IF(SOWS[[#This Row],[Days to Contract End]]<=90,"R",IF(AND(SOWS[[#This Row],[Days to Contract End]]<180),"A","G")) -> G
C64: Centene | E64: SOW | F64: Professional Services | H64: 44378 | I64: Exadata Optimization, Upgrades and Patching, Data Center Services, & Technical Advisory Services | J64: =IFERROR(VLOOKUP(C64,'QB Consolidated Contacts'!$A$1:$F$333,6),"-") -> 0 | K64: Yes | M64: Inactive | U64: ON-GOING | V64: =IFERROR(EDATE(H64,U64),"") | W64: =IFERROR(V64-TODAY(),"") | X64: =IF(SOWS[[#This Row],[Days to Contract End]]<=90,"R",IF(AND(SOWS[[#This Row],[Days to Contract End]]<180),"A","G")) -> G
B65: VNA | C65: Civic Telehealth | D65: Development | E65: SOW | F65: Professional Services | H65: 45369 | I65: CTH SOW Strategy.docx | J65: n/a | K65: No | L65: No | M65: Active | U65: TBD | V65: =IFERROR(EDATE(H65,U65),"") | W65: =IFERROR(V65-TODAY(),"") | X65: =IF(SOWS[[#This Row],[Days to Contract End]]<=90,"R",IF(AND(SOWS[[#This Row],[Days to Contract End]]<180),"A","G")) -> G
B66: VT | C66: Clario | D66: Infrastructure | E66: Change Order | F66: Managed Services | H66: 45117 | I66: CLARIO MANAGED SERVICES CHANGE ORDER 5-22-23.docx | J66: =IFERROR(VLOOKUP(C66,'QB Consolidated Contacts'!$A$1:$F$333,6),"-") -> 0 | K66: Yes | M66: Active | V66: =IFERROR(EDATE(H66,U66),"") -> 45117 | W66: =IFERROR(V66-TODAY(),"") -> -976 | X66: =IF(SOWS[[#This Row],[Days to Contract End]]<=90,"R",IF(AND(SOWS[[#This Row],[Days to Contract End]]<180),"A","G")) -> R | Y66: Revision in scope for Clario Managed Services agreement specific to monitored components:
B67: VT | C67: Clario | D67: Infrastructure | E67: Change Order | F67: Managed Services | H67: 44848 | I67: Clario_Linux_Unix_ODA_Managed_Services_SOW.v3.ADDENDUM.20221122.13.19.docx | J67: =IFERROR(VLOOKUP(C67,'QB Consolidated Contacts'!$A$1:$F$333,6),"-") -> 0 | K67: Yes | M67: Active | U67: 36 | V67: =IFERROR(EDATE(H67,U67),"") -> 45944 | W67: =IFERROR(V67-TODAY(),"") -> -149 | X67: =IF(SOWS[[#This Row],[Days to Contract End]]<=90,"R",IF(AND(SOWS[[#This Row],[Days to Contract End]]<180),"A","G")) -> R
B68: VT | C68: Clario | D68: Infrastructure | E68: SOW | F68: Managed Services | H68: 44848 | I68: Clario_Linux_Unix_ODA_Managed_Services_SOW.v3.20220715.FINAL.docx | J68: =IFERROR(VLOOKUP(C68,'QB Consolidated Contacts'!$A$1:$F$333,6),"-") -> 0 | K68: Yes | M68: Active | N68: Yes | O68: 101102037 | P68: Monthly | T68: 50 Hrs/Quarter | U68: 36 | V68: =IFERROR(EDATE(H68,U68),"") -> 45944 | W68: =IFERROR(V68-TODAY(),"") -> -149 | X68: =IF(SOWS[[#This Row],[Days to Contract End]]<=90,"R",IF(AND(SOWS[[#This Row],[Days to Contract End]]<180),"A","G")) -> R | Y68: Automatic Renewal after 36 months - 10/14/2025
B69: VNA | C69: COE | E69: SOW | F69: Managed Services | H69: 45200 | I69: COE.APEX REMOTE SUPPORT SERVICES.SOW.2024.EXECUTED | J69: Patricia Hammond | K69: Yes | L69: Yes | M69: Active | U69: 36 | V69: =IFERROR(EDATE(H69,U69),"") -> 46296 | W69: =IFERROR(V69-TODAY(),"") -> 203 | X69: =IF(SOWS[[#This Row],[Days to Contract End]]<=90,"R",IF(AND(SOWS[[#This Row],[Days to Contract End]]<180),"A","G")) -> G
B70: VNA | C70: COE | D70: Infrastructure | E70: SOW | F70: Managed Services | H70: 45200 | I70: COE.APEX REMOTE SUPPORT SERVICES.SOW.2024.EXECUTED | J70: =IFERROR(VLOOKUP(C70,'QB Consolidated Contacts'!$A$1:$F$333,6),"-") -> 0 | K70: Yes | L70: Yes | M70: Active | O70: No | P70: Monthly | R70: 4050 | S70: =SOWS[[#This Row],[Monthly Budget]]*36 -> 145800 | T70: 40 | U70: 36 | V70: 46295 | W70: 1440 | X70: =IF(SOWS[[#This Row],[Days to Contract End]]<=90,"R",IF(AND(SOWS[[#This Row],[Days to Contract End]]<180),"A","G")) -> G | Y70: 3-Year Term
B71: VNA | C71: COE | D71: Infrastructure | E71: SOW | F71: Managed Services | H71: 43709 | I71: COE_DBA_Sep_2019 | J71: =IFERROR(VLOOKUP(C71,'QB Consolidated Contacts'!$A$1:$F$333,6),"-") -> 0 | K71: Yes | M71: Expired | O71: No | P71: Monthly | U71: 24 | V71: =IFERROR(EDATE(H71,U71),"") -> 44440 | W71: =IFERROR(V71-TODAY(),"") -> -1653 | X71: =IF(SOWS[[#This Row],[Days to Contract End]]<=90,"R",IF(AND(SOWS[[#This Row],[Days to Contract End]]<180),"A","G")) -> R
B72: VNA | C72: College of American Pathologists (“CAP”) | D72: Infrastructure | E72: SOW | F72: Professional Services | H72: 45110 | I72: ODA Migration | J72: =IFERROR(VLOOKUP(C72,'QB Consolidated Contacts'!$A$1:$F$333,6),"-") -> 0 | K72: No | M72: Active | O72: 100550 | U72: 7.5 | V72: 45350 | W72: =IFERROR(V72-TODAY(),"") -> -743 | X72: =IF(SOWS[[#This Row],[Days to Contract End]]<=90,"R",IF(AND(SOWS[[#This Row],[Days to Contract End]]<180),"A","G")) -> R
B73: VNA | C73: Computex Technology Solutions - Dresser | D73: Infrastructure | E73: SOW | F73: Professional Services | H73: 44512 | I73: Dresser EBS Migration | J73: =IFERROR(VLOOKUP(C73,'QB Consolidated Contacts'!$A$1:$F$333,6),"-") -> 0 | K73: Yes | M73: Inactive | P73: Monthly | T73: 1300 | U73: ON-GOING | V73: =IFERROR(EDATE(H73,U73),"") | W73: =IFERROR(V73-TODAY(),"") | X73: =IF(SOWS[[#This Row],[Days to Contract End]]<=90,"R",IF(AND(SOWS[[#This Row],[Days to Contract End]]<180),"A","G")) -> G | Y73: Consultant will migrate client’s Oracle eBusiness Suite application and database currently residing on target entity (on-premises) application server and database server Dresser’s
B74: VNA | C74: Computex Technology Solutions - Dresser | D74: Infrastructure | E74: SOW | F74: Assessment | H74: 44850 | I74: Dresser CIM/JiT Assessment | J74: =IFERROR(VLOOKUP(C74,'QB Consolidated Contacts'!$A$1:$F$333,6),"-") -> 0 | K74: Yes | M74: Inactive | N74: Yes | O74: PO223602M | P74: Custom | S74: =55440 -> 55440 | T74: =40+40+32 -> 112 | V74: =IFERROR(EDATE(H74,U74),"") -> 44850 | W74: =IFERROR(V74-TODAY(),"") -> -1243 | X74: =IF(SOWS[[#This Row],[Days to Contract End]]<=90,"R",IF(AND(SOWS[[#This Row],[Days to Contract End]]<180),"A","G")) -> R
C75: Cynet | J75: =IFERROR(VLOOKUP(C75,'QB Consolidated Contacts'!$A$1:$F$333,6),"-") -> 0 | M75: Unknown | V75: =IFERROR(EDATE(H75,U75),"") -> 0 | W75: =IFERROR(V75-TODAY(),"") -> -46093 | X75: =IF(SOWS[[#This Row],[Days to Contract End]]<=90,"R",IF(AND(SOWS[[#This Row],[Days to Contract End]]<180),"A","G")) -> R
B76: VNA | C76: Dallas Independent School District | D76: Development | E76: Renewal | F76: Managed Services | G76: 45030 | H76: Upon Issued PO | I76: DISD- BOS Managed-Services-SOW.2023.75 Hours.docx | J76: =IFERROR(VLOOKUP(Agreements!B172,'QB Consolidated Contacts'!$A$1:$F$333,6),"-") -> - | K76: Yes | L76: Yes | V76: =IFERROR(EDATE(Agreements!U172,Agreements!V172),"") -> 0 | W76: =IFERROR(Agreements!W172-TODAY(),"") -> -46093 | X76: =IF(SOWS[[#This Row],[Days to Contract End]]<=90,"R",IF(AND(SOWS[[#This Row],[Days to Contract End]]<180),"A","G")) -> R
B77: VNA | C77: Dallas Independent School District | D77: Development | E77: Renewal | F77: Managed Services | H77: 45145 | I77: 2024 Renewal Letter KH-205563 Viscosity North America.pdf | J77: =IFERROR(VLOOKUP(C77,'QB Consolidated Contacts'!$A$1:$F$333,6),"-") -> 0 | K77: Yes | L77: Yes | M77: Active | T77: NA | U77: Annual | V77: 45535 | W77: =IFERROR(V77-TODAY(),"") -> -558 | X77: =IF(SOWS[[#This Row],[Days to Contract End]]<=90,"R",IF(AND(SOWS[[#This Row],[Days to Contract End]]<180),"A","G")) -> R | Y77: the Dallas Independent School District issued an Award for the above-referenced Request for Proposal (RFP) and it will expire August 31, 2023. The Dallas Independent School District wishes, in accordance of the award and Viscosity North America RFP response, to extend the award through August 31, 2024. The extension includes the same terms and conditions of the original Award.
B78: VNA | C78: Dallas Independent School District | D78: Development | E78: PO | F78: Managed Services | H78: 45084 | I78: BOS Managed Services | J78: =IFERROR(VLOOKUP(C78,'QB Consolidated Contacts'!$A$1:$F$333,6),"-") -> 0 | K78: No | L78: Yes | M78: Active | O78: 2023 PO-924830 | U78: 12 | V78: =IFERROR(EDATE(H78,U78),"") -> 45450 | W78: =IFERROR(V78-TODAY(),"") -> -643 | X78: =IF(SOWS[[#This Row],[Days to Contract End]]<=90,"R",IF(AND(SOWS[[#This Row],[Days to Contract End]]<180),"A","G")) -> R
B79: VNA | C79: Dallas Independent School District | D79: Infrastructure | E79: SOW | F79: Managed Services | H79: 45030 | I79: BOS Phase-3 | J79: =IFERROR(VLOOKUP(C79,'QB Consolidated Contacts'!$A$1:$F$333,6),"-") -> 0 | K79: No | M79: Expired | N79: Yes | P79: Monthly | T79: 660 | V79: =IFERROR(EDATE(H79,U79),"") -> 45030 | W79: =IFERROR(V79-TODAY(),"") -> -1063 | X79: =IF(SOWS[[#This Row],[Days to Contract End]]<=90,"R",IF(AND(SOWS[[#This Row],[Days to Contract End]]<180),"A","G")) -> R | Y79: Upon completion of this statement of work (SOW), Consultant and Client deliver a design, documentation, updated, and working application of the BOS budget management system.
B80: VNA | C80: Dallas Independent School District | D80: Infrastructure | E80: PO | F80: Professional Services | H80: 44649 | I80: License Assessment - 2022 | J80: =IFERROR(VLOOKUP(C80,'QB Consolidated Contacts'!$A$1:$F$333,6),"-") -> 0 | K80: No | M80: Inactive | N80: Yes | O80: 862363 | P80: Custom | T80: 144 | U80: ON-GOING | V80: =IFERROR(EDATE(H80,U80),"") | W80: =IFERROR(V80-TODAY(),"") | X80: =IF(SOWS[[#This Row],[Days to Contract End]]<=90,"R",IF(AND(SOWS[[#This Row],[Days to Contract End]]<180),"A","G")) -> G | Y80: Perform a license review of their current footprint for their E-Business Suite, application, and, and database tier.
B81: VNA | C81: Dallas Independent School District | D81: Infrastructure | E81: SOW | F81: Professional Services | H81: Unknown | I81: Apex Services & Support | J81: =IFERROR(VLOOKUP(C81,'QB Consolidated Contacts'!$A$1:$F$333,6),"-") -> 0 | K81: Yes | M81: Unknown | N81: Yes | T81: 150 Hrs/Quarter | U81: 12 | V81: 45473 | W81: =IFERROR(V81-TODAY(),"") -> -620 | X81: =IF(SOWS[[#This Row],[Days to Contract End]]<=90,"R",IF(AND(SOWS[[#This Row],[Days to Contract End]]<180),"A","G")) -> R
B82: VNA | C82: Dallas Independent School District | D82: Infrastructure | E82: PO | F82: AOP Renewal | H82: 45076 | I82: APEX Office Print - On-premises Gold | J82: =IFERROR(VLOOKUP(C82,'QB Consolidated Contacts'!$A$1:$F$333,6),"-") -> 0 | K82: Yes | M82: Active | N82: Yes | P82: Custom | U82: 12 | V82: =IFERROR(EDATE(H82,U82),"") -> 45442 | W82: =IFERROR(V82-TODAY(),"") -> -651 | X82: =IF(SOWS[[#This Row],[Days to Contract End]]<=90,"R",IF(AND(SOWS[[#This Row],[Days to Contract End]]<180),"A","G")) -> R
B83: VNA | C83: Dallas Independent School District | D83: Development | E83: PO | F83: Professional Services | H83: 45200 | I83: BOS - Fusion Integration | J83: =IFERROR(VLOOKUP(C83,'QB Consolidated Contacts'!$A$1:$F$333,6),"-") -> 0 | K83: No | L83: Yes | M83: Active | O83: 933851 | U83: 12 | V83: 45565 | W83: =IFERROR(V83-TODAY(),"") -> -528 | X83: =IF(SOWS[[#This Row],[Days to Contract End]]<=90,"R",IF(AND(SOWS[[#This Row],[Days to Contract End]]<180),"A","G")) -> R
B84: VNA | C84: Dallas Independent School District | D84: Infrastructure | E84: PO | F84: Managed Services | H84: 43831 | I84: BOS Managed Services | J84: =IFERROR(VLOOKUP(C84,'QB Consolidated Contacts'!$A$1:$F$333,6),"-") -> 0 | K84: No | M84: Expired | N84: Yes | P84: Custom | T84: 100 | U84: 24 | V84: =IFERROR(EDATE(H84,U84),"") -> 44562 | W84: =IFERROR(V84-TODAY(),"") -> -1531 | X84: =IF(SOWS[[#This Row],[Days to Contract End]]<=90,"R",IF(AND(SOWS[[#This Row],[Days to Contract End]]<180),"A","G")) -> R | Y84: Scope and Tasks:_x000D_ The scope and requirements are categorized into these phases:_x000D_ 1. Support Hours (100 hours per Quarter)_x000D_ 2. Overage and Out-of-Scope Support
B85: VNA | C85: Dominion Questar | D85: Development | E85: PO | F85: Managed Services | H85: 44742 | I85: 50162797 DEUWI DOT GAS Purchase Order.Executed PO.12MOS (see linked PO) | J85: ramon.rammell@do minionenergy.com | K85: Yes | L85: No | M85: Active | N85: Yes | O85: 50162797 | P85: Monthly | T85: 2080 | V85: =IFERROR(EDATE(H85,U85),"") -> 44742 | W85: =IFERROR(V85-TODAY(),"") -> -1351 | X85: =IF(SOWS[[#This Row],[Days to Contract End]]<=90,"R",IF(AND(SOWS[[#This Row],[Days to Contract End]]<180),"A","G")) -> R | Y85: 12 Month- Staff Augmentation
B86: VNA | C86: Dominion Questar | D86: Development | E86: PO | F86: Managed Services | H86: 44497 | I86: 50162702 DEQP Mobile Pipeline- Staff Aug-Purchase Order.Executed PO6MOS. (see linked PO) | J86: ramon.rammell@do minionenergy.com | K86: Yes | L86: No | M86: Active | N86: Yes | O86: 50162702 | P86: Monthly | T86: 1040 | V86: =IFERROR(EDATE(H86,U86),"") -> 44497 | W86: =IFERROR(V86-TODAY(),"") -> -1596 | X86: =IF(SOWS[[#This Row],[Days to Contract End]]<=90,"R",IF(AND(SOWS[[#This Row],[Days to Contract End]]<180),"A","G")) -> R | Y86: Oracle, APEX and PL/SQL Support- SIX MONTH TERM
B87: VNA | C87: Drill Tech Drilling & Shoring, Inc. | D87: Development | E87: SOW | F87: Professional Services | H87: 45523 | I87: VNA SOW Phase 1 - drilltech SOW oracle vna v2.2.2 2024 07 30.FINAL.docx.pdf | J87: =IFERROR(VLOOKUP(C87,'QB Consolidated Contacts'!$A$1:$F$333,6),"-") -> 0 | K87: Yes | L87: Yes | M87: Active | U87: 8 | V87: =IFERROR(EDATE(H87,U87),"")+11 -> 45777 | W87: =IFERROR(V87-TODAY(),"") -> -316 | X87: =IF(SOWS[[#This Row],[Days to Contract End]]<=90,"R",IF(AND(SOWS[[#This Row],[Days to Contract End]]<180),"A","G")) -> R
B88: VNA | C88: Drill Tech Drilling & Shoring, Inc. | D88: Development | E88: SOW | F88: Professional Services | H88: 45885 | I88: VNA SOW Long Term Rate Card v2.3.docx.pdf | J88: =IFERROR(VLOOKUP(C88,'QB Consolidated Contacts'!$A$1:$F$333,6),"-") -> 0 | K88: Yes | L88: Yes | M88: Active | U88: TBD | V88: =IFERROR(EDATE(H88,U88),"") | W88: =IFERROR(V88-TODAY(),"") | X88: =IF(SOWS[[#This Row],[Days to Contract End]]<=90,"R",IF(AND(SOWS[[#This Row],[Days to Contract End]]<180),"A","G")) -> G
B89: VNA | C89: Excellus | D89: Development | E89: SOW | F89: Professional Services | H89: 44816 | I89: Oracle XMLDB Review | J89: =IFERROR(VLOOKUP(C89,'QB Consolidated Contacts'!$A$1:$F$333,6),"-") -> 0 | K89: Yes | M89: Expired | P89: Custom | T89: 60 | U89: 3 | V89: =IFERROR(EOMONTH(H89,U89),"") -> 44926 | W89: =IFERROR(V89-TODAY(),"") -> -1167 | X89: =IF(SOWS[[#This Row],[Days to Contract End]]<=90,"R",IF(AND(SOWS[[#This Row],[Days to Contract End]]<180),"A","G")) -> R | Y89: Health Plan seeks to engage a supplier to provide practical experience using Oracle’s XML solution to review and provide recommendations on the solution proposed for the Consolidated Clinical Document
B90: VNA | C90: Excellus | D90: Development | E90: SOW | F90: Professional Services | H90: 44578 | I90: APEX Forms | J90: =IFERROR(VLOOKUP(C90,'QB Consolidated Contacts'!$A$1:$F$333,6),"-") -> 0 | K90: Yes | M90: Expired | P90: Daily | T90: 640 | U90: 11 | V90: =IFERROR(EOMONTH(H90,U90),"") -> 44926 | W90: =IFERROR(V90-TODAY(),"") -> -1167 | X90: =IF(SOWS[[#This Row],[Days to Contract End]]<=90,"R",IF(AND(SOWS[[#This Row],[Days to Contract End]]<180),"A","G")) -> R | Y90: Creation of 25 APEX forms
B91: VT | C91: Florida Realtors | D91: Infrastructure | E91: SOW | F91: Managed Services | H91: 44775 | I91: Florida Realtors Monitoring Support Services | J91: =IFERROR(VLOOKUP(C91,'QB Consolidated Contacts'!$A$1:$F$333,6),"-") -> 0 | K91: Yes | M91: Active | P91: Monthly | S91: 479200 | T91: $2,000/month | U91: ON-GOING | V91: =IFERROR(EDATE(H91,U91),"") | W91: =IFERROR(V91-TODAY(),"") | X91: =IF(SOWS[[#This Row],[Days to Contract End]]<=90,"R",IF(AND(SOWS[[#This Row],[Days to Contract End]]<180),"A","G")) -> G
B92: VT | C92: FNF | D92: Infrastructure | E92: SOW | F92: Managed Services | H92: 44294 | I92: 19c Upgrade | J92: =IFERROR(VLOOKUP(C92,'QB Consolidated Contacts'!$A$1:$F$333,6),"-") -> 0 | K92: Yes | M92: Inactive | P92: Monthly | U92: ON-GOING | V92: =IFERROR(EDATE(H92,U92),"") | W92: =IFERROR(V92-TODAY(),"") | X92: =IF(SOWS[[#This Row],[Days to Contract End]]<=90,"R",IF(AND(SOWS[[#This Row],[Days to Contract End]]<180),"A","G")) -> G | Y92: Upon completion of each environment, after load test successfully completes their run (if applicable), Viscosity will submit an invoice to FNF for payment. Total project cost will not exceed $479,200
B93: VNA | C93: FNF | D93: Infrastructure | E93: SOW | F93: Managed Services | I93: Managed Services | J93: =IFERROR(VLOOKUP(C93,'QB Consolidated Contacts'!$A$1:$F$333,6),"-") -> 0 | K93: No | M93: Active | P93: Monthly | V93: =IFERROR(EDATE(H93,U93),"") -> 0 | W93: =IFERROR(V93-TODAY(),"") -> -46093 | X93: =IF(SOWS[[#This Row],[Days to Contract End]]<=90,"R",IF(AND(SOWS[[#This Row],[Days to Contract End]]<180),"A","G")) -> R | Y93: Flat fee of $78K monthly
B94: VNA | C94: Follet Content Solutions LLC (SQL Server) | D94: Infrastructure | E94: Change Order | F94: Managed Services | H94: 45490 | I94: FCS.BucketOfHoursSeparationWorkChangeOrder.7-17-24.docx | J94: David Walker | K94: Yes | L94: Yes | M94: Active | U94: 11 | V94: =IFERROR(EDATE(H94,U94),"") -> 45825 | W94: =IFERROR(V94-TODAY(),"") -> -268 | X94: =IF(SOWS[[#This Row],[Days to Contract End]]<=90,"R",IF(AND(SOWS[[#This Row],[Days to Contract End]]<180),"A","G")) -> R
B95: VNA | C95: Follet Content Solutions LLC (SQL Server) | D95: Infrastructure | E95: Change Order | F95: Managed Services | H95: 8/26/204 | I95: FCS.BucketOfHoursSeparationWorkChangeOrder.8-26-24.docx | J95: David Walker | K95: Yes | L95: Yes | M95: Active | S95: 14000 | T95: 80 Hrs | U95: 11 | V95: =IFERROR(EDATE(H95,U95),"") | W95: =IFERROR(V95-TODAY(),"") | X95: =IF(SOWS[[#This Row],[Days to Contract End]]<=90,"R",IF(AND(SOWS[[#This Row],[Days to Contract End]]<180),"A","G")) -> G
B96: VNA | C96: Follett Content Soultions LLC (SQL Server) | D96: Infrastructure | E96: SOW | F96: Managed Services | H96: 45444 | I96: Follett Content Solutions LLC Managed Services SQL Server DB Support SOW.FINAL.docx | J96: David Walker | K96: Yes | L96: Yes | M96: Active | R96: 3500 | T96: 16 Hrs/Month | U96: ON-GOING | V96: =IFERROR(EDATE(H96,U96),"") | W96: =IFERROR(V96-TODAY(),"") | X96: =IF(SOWS[[#This Row],[Days to Contract End]]<=90,"R",IF(AND(SOWS[[#This Row],[Days to Contract End]]<180),"A","G")) -> G | Y96: Thereafter, this SOW shall automatically renew for successive one (1) year terms (each a “Renewal Term”) upon Client’s written approval. Fees upon renewal shall not increase by more than 5%.
B97: VNA | C97: Follett School Solutions LLC | D97: Infrastructure | E97: SOW | F97: Professional Services | G97: 45757 | H97: 45748 | I97: VNA SOW - Follett APEX Upgrade 2025 V2.docx SIGNED | J97: =IFERROR(VLOOKUP(Agreements!B195,'QB Consolidated Contacts'!$A$1:$F$333,6),"-") -> - | K97: Yes | L97: Yes | U97: TBD | V97: =IFERROR(EDATE(Agreements!U195,Agreements!V195),"") -> 0 | W97: =IFERROR(Agreements!W195-TODAY(),"") -> -46093 | X97: =IF(SOWS[[#This Row],[Days to Contract End]]<=90,"R",IF(AND(SOWS[[#This Row],[Days to Contract End]]<180),"A","G")) -> R
B98: VT | C98: Follett School Solutions LLC | D98: Infrastructure | E98: SOW | F98: Managed Services | H98: 44748 | I98: Follett Managed Services Database Support SOW 02MAY.V4 Follett edits v1 (5.18.2022) Changes Accepted (002) | J98: David Walker | K98: Yes | L98: Yes | M98: Active | U98: TBD | V98: =IFERROR(EDATE(H98,U98),"") | W98: =IFERROR(V98-TODAY(),"") | X98: =IF(SOWS[[#This Row],[Days to Contract End]]<=90,"R",IF(AND(SOWS[[#This Row],[Days to Contract End]]<180),"A","G")) -> G
B99: VT | C99: Follett School Solutions LLC | D99: Infrastructure | E99: SOW | F99: MS Change Order | H99: 45324 | I99: Follett School Solutions LLC MS Change Order Jan 2024 FINAL.docx | J99: David Walker | K99: Yes | L99: Yes | M99: Active | P99: Monthly | T99: 32 Hrs/Month | U99: 12 | V99: =IFERROR(EDATE(H99,U99),"") -> 45690 | W99: =IFERROR(V99-TODAY(),"") -> -403 | X99: =IF(SOWS[[#This Row],[Days to Contract End]]<=90,"R",IF(AND(SOWS[[#This Row],[Days to Contract End]]<180),"A","G")) -> R | Y99: Thereafter, this SOW shall automatically renew for successive one (1) year terms (each a “Renewal Term”) upon Client’s written approval. Fees upon renewal shall not increase by more than 5%.
B100: VNA | C100: Globalstar | D100: Infrastructure | E100: SOW | F100: Professional Services | G100: 45016 | H100: 45031 | I100: Globalstar_SOW_for_ODA_Implementation.V3.03102023.docx | J100: =IFERROR(VLOOKUP(C100,'QB Consolidated Contacts'!$A$1:$F$333,6),"-") -> 0 | K100: Yes | L100: Yes | M100: Active | P100: Monthly | Q100: Net 30 | S100: 94775 | T100: 477 | U100: Block of Hours | V100: =IFERROR(EDATE(H100,U100),"") | W100: =IFERROR(V100-TODAY(),"") | X100: =IF(SOWS[[#This Row],[Days to Contract End]]<=90,"R",IF(AND(SOWS[[#This Row],[Days to Contract End]]<180),"A","G")) -> G
...

Sheet MS Dev Renewals
A1: Work Type | B1: (Multiple Items)
A2: R.A.G. Status | B2: (Multiple Items)
A3: Status | B3: (Multiple Items)
A5: Row Labels
A6: ABC Fitness Solutions, LLC
A7: American Heart Association, Inc. | B7: DEAD
A8: Captial Title of Texas
A9: COE
A10: Dallas Independent School District
A11: IdenTrust
A12: Identrust Db Patching 2022
A13: 45175
A14: IdenTrust DB Patching 2023
A15: 45506
A16: IdenTrust Retainer Services - Schedule A VT - Signed
A17: 44418
A18: STGenetics
A19: AMERICAN LEATHER HOLDINGS, LLC
A20: Dominion Energy Services, Inc.

Sheet Settings & Instructions
A1: Contract Type | B1: Description | C1: Work Type | D1: Line of Business | E1: Status | F1: Term and Renewal | I1: vnacontratsadministration@viscosityna.com
A2: Addendum | B2: Consultant Service Agreement | C2: Agreement | D2: Development | E2: Active | F2: Evergreen
A3: Change Order | B3: Master Service Agreement OR Managed Service Agreement | C3: Amendment | D3: Infrastructure | E3: Expired | F3: Fixed-Term
A4: CSA | B4: Non-Disclosure Agreement | C4: AOP Renewal | D4: Unknown | E4: Inactive | F4: Mutal Agreement
A5: Fifth Amendment Agreement | B5: Statement of Work | C5: Assessment | D5: Project Management | E5: Pending | F5: Evergreen w/ Price Adjust.
A6: HIPAA | C6: Managed Services | D6: Legal Agreement | E6: Unknown | F6: Conditional Renewal
A7: Limited Services Agreement | C7: Professional Services | E7: Redlines
A8: MBE_WBE Statement | B8: SMB Certificate | C8: Purchase Order
A9: MCSA | B9: Master Contractor Services Agreement | C9: Partnership
A10: MSA | C10: Retainer Services
A11: NDA | C11: Staff Aug
A12: PO | C12: Unknown
A13: Renewal | C13: Change Order
A14: Retainer Services | C14: Addendum
A15: SOW | C15: Order Document
A16: Sales & Use Tax Addendum
A17: VAR Agreement
A18: Referral Agreement
A19: Resell Agreement

Sheet Software | Licensing Agreements
B1: Software | Licensing Agreements
B2: Business | C2: Client | D2: Product | E2: Contract Name | F2: Signed Copy | G2: Status | H2: Requires PO | I2: Notes
C3: AMDI | D3: AMP | E3: n/a | G3: Pending | I3: New Customers, will be in production this year 2024.
C4: American Leather | D4: AMP | E4: n/a | G4: Active | I4: The project paused, but they’re in production; not sure as of when.
C5: NGCSI | D5: AMP | E5: n/a | G5: Active | I5: Recent /New customer, they went to production recently sometime around June 2024.
C6: SMRTL | D6: AMP | E6: n/a | G6: Pending | I6: Recent/New customers, will be in production soon June 2024
C7: STgenetics | D7: AMP | E7: n/a | G7: Unknown | I7: I am not sure if we ever billed them for AMP or if they are aware they have to pay for AMP subscription and do not know next steps to rectify as years have passed
C8: COE | D8: AMP | E8: n/a- not seeing it list in SOWs either | G8: Unknown | I8: I am not sure if we ever billed them for AMP or if they are aware they have to pay for AMP subscription and do not know next steps to rectify as years have passed.
C9: Region 10 | D9: AMP | E9: Pending David Wangs Approval | G9: Pending | I9: Recent/New customer, will be in production soon June 2024.
B10: VNA | C10: Capital Title of Texas | D10: AMP | E10: Viscosity_AMP_EULA -CTOT.pdf | F10: No Signed Copy | G10: Unknown | I10: I am not sure if we ever billed them for AMP or if they are aware they have to pay for AMP subscription and do not know next steps to rectify as years have passed.
B11: VNA | C11: National Mango Board | D11: AMP | E11: Viscosity_AMP_EULA -NMB Internal.04302021.pdf | F11: No Signed Copy | G11: Active | I11: They have been in production for a while, and we know for sure they are paying their subscription.
B12: VNA | C12: Sherwin Williams | D12: AMP | E12: Viscosity_AMP_Software_License_Agreement_08112020.docx | F12: Yes - DocuSign | G12: Active | I12: They have been in production for a while, and we know for sure they are paying their subscription.

Sheet Contracts
B2: Client | C2: Contact | D2: Line of Business | E2: Contract Type | F2: Work Type | G2: Project Manager | H2: Description | I2: Signed Copy | J2: DocuSign | K2: Status | L2: Business | M2: Requires PO | N2: PO # | O2: Cycle | P2: Payment Terms | Q2: Monthly Budget | R2: Total Budget | S2: Block Of Hours | T2: Effective Date | U2: Duration (Months) | V2: Expiration Date | W2: Days to Contract End | X2: General Liability Insurance | Y2: COI Requirement | Z2: GL Aggregate Limits | AA2: GL per Occurrence | AB2: Workers Compensation | AC2: Employers Liability | AD2: Umbrella Aggregate | AE2: Umbrella per Occurrence | AF2: Cyber Aggregate | AG2: Cyber per Occurrence | AH2: Professional Liability (E&O) | AI2: Property in Transit | AJ2: Employee Theft of Client Property | AK2: Products/Completed Operations | AL2: Personal & Advertising Injury | AM2: Fire Legal Liability Injury | AN2: Medical Payments | AO2: Auto Insurance Combined Single Limit | AP2: Auto Insurance per Occurrence2 | AQ2: R.A.G. Status | AR2: Notes | AT2: Yes | AU2: No
B3: ABC Fitness Solutions, LLC | C3: =IFERROR(VLOOKUP(B3,'QB Consolidated Contacts'!$A$1:$F$333,6),"-") -> Prakash Rikhilal | E3: MSA | F3: Agreement | H3: Master Services Agreement | I3: Yes | K3: Active | L3: VNA | O3: - | S3: - | T3: 44053 | U3: ON-GOING | V3: =IFERROR(EDATE(T3,U3),"") | W3: =IFERROR(V3-TODAY(),"") | X3: Yes | Z3: $1M | AA3: $1M | AD3: - | AF3: - | AG3: - | AP3: $100K | AQ3: =IF(ALL_02FEB2024[[#This Row],[Days to Contract End]]<=90,"R",IF(AND(ALL_02FEB2024[[#This Row],[Days to Contract End]]<180),"A","G")) -> G
B4: ABC Fitness Solutions, LLC | C4: =IFERROR(VLOOKUP(B4,'QB Consolidated Contacts'!$A$1:$F$333,6),"-") -> Prakash Rikhilal | D4: Infrastructure | E4: SOW | F4: Managed Services | G4: Melissa Schuetter | H4: VNA.ABC.Managed Services SoW.EDW Monitoring.Offshore.2023July.docx | I4: Yes | J4: Yes | K4: Active | L4: VNA | N4: PO22-24864 | T4: 45108 | U4: 6 | V4: =IFERROR(EDATE(T4,U4),"") -> 45292 | W4: =IFERROR(V4-TODAY(),"") -> -801 | AQ4: =IF(ALL_02FEB2024[[#This Row],[Days to Contract End]]<=90,"R",IF(AND(ALL_02FEB2024[[#This Row],[Days to Contract End]]<180),"A","G")) -> R
B5: ABC Fitness Solutions, LLC | C5: =IFERROR(VLOOKUP(B5,'QB Consolidated Contacts'!$A$1:$F$333,6),"-") -> Prakash Rikhilal | D5: Development | E5: SOW | F5: Managed Services | H5: Offshore - Monitoring & Support | I5: Yes | K5: Expired | L5: VT | M5: Yes | O5: Monthly | Q5: 13410 | R5: =ALL_02FEB2024[[#This Row],[Monthly Budget]]*12 -> 160920 | S5: =106+106+10 -> 222 | T5: 44739 | U5: 12 | V5: =IFERROR(EDATE(T5,U5),"") -> 45104 | W5: =IFERROR(V5-TODAY(),"") -> -989 | X5: No | AA5: - | AD5: - | AF5: - | AG5: - | AP5: - | AQ5: =IF(ALL_02FEB2024[[#This Row],[Days to Contract End]]<=90,"R",IF(AND(ALL_02FEB2024[[#This Row],[Days to Contract End]]<180),"A","G")) -> R
B6: ABC Fitness Solutions, LLC | C6: =IFERROR(VLOOKUP(B6,'QB Consolidated Contacts'!$A$1:$F$333,6),"-") -> Prakash Rikhilal | D6: Infrastructure | E6: SOW | F6: Managed Services | G6: Melissa Schuetter | H6: Offshore - DBA Support | I6: Yes | K6: Active | L6: VNA | M6: Yes | O6: Block of Hours | Q6: 9000 | R6: =ALL_02FEB2024[[#This Row],[Monthly Budget]]*12 -> 108000 | S6: 40 hrs/week | T6: 44972 | U6: 12 | V6: =IFERROR(EDATE(T6,U6),"") -> 45337 | W6: =IFERROR(V6-TODAY(),"") -> -756 | X6: No | Z6: - | AA6: - | AD6: - | AF6: - | AG6: - | AP6: - | AQ6: =IF(ALL_02FEB2024[[#This Row],[Days to Contract End]]<=90,"R",IF(AND(ALL_02FEB2024[[#This Row],[Days to Contract End]]<180),"A","G")) -> R
B7: ABC Fitness Solutions, LLC | C7: =IFERROR(VLOOKUP(B7,'QB Consolidated Contacts'!$A$1:$F$333,6),"-") -> Prakash Rikhilal | E7: SOW | F7: Managed Services | G7: Melissa Schuetter | H7: VNA.ABC.Professional Services.SoW.2024Jan-Jun.docx | I7: Yes | J7: Yes | K7: Active | L7: VNA | T7: 45292 | U7: TBD | V7: 45658 | W7: =IFERROR(V7-TODAY(),"") -> -435 | AQ7: =IF(ALL_02FEB2024[[#This Row],[Days to Contract End]]<=90,"R",IF(AND(ALL_02FEB2024[[#This Row],[Days to Contract End]]<180),"A","G")) -> R
B8: ABC Fitness Solutions, LLC | C8: =IFERROR(VLOOKUP(B8,'QB Consolidated Contacts'!$A$1:$F$333,6),"-") -> Prakash Rikhilal | E8: SOW | F8: Managed Services | G8: Melissa Schuetter | H8: VNA.ABC.Support Services SoW.EDW Monitoring.Offshore.2024Jan-Jun.docx | I8: Yes | J8: Yes | K8: Active | L8: VNA | T8: 45292 | U8: 6 | V8: =IFERROR(EDATE(T8,U8),"") -> 45474 | W8: =IFERROR(V8-TODAY(),"") -> -619 | AQ8: =IF(ALL_02FEB2024[[#This Row],[Days to Contract End]]<=90,"R",IF(AND(ALL_02FEB2024[[#This Row],[Days to Contract End]]<180),"A","G")) -> R
B9: ABC Fitness Solutions, LLC | C9: =IFERROR(VLOOKUP(B9,'QB Consolidated Contacts'!$A$1:$F$333,6),"-") -> Prakash Rikhilal | E9: SOW | F9: Managed Services | G9: Melissa Schuetter | H9: VNA.ABC.Support Services SoW.Offshore DBA.2024Mar-Dec.docx | I9: Yes | J9: Yes | K9: Active | L9: VNA | T9: 45352 | U9: 10 | V9: 45657 | W9: =IFERROR(V9-TODAY(),"") -> -436 | AQ9: =IF(ALL_02FEB2024[[#This Row],[Days to Contract End]]<=90,"R",IF(AND(ALL_02FEB2024[[#This Row],[Days to Contract End]]<180),"A","G")) -> R
B10: ABC Fitness Solutions, LLC | C10: =IFERROR(VLOOKUP(B10,'QB Consolidated Contacts'!$A$1:$F$333,6),"-") -> Prakash Rikhilal | D10: Infrastructure | E10: SOW | F10: Professional Services | G10: Melissa Schuetter | H10: ABC - Professional Services | I10: Yes | K10: Active | L10: VNA | M10: Yes | N10: PO23-29200 | O10: Block of Hours | R10: 91000 | S10: 520 | T10: 44621 | U10: ON-GOING | V10: =IFERROR(EDATE(T10,U10),"") | W10: =IFERROR(V10-TODAY(),"") | X10: No | Z10: - | AA10: - | AD10: - | AF10: - | AG10: - | AP10: - | AQ10: =IF(ALL_02FEB2024[[#This Row],[Days to Contract End]]<=90,"R",IF(AND(ALL_02FEB2024[[#This Row],[Days to Contract End]]<180),"A","G")) -> G
B11: ABC Fitness Solutions, LLC | C11: =IFERROR(VLOOKUP(B11,'QB Consolidated Contacts'!$A$1:$F$333,6),"-") -> Prakash Rikhilal | E11: SOW | F11: Professional Services | G11: Melissa Schuetter | H11: VNA.ABC_DBA Professional Services_SoW_May 2023.docx | I11: Yes | J11: Yes | K11: Active | L11: VNA | S11: 60/week | T11: 45069 | U11: ON-GOING | V11: =IFERROR(EDATE(T11,U11),"") | W11: =IFERROR(V11-TODAY(),"") | AQ11: =IF(ALL_02FEB2024[[#This Row],[Days to Contract End]]<=90,"R",IF(AND(ALL_02FEB2024[[#This Row],[Days to Contract End]]<180),"A","G")) -> G
B12: ABC Fitness Solutions, LLC | C12: =IFERROR(VLOOKUP(B12,'QB Consolidated Contacts'!$A$1:$F$333,6),"-") -> Prakash Rikhilal | E12: SOW | F12: Professional Services | G12: Melissa Schuetter | H12: VNA.ABC_Professional Services_SoW_Q4 2023.docx | I12: Yes | J12: Yes | K12: Active | L12: VNA | M12: Yes | S12: =332+24 -> 356 | T12: 45214 | U12: TBD | V12: =IFERROR(EDATE(T12,U12),"") | W12: =IFERROR(V12-TODAY(),"") | AQ12: =IF(ALL_02FEB2024[[#This Row],[Days to Contract End]]<=90,"R",IF(AND(ALL_02FEB2024[[#This Row],[Days to Contract End]]<180),"A","G")) -> G
B13: ABC Fitness Solutions, LLC | C13: =IFERROR(VLOOKUP(B13,'QB Consolidated Contacts'!$A$1:$F$333,6),"-") -> Prakash Rikhilal | D13: Infrastructure | E13: SOW | F13: Professional Services | G13: Melissa Schuetter | H13: ABC-Fitness BI - Azure DevOps Integration | I13: Yes | K13: Active | L13: VNA | M13: Yes | O13: Block of Hours | R13: 229600 | S13: 1312 | T13: 44586 | U13: ON-GOING | V13: =IFERROR(EDATE(T13,U13),"") | W13: =IFERROR(V13-TODAY(),"") | X13: No | Z13: - | AA13: - | AD13: - | AF13: - | AG13: - | AP13: - | AQ13: =IF(ALL_02FEB2024[[#This Row],[Days to Contract End]]<=90,"R",IF(AND(ALL_02FEB2024[[#This Row],[Days to Contract End]]<180),"A","G")) -> G
B14: ACGI Software | C14: =IFERROR(VLOOKUP(B14,'QB Consolidated Contacts'!$A$1:$F$333,6),"-") -> Kevin Hostintler | E14: MSA | F14: Agreement | H14: Master Services Agreement | I14: No | K14: Inactive | L14: VNA | O14: - | S14: - | T14: 43252 | U14: ON-GOING | V14: =IFERROR(EDATE(T14,U14),"") | W14: =IFERROR(V14-TODAY(),"") | X14: Yes | Z14: $1M | AA14: $1M | AD14: - | AF14: - | AG14: - | AP14: $100K | AQ14: =IF(ALL_02FEB2024[[#This Row],[Days to Contract End]]<=90,"R",IF(AND(ALL_02FEB2024[[#This Row],[Days to Contract End]]<180),"A","G")) -> G | AR14: Last billed in 2018
B15: ACGI Software | C15: =IFERROR(VLOOKUP(B15,'QB Consolidated Contacts'!$A$1:$F$333,6),"-") -> Kevin Hostintler | D15: Infrastructure | E15: SOW | F15: Managed Services | H15: On Demand Consulting - Signed | I15: Yes | K15: Inactive | L15: VNA | O15: - | S15: 135/hour | T15: 44713 | U15: ON-GOING | V15: =IFERROR(EDATE(T15,U15),"") | W15: =IFERROR(V15-TODAY(),"") | X15: No | Z15: - | AA15: - | AD15: - | AF15: - | AG15: - | AP15: - | AQ15: =IF(ALL_02FEB2024[[#This Row],[Days to Contract End]]<=90,"R",IF(AND(ALL_02FEB2024[[#This Row],[Days to Contract End]]<180),"A","G")) -> G
B16: Airport Terminal Services | C16: =IFERROR(VLOOKUP(B16,'QB Consolidated Contacts'!$A$1:$F$333,6),"-") -> Christina Green | D16: Infrastructure | E16: SOW | F16: Managed Services | H16: Oracle ERP Managed Services | I16: Yes | K16: Inactive | L16: VNA | O16: Monthly | Q16: 4500 | S16: 30 | T16: 43466 | U16: ON-GOING | V16: =IFERROR(EDATE(T16,U16),"") | W16: =IFERROR(V16-TODAY(),"") | X16: No | Z16: - | AA16: - | AD16: - | AF16: - | AG16: - | AP16: - | AQ16: =IF(ALL_02FEB2024[[#This Row],[Days to Contract End]]<=90,"R",IF(AND(ALL_02FEB2024[[#This Row],[Days to Contract End]]<180),"A","G")) -> G
B17: American Heart Association, Inc. | C17: =IFERROR(VLOOKUP(B17,'QB Consolidated Contacts'!$A$1:$F$333,6),"-") -> Roger Santone | D17: Infrastructure | E17: SOW | F17: Managed Services | H17: DBA Managed Services | I17: Yes | K17: Inactive | L17: VNA | O17: Monthly | Q17: 5000 | R17: =ALL_02FEB2024[[#This Row],[Monthly Budget]]*12 -> 60000 | S17: 30 | T17: 44743 | U17: Expired | V17: =IFERROR(EOMONTH(T17,U17),"") | W17: =IFERROR(V17-TODAY(),"") | X17: No | Z17: - | AA17: - | AD17: - | AF17: - | AG17: - | AP17: - | AQ17: =IF(ALL_02FEB2024[[#This Row],[Days to Contract End]]<=90,"R",IF(AND(ALL_02FEB2024[[#This Row],[Days to Contract End]]<180),"A","G")) -> G
B18: American Leather | C18: =IFERROR(VLOOKUP(B18,'QB Consolidated Contacts'!$A$1:$F$333,6),"-") -> Roger Santone | E18: MSA | F18: Agreement | H18: VNA.MSA.AMERICAN_LEATHER.2023.docx | I18: Yes | J18: Yes | K18: Active | L18: VNA | T18: 45139 | U18: ON-GOING | V18: =IFERROR(EDATE(T18,U18),"") | W18: =IFERROR(V18-TODAY(),"") | AQ18: =IF(ALL_02FEB2024[[#This Row],[Days to Contract End]]<=90,"R",IF(AND(ALL_02FEB2024[[#This Row],[Days to Contract End]]<180),"A","G")) -> G
B19: American Leather | C19: =IFERROR(VLOOKUP(B19,'QB Consolidated Contacts'!$A$1:$F$333,6),"-") -> Roger Santone | D19: Development | E19: SOW | F19: Professional Services | G19: Sabika Rizvi | H19: SOW.American_Leather.Web_Services.SOW.ORACLE_EBS.AUG2023.docx | I19: Yes | J19: Yes | K19: Active | L19: VNA | T19: 45160 | U19: TBD | V19: =IFERROR(EDATE(T19,U19),"") | W19: =IFERROR(V19-TODAY(),"") | AQ19: =IF(ALL_02FEB2024[[#This Row],[Days to Contract End]]<=90,"R",IF(AND(ALL_02FEB2024[[#This Row],[Days to Contract End]]<180),"A","G")) -> G
B20: American Leather | C20: =IFERROR(VLOOKUP(B20,'QB Consolidated Contacts'!$A$1:$F$333,6),"-") -> Roger Santone | D20: Development | E20: SOW | F20: Professional Services | G20: Beatriz Aguirre | H20: SOW_HRMS_and_Financial_Archiving..Executed | I20: Yes | J20: Yes | K20: Active | L20: VNA | M20: Yes | T20: 45152 | U20: TBD | V20: 45535 | W20: =IFERROR(V20-TODAY(),"") -> -558 | AQ20: =IF(ALL_02FEB2024[[#This Row],[Days to Contract End]]<=90,"R",IF(AND(ALL_02FEB2024[[#This Row],[Days to Contract End]]<180),"A","G")) -> R
B21: American Leather | C21: =IFERROR(VLOOKUP(B21,'QB Consolidated Contacts'!$A$1:$F$333,6),"-") -> Roger Santone | D21: Development | E21: SOW | F21: Professional Services | G21: Leisa Pitner | H21: APEX Staff Augmentation- Transfer Views from Oracle to Alternative Data Store | I21: Yes | J21: Yes | K21: Active | L21: VNA | S21: 80 | T21: 45118 | U21: TBD | V21: =IFERROR(EDATE(T21,U21),"") | W21: =IFERROR(V21-TODAY(),"") | AQ21: =IF(ALL_02FEB2024[[#This Row],[Days to Contract End]]<=90,"R",IF(AND(ALL_02FEB2024[[#This Row],[Days to Contract End]]<180),"A","G")) -> G
B22: American Leather | C22: =IFERROR(VLOOKUP(B22,'QB Consolidated Contacts'!$A$1:$F$333,6),"-") -> Roger Santone | D22: Development | E22: SOW | F22: Professional Services | G22: Leisa Pitner | H22: SOW.AMERICAN LEATHER.VNA STAFF AUGUMENTATION.APR2023.docx | I22: Yes | J22: Yes | K22: Active | L22: VNA | O22: Monthly | P22: - | Q22: 12250 | R22: =ALL_02FEB2024[[#This Row],[Monthly Budget]]*12 -> 147000 | S22: =16*12 -> 192 | T22: 45033 | U22: 12 | V22: =IFERROR(EDATE(T22,U22),"") -> 45399 | W22: =IFERROR(V22-TODAY(),"") -> -694 | AQ22: =IF(ALL_02FEB2024[[#This Row],[Days to Contract End]]<=90,"R",IF(AND(ALL_02FEB2024[[#This Row],[Days to Contract End]]<180),"A","G")) -> R
B23: American Heart Association, Inc. | C23: =IFERROR(VLOOKUP(B23,'QB Consolidated Contacts'!$A$1:$F$333,6),"-") -> Roger Santone | E23: MSA | F23: Agreement | H23: Master Services Agreement | I23: Yes | K23: Active | L23: VNA | O23: - | S23: - | T23: 42880 | U23: ON-GOING | V23: =IFERROR(EDATE(T23,U23),"") | W23: =IFERROR(V23-TODAY(),"") | X23: Yes | Z23: $2M | AA23: $1M | AD23: $5M | AF23: $6M | AG23: $1M | AP23: $1M | AQ23: =IF(ALL_02FEB2024[[#This Row],[Days to Contract End]]<=90,"R",IF(AND(ALL_02FEB2024[[#This Row],[Days to Contract End]]<180),"A","G")) -> G
B24: AssetWorks | C24: =IFERROR(VLOOKUP(B24,'QB Consolidated Contacts'!$A$1:$F$333,6),"-") -> 0 | D24: Infrastructure | E24: SOW | F24: Professional Services | H24: Asset Works Database and AOP Assessment SOW | I24: No | K24: Pending | L24: VNA | T24: 45036 | V24: =IFERROR(EDATE(T24,U24),"") -> 45036 | W24: 2693 | AQ24: =IF(ALL_02FEB2024[[#This Row],[Days to Contract End]]<=90,"R",IF(AND(ALL_02FEB2024[[#This Row],[Days to Contract End]]<180),"A","G")) -> G
B25: Athenian Group, LLC | C25: =IFERROR(VLOOKUP(B25,'QB Consolidated Contacts'!$A$1:$F$333,6),"-") -> 0 | E25: NDA | F25: Agreement | H25: Non-Disclosure Agreement | I25: Yes | K25: Active | L25: VNA | T25: 44883 | U25: 24 | V25: =IFERROR(EDATE(T25,U25),"") -> 45614 | W25: =IFERROR(V25-TODAY(),"") -> -479 | X25: No | AQ25: =IF(ALL_02FEB2024[[#This Row],[Days to Contract End]]<=90,"R",IF(AND(ALL_02FEB2024[[#This Row],[Days to Contract End]]<180),"A","G")) -> R
B26: Athenian Group, LLC - LA Metro | C26: =IFERROR(VLOOKUP(B26,'QB Consolidated Contacts'!$A$1:$F$333,6),"-") -> 0 | E26: MSA | F26: Agreement | H26: Master Services Agreement | I26: Yes | K26: Active | L26: VNA | T26: 45016 | U26: 36 | V26: =IFERROR(EDATE(T26,U26),"") -> 46112 | W26: =IFERROR(V26-TODAY(),"") -> 19 | AQ26: =IF(ALL_02FEB2024[[#This Row],[Days to Contract End]]<=90,"R",IF(AND(ALL_02FEB2024[[#This Row],[Days to Contract End]]<180),"A","G")) -> R
B27: Athenian Group, LLC - LA Metro | C27: =IFERROR(VLOOKUP(B27,'QB Consolidated Contacts'!$A$1:$F$333,6),"-") -> 0 | D27: Development | E27: SOW | F27: Professional Services | H27: Data Input/Automation POV | I27: Yes | K27: Expired | L27: VNA | T27: 45012 | U27: 2 | V27: =IFERROR(EDATE(T27,U27),"") -> 45073 | W27: =IFERROR(V27-TODAY(),"") -> -1020 | AQ27: =IF(ALL_02FEB2024[[#This Row],[Days to Contract End]]<=90,"R",IF(AND(ALL_02FEB2024[[#This Row],[Days to Contract End]]<180),"A","G")) -> R
B28: BMW | C28: =IFERROR(VLOOKUP(B28,'QB Consolidated Contacts'!$A$1:$F$333,6),"-") -> 0 | E28: MSA | F28: Agreement | H28: Master Services Agreement | I28: No | K28: Inactive | L28: VNA | O28: - | S28: - | V28: =IFERROR(EDATE(T28,U28),"") -> 0 | W28: =IFERROR(V28-TODAY(),"") -> -46093 | X28: Yes | Z28: $5M | AA28: $5M | AB28: Statutory Limits | AC28: $1M | AP28: $1M | AQ28: =IF(ALL_02FEB2024[[#This Row],[Days to Contract End]]<=90,"R",IF(AND(ALL_02FEB2024[[#This Row],[Days to Contract End]]<180),"A","G")) -> R | AR28: We assumed this client when we bought Sumner Technologies in 2018; I went through some of that stuff and can’t find anything.
B29: BMW | C29: =IFERROR(VLOOKUP(B29,'QB Consolidated Contacts'!$A$1:$F$333,6),"-") -> 0 | E29: NDA | F29: Agreement | H29: Non-Disclosure Agreement | I29: No | K29: Inactive | L29: VNA | V29: =IFERROR(EDATE(T29,U29),"") -> 0 | W29: =IFERROR(V29-TODAY(),"") -> -46093 | AQ29: =IF(ALL_02FEB2024[[#This Row],[Days to Contract End]]<=90,"R",IF(AND(ALL_02FEB2024[[#This Row],[Days to Contract End]]<180),"A","G")) -> R
B30: BMW | C30: =IFERROR(VLOOKUP(B30,'QB Consolidated Contacts'!$A$1:$F$333,6),"-") -> 0 | E30: PO | F30: Professional Services | H30: Sql/Apex Training.2022 | I30: No | K30: Inactive | L30: VNA | N30: F3RKHXJ | V30: =IFERROR(EDATE(T30,U30),"") -> 0 | W30: =IFERROR(V30-TODAY(),"") -> -46093 | X30: No | AQ30: =IF(ALL_02FEB2024[[#This Row],[Days to Contract End]]<=90,"R",IF(AND(ALL_02FEB2024[[#This Row],[Days to Contract End]]<180),"A","G")) -> R
B31: American Leather | C31: =IFERROR(VLOOKUP(B31,'QB Consolidated Contacts'!$A$1:$F$333,6),"-") -> Roger Santone | D31: Project Management | E31: SOW | F31: Professional Services | G31: Leisa Pitner | H31: ecommerce program manager support SOW signed 9 December 2023 | I31: Yes | J31: Yes | K31: Active | L31: VT | T31: 45634 | U31: TBD | V31: 45382 | W31: =IFERROR(V31-TODAY(),"") -> -711 | AQ31: =IF(ALL_02FEB2024[[#This Row],[Days to Contract End]]<=90,"R",IF(AND(ALL_02FEB2024[[#This Row],[Days to Contract End]]<180),"A","G")) -> R
B32: Bot Construction Limited | C32: =IFERROR(VLOOKUP(B32,'QB Consolidated Contacts'!$A$1:$F$333,6),"-") -> 0 | D32: Infrastructure | E32: SOW | F32: Professional Services | H32: Oracle Apex Timekeeping | I32: No | K32: Unknown | L32: VNA | O32: Monthly | S32: 100 | T32: 44835 | U32: 24 | V32: =IFERROR(EDATE(T32,U32),"") -> 45566 | W32: =IFERROR(V32-TODAY(),"") -> -527 | X32: No | AQ32: =IF(ALL_02FEB2024[[#This Row],[Days to Contract End]]<=90,"R",IF(AND(ALL_02FEB2024[[#This Row],[Days to Contract End]]<180),"A","G")) -> R
B33: CACI | C33: =IFERROR(VLOOKUP(B33,'QB Consolidated Contacts'!$A$1:$F$333,6),"-") -> 0 | E33: NDA | F33: Agreement | H33: CACI_Agreement.NDA.12022022 | I33: Yes | L33: VNA | T33: 44897 | U33: 36 | V33: =IFERROR(EDATE(T33,U33),"") -> 45993 | W33: =IFERROR(V33-TODAY(),"") -> -100 | AQ33: =IF(ALL_02FEB2024[[#This Row],[Days to Contract End]]<=90,"R",IF(AND(ALL_02FEB2024[[#This Row],[Days to Contract End]]<180),"A","G")) -> R
B34: CACI - LGS Labs | C34: =IFERROR(VLOOKUP(B34,'QB Consolidated Contacts'!$A$1:$F$333,6),"-") -> 0 | E34: NDA | F34: Agreement | H34: Non-Disclosure Agreement | I34: Yes | K34: Active | L34: VNA | O34: - | S34: - | T34: 44887 | U34: 36 | V34: =IFERROR(EDATE(T34,U34),"") -> 45983 | W34: =IFERROR(V34-TODAY(),"") -> -110 | X34: Yes | Z34: $2M | AA34: $1M | AB34: $500K | AK34: $1M | AL34: $1M | AM34: $300K | AN34: $10K | AO34: $1M | AQ34: =IF(ALL_02FEB2024[[#This Row],[Days to Contract End]]<=90,"R",IF(AND(ALL_02FEB2024[[#This Row],[Days to Contract End]]<180),"A","G")) -> R
B35: CACI - LGS Labs | C35: =IFERROR(VLOOKUP(B35,'QB Consolidated Contacts'!$A$1:$F$333,6),"-") -> 0 | E35: MSA | F35: Agreement | H35: Master Services Agreement | I35: No | T35: 26 | V35: =IFERROR(EDATE(T35,U35),"") -> 26 | W35: =IFERROR(V35-TODAY(),"") -> -46067 | AQ35: =IF(ALL_02FEB2024[[#This Row],[Days to Contract End]]<=90,"R",IF(AND(ALL_02FEB2024[[#This Row],[Days to Contract End]]<180),"A","G")) -> R
B36: CACI - LGS Labs | C36: =IFERROR(VLOOKUP(B36,'QB Consolidated Contacts'!$A$1:$F$333,6),"-") -> 0 | D36: Development | E36: SOW | F36: Professional Services | H36: KURT Statement of Work | I36: Yes | K36: Expired | L36: VNA | T36: 44901 | U36: 12 | V36: =IFERROR(EDATE(T36,U36),"") -> 45266 | W36: =IFERROR(V36-TODAY(),"") -> -827 | AQ36: =IF(ALL_02FEB2024[[#This Row],[Days to Contract End]]<=90,"R",IF(AND(ALL_02FEB2024[[#This Row],[Days to Contract End]]<180),"A","G")) -> R
B37: CACI - LGS Labs | C37: =IFERROR(VLOOKUP(B37,'QB Consolidated Contacts'!$A$1:$F$333,6),"-") -> 0 | D37: Development | E37: SOW | F37: Professional Services | H37: KURT Migration to AWS - 2nd Run | I37: Yes | K37: Expired | L37: VNA | T37: 44907 | U37: 12 | V37: =IFERROR(EDATE(T37,U37),"") -> 45272 | W37: =IFERROR(V37-TODAY(),"") -> -821 | AQ37: =IF(ALL_02FEB2024[[#This Row],[Days to Contract End]]<=90,"R",IF(AND(ALL_02FEB2024[[#This Row],[Days to Contract End]]<180),"A","G")) -> R | AR37: Optional Year 1 (if excersised) 12 December 2023 – 11 December 2024
B38: CACI - LGS Labs | C38: =IFERROR(VLOOKUP(B38,'QB Consolidated Contacts'!$A$1:$F$333,6),"-") -> 0 | D38: Development | E38: SOW | F38: Assessment | H38: Support LGS Labs’ Kinetic User Repair Tracker KURT database | I38: Yes | K38: Unknown | L38: VNA | O38: Monthly | S38: 1120 | T38: 44901 | U38: 24 | V38: =IFERROR(EDATE(T38,U38),"") -> 45632 | W38: =IFERROR(V38-TODAY(),"") -> -461 | Z38: - | AA38: - | AD38: - | AF38: - | AG38: - | AP38: - | AQ38: =IF(ALL_02FEB2024[[#This Row],[Days to Contract End]]<=90,"R",IF(AND(ALL_02FEB2024[[#This Row],[Days to Contract End]]<180),"A","G")) -> R
B39: Captial Title of Texas | C39: =IFERROR(VLOOKUP(B39,'QB Consolidated Contacts'!$A$1:$F$333,6),"-") -> 0 | E39: MSA | F39: Agreement | H39: Master Services Agreement | I39: Yes | K39: Active | L39: VNA | T39: 44102 | U39: ON-GOING | V39: =IFERROR(EDATE(T39,U39),"") | W39: =IFERROR(V39-TODAY(),"") | X39: Yes | AA39: S1M | AP39: $100K | AQ39: =IF(ALL_02FEB2024[[#This Row],[Days to Contract End]]<=90,"R",IF(AND(ALL_02FEB2024[[#This Row],[Days to Contract End]]<180),"A","G")) -> G
B40: Captial Title of Texas | C40: =IFERROR(VLOOKUP(B40,'QB Consolidated Contacts'!$A$1:$F$333,6),"-") -> 0 | D40: Development | E40: SOW | F40: Managed Services | H40: Capital Sales CRM | I40: Yes | K40: Active | L40: VNA | T40: 44136 | U40: ON-GOING | V40: =IFERROR(EDATE(T40,U40),"") | W40: =IFERROR(V40-TODAY(),"") | AQ40: =IF(ALL_02FEB2024[[#This Row],[Days to Contract End]]<=90,"R",IF(AND(ALL_02FEB2024[[#This Row],[Days to Contract End]]<180),"A","G")) -> G
B41: Captial Title of Texas | C41: =IFERROR(VLOOKUP(B41,'QB Consolidated Contacts'!$A$1:$F$333,6),"-") -> 0 | D41: Development | E41: SOW | F41: Managed Services | H41: CRM SQL Server Migration | I41: Yes | K41: Expired | L41: VNA | S41: 48 | T41: 44645 | U41: 12 | V41: =IFERROR(EDATE(T41,U41),"") -> 45010 | W41: =IFERROR(V41-TODAY(),"") -> -1083 | AQ41: =IF(ALL_02FEB2024[[#This Row],[Days to Contract End]]<=90,"R",IF(AND(ALL_02FEB2024[[#This Row],[Days to Contract End]]<180),"A","G")) -> R
B42: Clario | C42: =IFERROR(VLOOKUP(B42,'QB Consolidated Contacts'!$A$1:$F$333,6),"-") -> 0 | E42: MSA | F42: Agreement | H42: Master Services Agreement | I42: Yes | K42: Active | L42: VT | T42: 44869 | U42: 24 | V42: =IFERROR(EDATE(T42,U42),"") -> 45600 | W42: =IFERROR(V42-TODAY(),"") -> -493 | AQ42: =IF(ALL_02FEB2024[[#This Row],[Days to Contract End]]<=90,"R",IF(AND(ALL_02FEB2024[[#This Row],[Days to Contract End]]<180),"A","G")) -> R | AR42: It appears that the redlines have not been resolved and there is no signed MSA currently in effect. Nonetheless, we do have an active PO.
B43: Clario | C43: =IFERROR(VLOOKUP(B43,'QB Consolidated Contacts'!$A$1:$F$333,6),"-") -> 0 | E43: NDA | F43: Agreement | H43: Non-Disclosure Agreement | I43: Yes | K43: Active | L43: VT | T43: 44778 | U43: =5*12 -> 60 | V43: =IFERROR(EDATE(T43,U43),"") -> 46604 | W43: =IFERROR(V43-TODAY(),"") -> 511 | AQ43: =IF(ALL_02FEB2024[[#This Row],[Days to Contract End]]<=90,"R",IF(AND(ALL_02FEB2024[[#This Row],[Days to Contract End]]<180),"A","G")) -> G
B44: Clario | C44: =IFERROR(VLOOKUP(B44,'QB Consolidated Contacts'!$A$1:$F$333,6),"-") -> 0 | D44: Infrastructure | E44: Change Order | F44: Managed Services | H44: Clario_Linux_Unix_ODA_Managed_Services_SOW.v3.ADDENDUM.20221122.13.19.docx | I44: Yes | K44: Active | L44: VT | T44: 44848 | U44: 36 | V44: =IFERROR(EDATE(T44,U44),"") -> 45944 | W44: =IFERROR(V44-TODAY(),"") -> -149 | AQ44: =IF(ALL_02FEB2024[[#This Row],[Days to Contract End]]<=90,"R",IF(AND(ALL_02FEB2024[[#This Row],[Days to Contract End]]<180),"A","G")) -> R
B45: Clario | C45: =IFERROR(VLOOKUP(B45,'QB Consolidated Contacts'!$A$1:$F$333,6),"-") -> 0 | D45: Infrastructure | E45: SOW | F45: Managed Services | G45: Sophie Aaron | H45: Clario_Linux_Unix_ODA_Managed_Services_SOW.v3.20220715.FINAL.docx | I45: Yes | K45: Active | L45: VT | M45: Yes | N45: 101102037 | O45: Monthly | S45: 50 Hrs/Quarter | T45: 44848 | U45: 36 | V45: =IFERROR(EDATE(T45,U45),"") -> 45944 | W45: =IFERROR(V45-TODAY(),"") -> -149 | AQ45: =IF(ALL_02FEB2024[[#This Row],[Days to Contract End]]<=90,"R",IF(AND(ALL_02FEB2024[[#This Row],[Days to Contract End]]<180),"A","G")) -> R | AR45: Automatic Renewal after 36 months - 10/14/2025
B46: Clario | C46: =IFERROR(VLOOKUP(B46,'QB Consolidated Contacts'!$A$1:$F$333,6),"-") -> 0 | D46: Infrastructure | E46: Change Order | F46: Managed Services | H46: CLARIO MANAGED SERVICES CHANGE ORDER 5-22-23.docx | I46: Yes | K46: Active | L46: VT | T46: 45117 | V46: =IFERROR(EDATE(T46,U46),"") -> 45117 | W46: =IFERROR(V46-TODAY(),"") -> -976 | AQ46: =IF(ALL_02FEB2024[[#This Row],[Days to Contract End]]<=90,"R",IF(AND(ALL_02FEB2024[[#This Row],[Days to Contract End]]<180),"A","G")) -> R | AR46: Revision in scope for Clario Managed Services agreement specific to monitored components:
B47: COE | C47: =IFERROR(VLOOKUP(B47,'QB Consolidated Contacts'!$A$1:$F$333,6),"-") -> 0 | E47: MSA | F47: Agreement | H47: Master Services Agreement | I47: Yes | K47: Active | L47: VNA | T47: 43089 | U47: ON-GOING | V47: =IFERROR(EDATE(T47,U47),"") | W47: =IFERROR(V47-TODAY(),"") | X47: Yes | Z47: $1M | AA47: $1M | AD47: - | AF47: - | AG47: - | AP47: $100K | AQ47: =IF(ALL_02FEB2024[[#This Row],[Days to Contract End]]<=90,"R",IF(AND(ALL_02FEB2024[[#This Row],[Days to Contract End]]<180),"A","G")) -> G
B48: COE | C48: =IFERROR(VLOOKUP(B48,'QB Consolidated Contacts'!$A$1:$F$333,6),"-") -> 0 | D48: Infrastructure | E48: SOW | F48: Managed Services | H48: COE.APEX REMOTE SUPPORT SERVICES.SOW.2024.EXECUTED | I48: Yes | J48: Yes | K48: Expired | L48: VNA | N48: No | O48: Monthly | Q48: 3825 | R48: =ALL_02FEB2024[[#This Row],[Monthly Budget]]*12 -> 45900 | S48: 30 | T48: 45200 | U48: 36 | V48: =IFERROR(EDATE(T48,U48),"") -> 46296 | W48: 1440 | X48: No | Z48: - | AA48: - | AD48: - | AF48: - | AG48: - | AP48: - | AQ48: =IF(ALL_02FEB2024[[#This Row],[Days to Contract End]]<=90,"R",IF(AND(ALL_02FEB2024[[#This Row],[Days to Contract End]]<180),"A","G")) -> G | AR48: 3-Year Term
B49: COE | C49: =IFERROR(VLOOKUP(B49,'QB Consolidated Contacts'!$A$1:$F$333,6),"-") -> 0 | D49: Infrastructure | E49: SOW | F49: Managed Services | H49: COE_DBA_Sep_2019 | I49: Yes | K49: Expired | L49: VNA | N49: No | O49: Monthly | T49: 43709 | U49: 24 | V49: =IFERROR(EDATE(T49,U49),"") -> 44440 | W49: =IFERROR(V49-TODAY(),"") -> -1653 | X49: No | Z49: - | AA49: - | AD49: - | AF49: - | AG49: - | AP49: - | AQ49: =IF(ALL_02FEB2024[[#This Row],[Days to Contract End]]<=90,"R",IF(AND(ALL_02FEB2024[[#This Row],[Days to Contract End]]<180),"A","G")) -> R
B50: College of American Pathologists (“CAP”) | C50: =IFERROR(VLOOKUP(B50,'QB Consolidated Contacts'!$A$1:$F$333,6),"-") -> 0 | E50: MSA | F50: Agreement | H50: PO 87781 Viscosity MASTER SERVICES AGREEMENT | V50: =IFERROR(EDATE(T50,U50),"") -> 0 | W50: =IFERROR(V50-TODAY(),"") -> -46093 | AQ50: =IF(ALL_02FEB2024[[#This Row],[Days to Contract End]]<=90,"R",IF(AND(ALL_02FEB2024[[#This Row],[Days to Contract End]]<180),"A","G")) -> R
B51: American Leather | C51: =IFERROR(VLOOKUP(B51,'QB Consolidated Contacts'!$A$1:$F$333,6),"-") -> Roger Santone | D51: Development | E51: SOW | F51: Agreement | G51: Beatriz Aguirre | H51: Records Management and Archive | I51: Yes | J51: Yes | K51: Active | L51: VNA | T51: 45152 | U51: TBD | V51: 45657 | W51: =IFERROR(V51-TODAY(),"") -> -436 | AQ51: =IF(ALL_02FEB2024[[#This Row],[Days to Contract End]]<=90,"R",IF(AND(ALL_02FEB2024[[#This Row],[Days to Contract End]]<180),"A","G")) -> R
B52: American Leather | C52: =IFERROR(VLOOKUP(B52,'QB Consolidated Contacts'!$A$1:$F$333,6),"-") -> Roger Santone | D52: Development | E52: SOW | F52: Agreement | G52: Beatriz Aguirre | H52: VNA-AL-AP Invoice Automation Services-SOW-v2.docx | I52: Yes | J52: Yes | K52: Active | L52: VNA | T52: 45511 | U52: TBD | V52: 45657 | W52: =IFERROR(V52-TODAY(),"") -> -436 | AQ52: =IF(ALL_02FEB2024[[#This Row],[Days to Contract End]]<=90,"R",IF(AND(ALL_02FEB2024[[#This Row],[Days to Contract End]]<180),"A","G")) -> R
B53: American Leather | C53: =IFERROR(VLOOKUP(B53,'QB Consolidated Contacts'!$A$1:$F$333,6),"-") -> Roger Santone | E53: SOW | F53: Professional Services | G53: Sabika Rizvi | H53: SOW.American_Leather.Web_Services.SOW.ORACLE_EBS.AUG2023 | I53: Yes | J53: Yes | K53: Active | T53: 45160 | V53: =IFERROR(EDATE(T53,U53),"") -> 45160 | W53: =IFERROR(V53-TODAY(),"") -> -933 | AQ53: =IF(ALL_02FEB2024[[#This Row],[Days to Contract End]]<=90,"R",IF(AND(ALL_02FEB2024[[#This Row],[Days to Contract End]]<180),"A","G")) -> R
B54: COE | C54: =IFERROR(VLOOKUP(B54,'QB Consolidated Contacts'!$A$1:$F$333,6),"-") -> 0 | E54: SOW | F54: Managed Services | H54: APEX Support | V54: =IFERROR(EDATE(T54,U54),"") -> 0 | W54: =IFERROR(V54-TODAY(),"") -> -46093 | AQ54: =IF(ALL_02FEB2024[[#This Row],[Days to Contract End]]<=90,"R",IF(AND(ALL_02FEB2024[[#This Row],[Days to Contract End]]<180),"A","G")) -> R
B55: COE | C55: =IFERROR(VLOOKUP(B55,'QB Consolidated Contacts'!$A$1:$F$333,6),"-") -> 0 | E55: SOW | F55: Managed Services | H55: Database Managed Services | V55: =IFERROR(EDATE(T55,U55),"") -> 0 | W55: =IFERROR(V55-TODAY(),"") -> -46093 | AQ55: =IF(ALL_02FEB2024[[#This Row],[Days to Contract End]]<=90,"R",IF(AND(ALL_02FEB2024[[#This Row],[Days to Contract End]]<180),"A","G")) -> R
B56: College of American Pathologists (“CAP”) | C56: =IFERROR(VLOOKUP(B56,'QB Consolidated Contacts'!$A$1:$F$333,6),"-") -> 0 | D56: Infrastructure | E56: SOW | F56: Professional Services | G56: Sophie Aaron | H56: ODA Migration | I56: No | K56: Active | L56: VNA | N56: 100550 | T56: 45110 | U56: 7.5 | V56: 45350 | W56: =IFERROR(V56-TODAY(),"") -> -743 | AQ56: =IF(ALL_02FEB2024[[#This Row],[Days to Contract End]]<=90,"R",IF(AND(ALL_02FEB2024[[#This Row],[Days to Contract End]]<180),"A","G")) -> R
B57: Computex Technology Solutions | C57: =IFERROR(VLOOKUP(B57,'QB Consolidated Contacts'!$A$1:$F$333,6),"-") -> 0 | E57: MSA | F57: Agreement | H57: Master Services Agreement | I57: Yes | K57: Active | L57: VNA | T57: 44258 | U57: ON-GOING | V57: =IFERROR(EDATE(T57,U57),"") | W57: =IFERROR(V57-TODAY(),"") | X57: Yes | Z57: $2M | AA57: $1M | AB57: $1M | AD57: $5M | AE57: $1M | AH57: $5M | AI57: $1M | AJ57: $1M | AP57: $1M | AQ57: =IF(ALL_02FEB2024[[#This Row],[Days to Contract End]]<=90,"R",IF(AND(ALL_02FEB2024[[#This Row],[Days to Contract End]]<180),"A","G")) -> G
B58: Computex Technology Solutions | C58: =IFERROR(VLOOKUP(B58,'QB Consolidated Contacts'!$A$1:$F$333,6),"-") -> 0 | E58: NDA | F58: Agreement | H58: Non-Disclosure Agreement | I58: Yes | K58: Active | L58: VNA | O58: - | S58: - | T58: 44270 | U58: ON-GOING | V58: =IFERROR(EDATE(T58,U58),"") | W58: =IFERROR(V58-TODAY(),"") | X58: No | AQ58: =IF(ALL_02FEB2024[[#This Row],[Days to Contract End]]<=90,"R",IF(AND(ALL_02FEB2024[[#This Row],[Days to Contract End]]<180),"A","G")) -> G | AR58: A Recipient’s duty to protect Confidential Information expires three (3) years from the date of any disclosure hereunder
B59: Computex Technology Solutions - Dresser | C59: =IFERROR(VLOOKUP(B59,'QB Consolidated Contacts'!$A$1:$F$333,6),"-") -> 0 | D59: Infrastructure | E59: SOW | F59: Professional Services | H59: Dresser EBS Migration | I59: Yes | K59: Inactive | L59: VNA | O59: Monthly | S59: 1300 | T59: 44512 | U59: ON-GOING | V59: =IFERROR(EDATE(T59,U59),"") | W59: =IFERROR(V59-TODAY(),"") | X59: No | Z59: - | AA59: - | AD59: - | AF59: - | AG59: - | AP59: - | AQ59: =IF(ALL_02FEB2024[[#This Row],[Days to Contract End]]<=90,"R",IF(AND(ALL_02FEB2024[[#This Row],[Days to Contract End]]<180),"A","G")) -> G | AR59: Consultant will migrate client’s Oracle eBusiness Suite application and database currently residing on target entity (on-premises) application server and database server Dresser’s
B60: Computex Technology Solutions - Dresser | C60: =IFERROR(VLOOKUP(B60,'QB Consolidated Contacts'!$A$1:$F$333,6),"-") -> 0 | D60: Infrastructure | E60: SOW | F60: Assessment | H60: Dresser CIM/JiT Assessment | I60: Yes | K60: Inactive | L60: VNA | M60: Yes | N60: PO223602M | O60: Custom | R60: =55440 -> 55440 | S60: =40+40+32 -> 112 | T60: 44850 | V60: =IFERROR(EDATE(T60,U60),"") -> 44850 | W60: =IFERROR(V60-TODAY(),"") -> -1243 | AQ60: =IF(ALL_02FEB2024[[#This Row],[Days to Contract End]]<=90,"R",IF(AND(ALL_02FEB2024[[#This Row],[Days to Contract End]]<180),"A","G")) -> R
B61: Cynet | C61: =IFERROR(VLOOKUP(B61,'QB Consolidated Contacts'!$A$1:$F$333,6),"-") -> 0 | V61: =IFERROR(EDATE(T61,U61),"") -> 0 | W61: =IFERROR(V61-TODAY(),"") -> -46093 | AQ61: =IF(ALL_02FEB2024[[#This Row],[Days to Contract End]]<=90,"R",IF(AND(ALL_02FEB2024[[#This Row],[Days to Contract End]]<180),"A","G")) -> R
B62: Dallas Independent School District | C62: =IFERROR(VLOOKUP(B62,'QB Consolidated Contacts'!$A$1:$F$333,6),"-") -> 0 | D62: Infrastructure | E62: PO | F62: Managed Services | H62: BOS Managed Services | I62: No | K62: Expired | L62: VNA | M62: Yes | O62: Custom | S62: 100 | T62: 43831 | U62: 24 | V62: =IFERROR(EDATE(T62,U62),"") -> 44562 | W62: =IFERROR(V62-TODAY(),"") -> -1531 | X62: No | Z62: - | AA62: - | AD62: - | AF62: - | AG62: - | AP62: - | AQ62: =IF(ALL_02FEB2024[[#This Row],[Days to Contract End]]<=90,"R",IF(AND(ALL_02FEB2024[[#This Row],[Days to Contract End]]<180),"A","G")) -> R | AR62: Scope and Tasks:_x000D_ The scope and requirements are categorized into these phases:_x000D_ 1. Support Hours (100 hours per Quarter)_x000D_ 2. Overage and Out-of-Scope Support
B63: Dallas Independent School District | C63: =IFERROR(VLOOKUP(B63,'QB Consolidated Contacts'!$A$1:$F$333,6),"-") -> 0 | D63: Infrastructure | E63: PO | F63: AOP Renewal | G63: Leisa Pitner | H63: APEX Office Print - On-premises Gold | I63: Yes | K63: Active | L63: VNA | M63: Yes | O63: Custom | T63: 45076 | U63: 12 | V63: =IFERROR(EDATE(T63,U63),"") -> 45442 | W63: =IFERROR(V63-TODAY(),"") -> -651 | AQ63: =IF(ALL_02FEB2024[[#This Row],[Days to Contract End]]<=90,"R",IF(AND(ALL_02FEB2024[[#This Row],[Days to Contract End]]<180),"A","G")) -> R
B64: Dallas Independent School District | C64: =IFERROR(VLOOKUP(B64,'QB Consolidated Contacts'!$A$1:$F$333,6),"-") -> 0 | D64: Infrastructure | E64: PO | F64: Professional Services | H64: License Assessment - 2022 | I64: No | K64: Inactive | L64: VNA | M64: Yes | N64: 862363 | O64: Custom | S64: 144 | T64: 44649 | U64: ON-GOING | V64: =IFERROR(EDATE(T64,U64),"") | W64: =IFERROR(V64-TODAY(),"") | X64: No | Z64: - | AA64: - | AD64: - | AF64: - | AG64: - | AP64: - | AQ64: =IF(ALL_02FEB2024[[#This Row],[Days to Contract End]]<=90,"R",IF(AND(ALL_02FEB2024[[#This Row],[Days to Contract End]]<180),"A","G")) -> G | AR64: Perform a license review of their current footprint for their E-Business Suite, application, and, and database tier.
B65: Dallas Independent School District | C65: =IFERROR(VLOOKUP(B65,'QB Consolidated Contacts'!$A$1:$F$333,6),"-") -> 0 | D65: Infrastructure | E65: SOW | F65: Managed Services | H65: BOS Phase-3 | I65: No | K65: Expired | L65: VNA | M65: Yes | O65: Monthly | S65: 660 | T65: 45030 | V65: =IFERROR(EDATE(T65,U65),"") -> 45030 | W65: =IFERROR(V65-TODAY(),"") -> -1063 | X65: Yes | Y65: Certificate Holder | Z65: - | AA65: - | AD65: - | AF65: - | AG65: - | AP65: - | AQ65: =IF(ALL_02FEB2024[[#This Row],[Days to Contract End]]<=90,"R",IF(AND(ALL_02FEB2024[[#This Row],[Days to Contract End]]<180),"A","G")) -> R | AR65: Upon completion of this statement of work (SOW), Consultant and Client deliver a design, documentation, updated, and working application of the BOS budget management system.
B66: Dallas Independent School District | C66: =IFERROR(VLOOKUP(B66,'QB Consolidated Contacts'!$A$1:$F$333,6),"-") -> 0 | D66: Infrastructure | E66: SOW | F66: Professional Services | G66: Leisa Pitner | H66: Apex Services & Support | I66: Yes | K66: Unknown | L66: VNA | M66: Yes | S66: 150 Hrs/Quarter | T66: Unknown | U66: 12 | V66: 45473 | W66: =IFERROR(V66-TODAY(),"") -> -620 | AQ66: =IF(ALL_02FEB2024[[#This Row],[Days to Contract End]]<=90,"R",IF(AND(ALL_02FEB2024[[#This Row],[Days to Contract End]]<180),"A","G")) -> R
B67: Dallas Independent School District | C67: =IFERROR(VLOOKUP(B67,'QB Consolidated Contacts'!$A$1:$F$333,6),"-") -> 0 | D67: Development | E67: Renewal | F67: Managed Services | H67: 2024 Renewal Letter KH-205563 Viscosity North America.pdf | I67: Yes | J67: Yes | K67: Active | L67: VNA | S67: NA | T67: 45145 | U67: Annual | V67: 45535 | W67: =IFERROR(V67-TODAY(),"") -> -558 | AQ67: =IF(ALL_02FEB2024[[#This Row],[Days to Contract End]]<=90,"R",IF(AND(ALL_02FEB2024[[#This Row],[Days to Contract End]]<180),"A","G")) -> R | AR67: the Dallas Independent School District issued an Award for the above-referenced Request for Proposal (RFP) and it will expire August 31, 2023. The Dallas Independent School District wishes, in accordance of the award and Viscosity North America RFP response, to extend the award through August 31, 2024. The extension includes the same terms and conditions of the original Award.
B68: Dominion Questar | C68: =IFERROR(VLOOKUP(B68,'QB Consolidated Contacts'!$A$1:$F$333,6),"-") -> 0 | E68: Fifth Amendment Agreement | F68: Agreement | H68: New Agreement PO# 50104298; Old Agreement #6163-01A-57112 | I68: Yes | K68: Active | L68: VNA | N68: 50104298 | T68: 44779 | U68: ON-GOING | V68: =IFERROR(EDATE(T68,U68),"") | W68: =IFERROR(V68-TODAY(),"") | AQ68: =IF(ALL_02FEB2024[[#This Row],[Days to Contract End]]<=90,"R",IF(AND(ALL_02FEB2024[[#This Row],[Days to Contract End]]<180),"A","G")) -> G
B69: Dallas Independent School District | C69: =IFERROR(VLOOKUP(B69,'QB Consolidated Contacts'!$A$1:$F$333,6),"-") -> 0 | D69: Development | E69: PO | F69: Professional Services | G69: Leisa Pitner | H69: BOS - Fusion Integration | I69: No | J69: Yes | K69: Active | L69: VNA | N69: 933851 | T69: 45200 | U69: 12 | V69: 45565 | W69: =IFERROR(V69-TODAY(),"") -> -528 | AQ69: =IF(ALL_02FEB2024[[#This Row],[Days to Contract End]]<=90,"R",IF(AND(ALL_02FEB2024[[#This Row],[Days to Contract End]]<180),"A","G")) -> R
B70: Dallas Independent School District | C70: =IFERROR(VLOOKUP(B70,'QB Consolidated Contacts'!$A$1:$F$333,6),"-") -> 0 | D70: Development | E70: PO | F70: Managed Services | G70: Leisa Pitner | H70: BOS Managed Services | I70: No | J70: Yes | K70: Active | L70: VNA | N70: 2023 PO-924830 | T70: 45084 | U70: 12 | V70: =IFERROR(EDATE(T70,U70),"") -> 45450 | W70: =IFERROR(V70-TODAY(),"") -> -643 | AQ70: =IF(ALL_02FEB2024[[#This Row],[Days to Contract End]]<=90,"R",IF(AND(ALL_02FEB2024[[#This Row],[Days to Contract End]]<180),"A","G")) -> R
B71: Dominion Questar | C71: =IFERROR(VLOOKUP(B71,'QB Consolidated Contacts'!$A$1:$F$333,6),"-") -> 0 | E71: PO | F71: Managed Services | G71: Leisa Pitner | H71: DEQP Mobile- Staff Aug- 50162702 | I71: Yes | K71: Active | L71: VNA | M71: Yes | N71: 50162702 | O71: Monthly | S71: 1040 | V71: =IFERROR(EDATE(T71,U71),"") -> 0 | W71: =IFERROR(V71-TODAY(),"") -> -46093 | Z71: - | AA71: - | AD71: - | AF71: - | AG71: - | AP71: - | AQ71: =IF(ALL_02FEB2024[[#This Row],[Days to Contract End]]<=90,"R",IF(AND(ALL_02FEB2024[[#This Row],[Days to Contract End]]<180),"A","G")) -> R | AR71: Oracle, APEX and PL/SQL Support- SIX MONTH TERM
B72: Dominion Questar | C72: =IFERROR(VLOOKUP(B72,'QB Consolidated Contacts'!$A$1:$F$333,6),"-") -> 0 | E72: PO | F72: Managed Services | G72: Leisa Pitner | H72: DEUWI DOT-50162797 | I72: Yes | K72: Active | L72: VNA | M72: Yes | N72: 50162797 | O72: Monthly | S72: 2080 | V72: =IFERROR(EDATE(T72,U72),"") -> 0 | W72: =IFERROR(V72-TODAY(),"") -> -46093 | Z72: - | AA72: - | AD72: - | AF72: - | AG72: - | AP72: - | AQ72: =IF(ALL_02FEB2024[[#This Row],[Days to Contract End]]<=90,"R",IF(AND(ALL_02FEB2024[[#This Row],[Days to Contract End]]<180),"A","G")) -> R | AR72: 12 Month- Staff Augmentation
B73: Excellus | C73: =IFERROR(VLOOKUP(B73,'QB Consolidated Contacts'!$A$1:$F$333,6),"-") -> 0 | D73: Development | E73: SOW | F73: Professional Services | H73: Oracle XMLDB Review | I73: Yes | K73: Expired | L73: VNA | O73: Custom | S73: 60 | T73: 44816 | U73: 3 | V73: =IFERROR(EOMONTH(T73,U73),"") -> 44926 | W73: =IFERROR(V73-TODAY(),"") -> -1167 | Z73: - | AA73: - | AD73: - | AF73: - | AG73: - | AP73: - | AQ73: =IF(ALL_02FEB2024[[#This Row],[Days to Contract End]]<=90,"R",IF(AND(ALL_02FEB2024[[#This Row],[Days to Contract End]]<180),"A","G")) -> R | AR73: Health Plan seeks to engage a supplier to provide practical experience using Oracle’s XML solution to review and provide recommendations on the solution proposed for the Consolidated Clinical Document
B74: Excellus | C74: =IFERROR(VLOOKUP(B74,'QB Consolidated Contacts'!$A$1:$F$333,6),"-") -> 0 | D74: Development | E74: SOW | F74: Professional Services | H74: APEX Forms | I74: Yes | K74: Expired | L74: VNA | O74: Daily | S74: 640 | T74: 44578 | U74: 11 | V74: =IFERROR(EOMONTH(T74,U74),"") -> 44926 | W74: =IFERROR(V74-TODAY(),"") -> -1167 | Z74: - | AA74: - | AD74: - | AF74: - | AG74: - | AP74: - | AQ74: =IF(ALL_02FEB2024[[#This Row],[Days to Contract End]]<=90,"R",IF(AND(ALL_02FEB2024[[#This Row],[Days to Contract End]]<180),"A","G")) -> R | AR74: Creation of 25 APEX forms
B75: Fleet Farm | C75: =IFERROR(VLOOKUP(B75,'QB Consolidated Contacts'!$A$1:$F$333,6),"-") -> 0 | E75: MSA | F75: Unknown | I75: No | K75: Unknown | L75: VT | V75: =IFERROR(EDATE(T75,U75),"") -> 0 | W75: =IFERROR(V75-TODAY(),"") -> -46093 | AQ75: =IF(ALL_02FEB2024[[#This Row],[Days to Contract End]]<=90,"R",IF(AND(ALL_02FEB2024[[#This Row],[Days to Contract End]]<180),"A","G")) -> R
B76: Florida Realtors | C76: =IFERROR(VLOOKUP(B76,'QB Consolidated Contacts'!$A$1:$F$333,6),"-") -> 0 | E76: MSA | F76: Agreement | H76: Master Services Agreement | I76: Yes | K76: Active | L76: VT | O76: - | T76: 44232 | U76: ON-GOING | V76: =IFERROR(EDATE(T76,U76),"") | W76: =IFERROR(V76-TODAY(),"") | X76: Yes | AA76: $1M | AP76: $100K | AQ76: =IF(ALL_02FEB2024[[#This Row],[Days to Contract End]]<=90,"R",IF(AND(ALL_02FEB2024[[#This Row],[Days to Contract End]]<180),"A","G")) -> G
B77: Florida Realtors | C77: =IFERROR(VLOOKUP(B77,'QB Consolidated Contacts'!$A$1:$F$333,6),"-") -> 0 | D77: Infrastructure | E77: SOW | F77: Managed Services | G77: Sophie Aaron | H77: Florida Realtors Monitoring Support Services | I77: Yes | K77: Active | L77: VT | O77: Monthly | R77: 479200 | S77: $2,000/month | T77: 44775 | U77: ON-GOING | V77: =IFERROR(EDATE(T77,U77),"") | W77: =IFERROR(V77-TODAY(),"") | X77: No | Z77: - | AA77: - | AD77: - | AF77: - | AG77: - | AP77: - | AQ77: =IF(ALL_02FEB2024[[#This Row],[Days to Contract End]]<=90,"R",IF(AND(ALL_02FEB2024[[#This Row],[Days to Contract End]]<180),"A","G")) -> G
B78: Flowtrac | C78: =IFERROR(VLOOKUP(B78,'QB Consolidated Contacts'!$A$1:$F$333,6),"-") -> 0 | E78: NDA | F78: Agreement | H78: Non-Disclosure Agreement | I78: Yes | J78: No | K78: Active | L78: VNA | T78: 45061 | U78: 24 | V78: =IFERROR(EDATE(T78,U78),"") -> 45792 | W78: =IFERROR(V78-TODAY(),"") -> -301 | AQ78: =IF(ALL_02FEB2024[[#This Row],[Days to Contract End]]<=90,"R",IF(AND(ALL_02FEB2024[[#This Row],[Days to Contract End]]<180),"A","G")) -> R
B79: FNF | C79: =IFERROR(VLOOKUP(B79,'QB Consolidated Contacts'!$A$1:$F$333,6),"-") -> 0 | E79: MSA | F79: Agreement | H79: Master Services Agreement | I79: Yes | J79: Yes | K79: Active | L79: VNA | T79: 43243 | U79: ON-GOING | V79: =IFERROR(EDATE(T79,U79),"") | W79: =IFERROR(V79-TODAY(),"") | AQ79: =IF(ALL_02FEB2024[[#This Row],[Days to Contract End]]<=90,"R",IF(AND(ALL_02FEB2024[[#This Row],[Days to Contract End]]<180),"A","G")) -> G
B80: FNF | C80: =IFERROR(VLOOKUP(B80,'QB Consolidated Contacts'!$A$1:$F$333,6),"-") -> 0 | D80: Infrastructure | E80: SOW | F80: Managed Services | H80: 19c Upgrade | I80: Yes | K80: Inactive | L80: VT | O80: Monthly | T80: 44294 | U80: ON-GOING | V80: =IFERROR(EDATE(T80,U80),"") | W80: =IFERROR(V80-TODAY(),"") | Z80: - | AA80: - | AD80: - | AF80: - | AG80: - | AP80: - | AQ80: =IF(ALL_02FEB2024[[#This Row],[Days to Contract End]]<=90,"R",IF(AND(ALL_02FEB2024[[#This Row],[Days to Contract End]]<180),"A","G")) -> G | AR80: Upon completion of each environment, after load test successfully completes their run (if applicable), Viscosity will submit an invoice to FNF for payment. Total project cost will not exceed $479,200
B81: FNF | C81: =IFERROR(VLOOKUP(B81,'QB Consolidated Contacts'!$A$1:$F$333,6),"-") -> 0 | D81: Infrastructure | E81: SOW | F81: Managed Services | G81: Sophie Aaron | H81: Managed Services | I81: No | K81: Active | L81: VNA | O81: Monthly | V81: =IFERROR(EDATE(T81,U81),"") -> 0 | W81: =IFERROR(V81-TODAY(),"") -> -46093 | Z81: - | AA81: - | AD81: - | AF81: - | AG81: - | AP81: - | AQ81: =IF(ALL_02FEB2024[[#This Row],[Days to Contract End]]<=90,"R",IF(AND(ALL_02FEB2024[[#This Row],[Days to Contract End]]<180),"A","G")) -> R | AR81: Flat fee of $78K monthly
B82: Follett Content Soultions LLC (SQL Server) | C82: =IFERROR(VLOOKUP(B82,'QB Consolidated Contacts'!$A$1:$F$333,6),"-") -> 0 | D82: Legal Agreement | E82: MBE_WBE Statement | F82: Agreement | G82: Sophie Aaron | H82: VT.MSA.Follett Content Solutions.27JAN2024 Follett Content Edits.FINAL.docx | I82: Yes | J82: Yes | K82: Active | L82: VT | T82: 45315 | U82: ON-GOING | V82: =IFERROR(EDATE(T82,U82),"") | W82: =IFERROR(V82-TODAY(),"") | AA82: $1M | AP82: $100k | AQ82: =IF(ALL_02FEB2024[[#This Row],[Days to Contract End]]<=90,"R",IF(AND(ALL_02FEB2024[[#This Row],[Days to Contract End]]<180),"A","G")) -> G
B83: Follett Content Soultions LLC (SQL Server) | C83: =IFERROR(VLOOKUP(B83,'QB Consolidated Contacts'!$A$1:$F$333,6),"-") -> 0 | D83: Legal Agreement | E83: NDA | F83: Agreement | G83: Sophie Aaron | H83: VT.MNDA.Follett Content Solutions.24JAN2024 (002) Follett Comments FINAL.doc | I83: Yes | J83: Yes | K83: Active | L83: VT | T83: 45324 | U83: 24 | V83: =IFERROR(EDATE(T83,U83),"") -> 46055 | W83: =IFERROR(V83-TODAY(),"") -> -38 | AQ83: =IF(ALL_02FEB2024[[#This Row],[Days to Contract End]]<=90,"R",IF(AND(ALL_02FEB2024[[#This Row],[Days to Contract End]]<180),"A","G")) -> R
B84: Follett Content Soultions LLC (SQL Server) | C84: =IFERROR(VLOOKUP(B84,'QB Consolidated Contacts'!$A$1:$F$333,6),"-") -> 0 | D84: Infrastructure | E84: SOW | F84: Managed Services | G84: Sophie Aaron | V84: =IFERROR(EDATE(T84,U84),"") -> 0 | W84: =IFERROR(V84-TODAY(),"") -> -46093 | AQ84: =IF(ALL_02FEB2024[[#This Row],[Days to Contract End]]<=90,"R",IF(AND(ALL_02FEB2024[[#This Row],[Days to Contract End]]<180),"A","G")) -> R
B85: Follett School Solutions LLC (Oracle EBS) | C85: =IFERROR(VLOOKUP(B85,'QB Consolidated Contacts'!$A$1:$F$333,6),"-") -> 0 | D85: Legal Agreement | E85: MSA | F85: Agreement | G85: Sophie Aaron | H85: Master Services Agreement | I85: Yes | K85: Active | L85: VT | T85: 44732 | U85: ON-GOING | V85: =IFERROR(EDATE(T85,U85),"") | W85: =IFERROR(V85-TODAY(),"") | X85: Yes | AA85: $1M | AP85: $100K | AQ85: =IF(ALL_02FEB2024[[#This Row],[Days to Contract End]]<=90,"R",IF(AND(ALL_02FEB2024[[#This Row],[Days to Contract End]]<180),"A","G")) -> G
B86: Follett School Solutions LLC (Oracle EBS) | C86: =IFERROR(VLOOKUP(B86,'QB Consolidated Contacts'!$A$1:$F$333,6),"-") -> 0 | D86: Legal Agreement | E86: NDA | F86: Agreement | G86: Sophie Aaron | H86: Non-Disclosure Agreement | I86: Yes | K86: Active | L86: VT | T86: 44749 | U86: 24 | V86: =IFERROR(EDATE(T86,U86),"") -> 45480 | W86: =IFERROR(V86-TODAY(),"") -> -613 | AQ86: =IF(ALL_02FEB2024[[#This Row],[Days to Contract End]]<=90,"R",IF(AND(ALL_02FEB2024[[#This Row],[Days to Contract End]]<180),"A","G")) -> R
B87: Follett School Solutions LLC (Oracle EBS) | C87: =IFERROR(VLOOKUP(B87,'QB Consolidated Contacts'!$A$1:$F$333,6),"-") -> 0 | D87: Infrastructure | E87: SOW | F87: Managed Services | G87: Sophie Aaron | H87: Follett Managed Services Database Support SOW 02MAY.V4 Follett edits v1 (5.18.2022) Changes Accepted (002) | I87: Yes | J87: Yes | K87: Active | L87: VT | T87: 45078 | U87: 12 | V87: =IFERROR(EDATE(T87,U87),"") -> 45444 | W87: =IFERROR(V87-TODAY(),"") -> -649 | AQ87: =IF(ALL_02FEB2024[[#This Row],[Days to Contract End]]<=90,"R",IF(AND(ALL_02FEB2024[[#This Row],[Days to Contract End]]<180),"A","G")) -> R
B88: Follett School Solutions LLC (Oracle EBS) | C88: =IFERROR(VLOOKUP(B88,'QB Consolidated Contacts'!$A$1:$F$333,6),"-") -> 0 | D88: Infrastructure | E88: SOW | F88: MS Change Order | G88: Sophie Aaron | H88: Follett School Solutions LLC MS Change Order Jan 2024 FINAL.docx | I88: Yes | J88: Yes | K88: Active | L88: VT | O88: Monthly | S88: 32 Hrs/Month | T88: 45078 | U88: 12 | V88: =IFERROR(EDATE(T88,U88),"") -> 45444 | W88: =IFERROR(V88-TODAY(),"") -> -649 | AQ88: =IF(ALL_02FEB2024[[#This Row],[Days to Contract End]]<=90,"R",IF(AND(ALL_02FEB2024[[#This Row],[Days to Contract End]]<180),"A","G")) -> R | AR88: Thereafter, this SOW shall automatically renew for successive one (1) year terms (each a “Renewal Term”) upon Client’s written approval. Fees upon renewal shall not increase by more than 5%.
B89: Globalstar | C89: =IFERROR(VLOOKUP(B89,'QB Consolidated Contacts'!$A$1:$F$333,6),"-") -> 0 | E89: MSA | F89: Agreement | H89: Master Services Agreement | I89: Yes | J89: Yes | K89: Active | L89: VNA | T89: 45016 | U89: ON-GOING | V89: =IFERROR(EDATE(T89,U89),"") | W89: =IFERROR(V89-TODAY(),"") | AQ89: =IF(ALL_02FEB2024[[#This Row],[Days to Contract End]]<=90,"R",IF(AND(ALL_02FEB2024[[#This Row],[Days to Contract End]]<180),"A","G")) -> G
B90: Globalstar | C90: =IFERROR(VLOOKUP(B90,'QB Consolidated Contacts'!$A$1:$F$333,6),"-") -> 0 | D90: Infrastructure | E90: SOW | F90: Professional Services | H90: ODA Implementation | I90: Yes | K90: Active | L90: VNA | O90: Monthly | P90: Net 30 | R90: 94775 | S90: 477 | T90: 45031 | U90: Block of Hours | V90: =IFERROR(EDATE(T90,U90),"") | W90: =IFERROR(V90-TODAY(),"") | AQ90: =IF(ALL_02FEB2024[[#This Row],[Days to Contract End]]<=90,"R",IF(AND(ALL_02FEB2024[[#This Row],[Days to Contract End]]<180),"A","G")) -> G
B91: HCTRA | C91: =IFERROR(VLOOKUP(B91,'QB Consolidated Contacts'!$A$1:$F$333,6),"-") -> 0 | E91: MSA | F91: Agreement | H91: Consulting Agreement | I91: Yes | K91: Active | L91: VNA | M91: No | N91: - | O91: Biweekly | Q91: - | R91: - | S91: - | T91: 43269 | U91: ON-GOING | V91: =IFERROR(EDATE(T91,U91),"") | W91: =IFERROR(V91-TODAY(),"") | AQ91: =IF(ALL_02FEB2024[[#This Row],[Days to Contract End]]<=90,"R",IF(AND(ALL_02FEB2024[[#This Row],[Days to Contract End]]<180),"A","G")) -> G | AR91: Notwithstanding the foregoing, if this Agreement terminates or is terminated while one or more Project Addenda (as defined in paragraph 2 below) remain outstanding, the terms of this Agreement shall continue to govern each outstanding Project Addendum, and the entire Agreement shall be deemed finally terminated only upon termination of all outstanding Project Addenda, or completion of the work thereunder.
B92: HCTRA | C92: =IFERROR(VLOOKUP(B92,'QB Consolidated Contacts'!$A$1:$F$333,6),"-") -> 0 | D92: Infrastructure | E92: SOW | F92: Professional Services | H92: Harris County | I92: No | K92: Active | L92: VNA | M92: No | N92: - | O92: Biweekly | Q92: - | R92: - | S92: - | T92: 44662 | U92: 6 | V92: =IFERROR(EDATE(T92,U92),"") -> 44845 | W92: =IFERROR(V92-TODAY(),"") -> -1248 | Z92: - | AA92: - | AD92: - | AF92: - | AG92: - | AP92: - | AQ92: =IF(ALL_02FEB2024[[#This Row],[Days to Contract End]]<=90,"R",IF(AND(ALL_02FEB2024[[#This Row],[Days to Contract End]]<180),"A","G")) -> R | AR92: Golden Gate
B93: HRL | C93: =IFERROR(VLOOKUP(B93,'QB Consolidated Contacts'!$A$1:$F$333,6),"-") -> 0 | E93: CSA | F93: Agreement | H93: Signed | I93: Yes | L93: VNA | O93: - | T93: 44301 | U93: 12 | V93: =IFERROR(EDATE(T93,U93),"") -> 44666 | W93: =IFERROR(V93-TODAY(),"") -> -1427 | AQ93: =IF(ALL_02FEB2024[[#This Row],[Days to Contract End]]<=90,"R",IF(AND(ALL_02FEB2024[[#This Row],[Days to Contract End]]<180),"A","G")) -> R
B94: HRL | C94: =IFERROR(VLOOKUP(B94,'QB Consolidated Contacts'!$A$1:$F$333,6),"-") -> 0 | D94: Infrastructure | E94: SOW | F94: Professional Services | H94: Migration And Upgrade | I94: No | K94: Unknown | L94: VNA | O94: Biweekly | S94: =20+24+24+16+88+32+108+28+104+56 -> 500 | T94: 44256 | U94: Block of Hours | V94: =IFERROR(EDATE(T94,U94),"") | W94: =IFERROR(V94-TODAY(),"") | X94: No | AQ94: =IF(ALL_02FEB2024[[#This Row],[Days to Contract End]]<=90,"R",IF(AND(ALL_02FEB2024[[#This Row],[Days to Contract End]]<180),"A","G")) -> G
B95: IdenTrust | C95: =IFERROR(VLOOKUP(B95,'QB Consolidated Contacts'!$A$1:$F$333,6),"-") -> 0 | E95: MSA | F95: Agreement | H95: Master Services Agreement | I95: Yes | J95: No | K95: Active | L95: VNA | O95: - | P95: Net 30 | T95: 43301 | U95: ON-GOING | V95: =IFERROR(EDATE(T95,U95),"") | W95: =IFERROR(V95-TODAY(),"") | AQ95: =IF(ALL_02FEB2024[[#This Row],[Days to Contract End]]<=90,"R",IF(AND(ALL_02FEB2024[[#This Row],[Days to Contract End]]<180),"A","G")) -> G
B96: IdenTrust | C96: =IFERROR(VLOOKUP(B96,'QB Consolidated Contacts'!$A$1:$F$333,6),"-") -> 0 | D96: Infrastructure | E96: SOW | F96: Managed Services | G96: Sophie Aaron | H96: IdenTrust DB Patching 2023 | I96: Yes | J96: Yes | K96: Active | L96: VT | M96: Yes | N96: 81151 | O96: Monthly | S96: 124 | T96: 45140 | U96: ON-GOING | V96: =IFERROR(EDATE(T96,U96),"") | W96: =IFERROR(V96-TODAY(),"") | Z96: - | AA96: - | AD96: - | AF96: - | AG96: - | AP96: - | AQ96: =IF(ALL_02FEB2024[[#This Row],[Days to Contract End]]<=90,"R",IF(AND(ALL_02FEB2024[[#This Row],[Days to Contract End]]<180),"A","G")) -> G | AR96: 4 hours per month are dedicated to Retainer Services meant to review the database environment on a regular basis. Expected in the fall 2023 - revisit no later than May 15
B97: IdenTrust | C97: =IFERROR(VLOOKUP(B97,'QB Consolidated Contacts'!$A$1:$F$333,6),"-") -> 0 | D97: Infrastructure | E97: SOW | F97: Managed Services | H97: IdenTrust Retainer Services - Schedule A VT - Signed | I97: Yes | K97: Expired | T97: 44053 | U97: 12 | V97: =IFERROR(EDATE(T97,U97),"") -> 44418 | W97: =IFERROR(V97-TODAY(),"") -> -1675 | AQ97: =IF(ALL_02FEB2024[[#This Row],[Days to Contract End]]<=90,"R",IF(AND(ALL_02FEB2024[[#This Row],[Days to Contract End]]<180),"A","G")) -> R
B98: IdenTrust | C98: =IFERROR(VLOOKUP(B98,'QB Consolidated Contacts'!$A$1:$F$333,6),"-") -> 0 | D98: Infrastructure | E98: PO | F98: Purchase Order | H98: IDENTRUST Performance Tuning 2023 PO-20069 | K98: Active | L98: VT | O98: Monthly | P98: Net 30 | R98: 19600 | T98: 45062 | U98: Block of Hours | V98: =IFERROR(EDATE(T98,U98),"") | W98: =IFERROR(V98-TODAY(),"") | AQ98: =IF(ALL_02FEB2024[[#This Row],[Days to Contract End]]<=90,"R",IF(AND(ALL_02FEB2024[[#This Row],[Days to Contract End]]<180),"A","G")) -> G
B99: IdenTrust | C99: =IFERROR(VLOOKUP(B99,'QB Consolidated Contacts'!$A$1:$F$333,6),"-") -> 0 | D99: Infrastructure | E99: SOW | F99: Managed Services | H99: Identrust Db Patching 2022 | I99: Yes | K99: Inactive | L99: VT | M99: Yes | O99: Monthly | P99: Net 30 | R99: 21700 | S99: 100 | T99: 44810 | U99: Block of Hours | V99: =IFERROR(EDATE(T99,U99),"") | W99: =IFERROR(V99-TODAY(),"") | X99: No | AQ99: =IF(ALL_02FEB2024[[#This Row],[Days to Contract End]]<=90,"R",IF(AND(ALL_02FEB2024[[#This Row],[Days to Contract End]]<180),"A","G")) -> G
B100: InComm | C100: =IFERROR(VLOOKUP(B100,'QB Consolidated Contacts'!$A$1:$F$333,6),"-") -> 0 | E100: NDA | F100: Agreement | H100: Non-Disclosure Agreement | I100: Yes | T100: 44299 | U100: 36 | V100: =IFERROR(EDATE(T100,U100),"") -> 45395 | W100: =IFERROR(V100-TODAY(),"") -> -698 | AQ100: =IF(ALL_02FEB2024[[#This Row],[Days to Contract End]]<=90,"R",IF(AND(ALL_02FEB2024[[#This Row],[Days to Contract End]]<180),"A","G")) -> R
B101: InComm | C101: =IFERROR(VLOOKUP(B101,'QB Consolidated Contacts'!$A$1:$F$333,6),"-") -> 0 | E101: MSA | F101: Agreement | H101: Master Services Agreement | I101: Yes | K101: Active | L101: VT | T101: 44326 | U101: 12 | V101: =IFERROR(EDATE(T101,U101),"") -> 44691 | W101: =IFERROR(V101-TODAY(),"") -> -1402 | AQ101: =IF(ALL_02FEB2024[[#This Row],[Days to Contract End]]<=90,"R",IF(AND(ALL_02FEB2024[[#This Row],[Days to Contract End]]<180),"A","G")) -> R | AR101: Term. The Term of the Agreement is hereby extended for one (1) year beginning on May 10, 2021 and concluding on May 9, 2022 (“Term”). Thereafter, the Agreement may be extended by written agreement of the parties.
...

Sheet Audit 11.09
A1: REVIEW OF MSA'S ARTICLE 5 - TAX LANGUAGE
A2: 1 | B2: ABC Fitness Solutions | C2: Green
A3: 2 | B3: American Leather | C3: Green
A4: 3 | B4: Clario | C4: Green
A5: 4 | B5: COE | C5: Red (Gov Entity - sb tax exempt maybe)
A6: 5 | B6: College of American Pathologists | C6: Green
A7: 6 | B7: Dallas Independent School District | C7: Yellow (no MSA copy)
A8: 7 | B8: Dominion Questar | C8: Green
A9: 8 | B9: Florida Realtors | C9: Red
A10: 9 | B10: FNF | C10: Yellow (no MSA copy)
A11: 10 | B11: HCTRA | C11: Yellow (no MSA copy)
A12: 11 | B12: IdenTrust | C12: Red
A13: 12 | B13: Just Born | C13: Green
... A17: 16 | B17: Region 10 Education Service Center | C17: Red
A18: 17 | B18: Rent-A-Center | C18: Yellow (no MSA copy) | D18: Lower priority - their agreement MPA
A19: 18 | B19: Ria Services | C19: Green
A20: 19 | B20: Sanofi U.S. Services | C20: Yellow (no MSA copy)
A21: 20 | B21: ServiceLink | C21: Yellow (no file folder)
A22: 21 | B22: Sherwin Williams | C22: Yellow (no MSA copy)
A23: 22 | B23: Sports Med Research & Testing Lab | C23: Yellow (no MSA copy) | D23: Need to get one drafted
A24: 23 | B24: STGenetics | C24: Yellow (no MSA copy)
A25: 24 | B25: Texas de Brazil | C25: Yellow (no MSA copy)
A26: 25 | B26: UMass Memorial Health | C26: Green

Sheet SOWs
A2: SOW Status Report | B2: Signed Copy
A3: Customers | B3: No | C3: Yes | D3: Total
A4: ABC Fitness Solutions, LLC | C4: 4 | D4: 4
A5: American Leather | C5: 6 | D5: 6
A6: College of American Pathologists (“CAP”) | B6: 1 | D6: 1
A7: Dallas Independent School District | B7: 1 | D7: 1
A8: Globalstar | C8: 1 | D8: 1
A9: HCTRA | B9: 1 | D9: 1
A10: Jiffy Lube | C10: 1 | D10: 1
A11: Merit Energy | C11: 1 | D11: 1
A12: MountainWest Pipleline, LLC | C12: 1 | D12: 1
A13: Neiman Marcus | C13: 1 | D13: 1
A14: Oak Ridge National Laboratory | C14: 1 | D14: 1
A15: R+L Carriers | C15: 1 | D15: 1
A16: Sanofi | C16: 1 | D16: 1
A17: Texas de Brazil | B17: 1 | D17: 1
A18: WellCare | C18: 1 | D18: 1
A19: Worldwide Clinical Trials Early Phase Services/Bio | C19: 1 | D19: 1
A20: Incorta | C20: 1 | D20: 1
A21: Just Born | C21: 1 | D21: 1
A22: Nationwide Mutal Insurance Company | C22: 1 | D22: 1
A23: Natural Gas Compression Systems, INC. (NGCSI) | C23: 2 | D23: 2
A24: Lamar Trailer | C24: 1 | D24: 1
A25: Rent-A-Center | B25: 1 | D25: 1
A26: Sports Med Research & Testing Lab | C26: 1 | D26: 1
A27: Total | B27: 5 | C27: 27 | D27: 32
G28: Expiring <90 days | H28: R | I28: =+IF(H28="","",COUNTIF(ALL_02FEB2024[R.A.G. Status],SOWs!H28)) -> 125
G29: Expiring <180 days | H29: A | I29: =+IF(H29="","",COUNTIF(ALL_02FEB2024[R.A.G. Status],SOWs!H29)) -> 0
G30: Active | H30: G | I30: =+IF(H30="","",COUNTIF(ALL_02FEB2024[R.A.G. Status],SOWs!H30)) -> 90
H31: Total | I31: =+COUNTA(ALL_02FEB2024[R.A.G. Status]) -> 215

Sheet Budgets
A3: Row Labels | B3: Sum of Monthly Budget | C3: Sum of Total Budget
A4: ABC Fitness Solutions, LLC | B4: 22410 | C4: 589520
A5: -
A6: Block of Hours | B6: 9000 | C6: 428600
A7: Monthly | B7: 13410 | C7: 160920
A8: ACGI Software
A9: -
A10: Airport Terminal Services | B10: 4500
A11: Monthly | B11: 4500
A12: American Heart Association, Inc. | B12: 5000 | C12: 60000
A13: -
A14: Monthly | B14: 5000 | C14: 60000
A15: American Leather | B15: 12250 | C15: 147000
A16: Monthly | B16: 12250 | C16: 147000
A17: BMW
A18: -
A19: Bot Construction Limited
A20: Monthly
A21: CACI - LGS Labs
A22: -
A23: Monthly
A24: Clario
A25: Monthly
A26: COE | B26: 3825 | C26: 45900
A27: Monthly | B27: 3825 | C27: 45900
A28: Computex Technology Solutions
A29: -
A30: Computex Technology Solutions - Dresser | C30: 55440
A31: Custom | C31: 55440
A32: Monthly
A33: Dallas Independent School District
A34: Custom
A35: Monthly
A36: Dominion Questar
A37: Monthly
A38: Excellus
A39: Custom
A40: Daily
A41: Florida Realtors | C41: 479200
A42: -
A43: Monthly | C43: 479200
A44: FNF
A45: Monthly
A46: Globalstar | C46: 94775
A47: Monthly | C47: 94775
A48: HCTRA | B48: 0 | C48: 0
A49: Biweekly | B49: 0 | C49: 0
A50: HRL
A51: -
A52: Biweekly
A53: IdenTrust | C53: 41300
A54: -
A55: Monthly | C55: 41300
A56: InterMetro Industries Corporation
A57: Monthly
A58: Jiffy Lube | C58: 116200
A59: -
A60: Monthly | C60: 116200
A61: Merit Energy | C61: 26400
A62: Monthly | C62: 26400
A63: Merit Medical Systems | B63: 0 | C63: 7000
A64: -
A65: Monthly | B65: 0 | C65: 7000
A66: Weekly | B66: 0 | C66: 0
A67: Morris-Shea Bridge Company Inc.
A68: -
A69: Monthly
A70: MountainWest Pipleline, LLC | B70: 21625 | C70: 129750
A71: Monthly | B71: 21625 | C71: 129750
A72: National Mango Board
A73: Custom
A74: Neiman Marcus | C74: 75000
A75: Custom | C75: 75000
A76: NeoSystems LLC
A77: Biweekly
A78: Custom
A79: Oak Ridge National Laboratory | C79: 10500
A80: Quarerly | C80: 10500
A81: PathAI/Poplar Healthcare | B81: 4210 | C81: 50520
A82: Monthly | B82: 4210 | C82: 50520
A83: Power Design
A84: -
A85: Monthly
A86: Quest - San Diego County Sheriffs Department
A87: Monthly
A88: Record Deposition Service (RDS)
A89: Monthly
A90: Weekly
A91: Saracen Energy
A92: -
A93: Monthly
A94: ServiceLink
A95: Monthly
A96: Sherwin Williams | B96: 1300
A97: Monthly | B97: 1300
A98: STGenetics
A99: Monthly
A100: Texas de Brazil
A101: Monthly
A102: Umass Memorial Health | B102: 4000
...

Sheet Renewals
B3: Follet | C3: The term of this Agreement is twelve (12) months. The term of this SOW shall begin on the Effective Date, as described on page 1 of this SOW, and shall continue until the last day of the month following the first anniversary of the Effective Date (collectively, the “Initial Term”).1 Thereafter, this SOW shall automatically renew for successive one (1) year terms (each a “Renewal Term”) upon Client’s written approval. Fees upon renewal shall not increase by more than 5%.
B4: IdenTrust | C4: Terms of pricing • Hourly rate for Time and Materials outside the scope of this Agreement will remain fixed at $175/hour for the term. • The term of this Agreement is twelve (12) months. • Viscosity will bill a minimum of 1 hour per service request.
B5: Umass Memorial Health
B15: FNF | C15: Missing SOW for Managed Services

Sheet Audit
A1: Client/Project | B1: Notes | C1: 06.09.2023
A2: Athenian Group
A3: LA Metro- Data Input/Automation | B3: No signed SOW
A4: COE
A5: APEX Support | B5: Expired SOW
A6: Dallas Independent School District
A7: BOS Managed Services | B7: Need to send new SOW/PO April 1st
A8: Dominion Questar
A9: DEQP Mobile- Staff Aug- 50162702 | B9: No signed SOW
A10: DEUWI DOT-50162797 | B10: No signed SOW
A11: FNF
A12: Managed Services | B12: No signed SOW | C12: Follow up with Charles for signed copy
A13: HCTRA
A14: Harris County | B14: No signed SOW
A15: IdenTrust
A16: Retainer Services | B16: SOW expired 08/10/2021
A17: Merit Energy
A18: SUSE Linux Upgrade | B18: No MSA in client folder
A19: Oak Ridge National Laboratory
A20: Exadata Patching - 19c-2023 | B20: No Consultant Agreement on file - invoicing is subject to the Consulting Agreement.
A21: Quest
A22: SAN DIEGO COUNTY SHERIFFS DEPARTMENT | B22: Nothing on file for this
A23: Record Deposition Service
A24: Development Support | B24: SOW Expired - No current change order on file for hours
A25: Ria Services
A26: DBA Managed Services | B26: No MSA and SOW is expired
A27: Scan Soft Solutions
A28: 1099B Managed Services
A29: ServiceLink
A30: DBA Managed Services | B30: No MSA or signed SOW - SOW on file is from 2017 and not signed
A31: Sherwin Williams
A32: Sherwin Managed Services | B32: No signed MSA on file
A33: Texas de Brazil
A34: Texas de Brazil
A35: Transformation Enhancements | B35: No signed SOW
A36: UMass Memorial Health
A37: Database Managed Services | B37: No signed SOW
A38: WellCare
A39: Oracle Database Performance Tuning | B39: No signed SOW
A40: Worldwide Clinical Trials Early Phase Services/Bio
A41: Managed Services | B41: Contract expired in 2020
A42: Innatech APEX Project | B42: not sure what this is
A43: Texas de Brazil Phase II | B43: not sure what this is
A45: Not in ScrumTime | B45: Notes
A46: Globalstar SOW | B46: MSA pending customer response
A47: Mountain West Pipeline | B47: Start date? No PO received - email request to submit invoice sent 03/07/2023 - No signed NDA in file
A48: LGS Labs | B48: Signed SOW - not marked as Open in ST
A49: National Mango | B49: Mango Volume & Inventory System SOW - s/b expiring EOM April 2023 - not marked as open in ST
A53: Planning | B53: Notes
A54: AssetWorks | B54: No MSA or NDA
A58: SOWs needing renewal as of 06.09.2023 | B58: Notes | E58: cancled
A59: American Heart Association, Inc. | B59: Infrastructure | C59: SOW | D59: Managed Services | E59: DBA Managed Services | F59: The term of this SOW begins July 1st, 2022 (“SOW Effective Date”) and shall end on June 30th, 2023 (“SOW End Date”)
A60: IdenTrust | B60: Infrastructure | C60: SOW | D60: Managed Services | E60: IdenTrust Retainer Services - Schedule A VT - Signed
A61: Umass Memorial Health | B61: Infrastructure | C61: SOW | D61: Managed Services | E61: Database Managed Services
A62: FNF | B62: Managed Services | C62: No signed SOW | D62: Follow up with Charles for signed copy
A66: Follett | B66: Infrastructure | C66: SOW | D66: Managed Services | E66: Managed Services

Sheet Contracts Insurance
B1: MSA
B2: Yes
B3: Client | C3: Contact | D3: Line of Business | E3: Contract Type | F3: Work Type | G3: Short Description | H3: Signed Copy | I3: Business | J3: PO | K3: Cycle | L3: Block Of Hours | M3: Effective | N3: Duration (Months) | O3: Expiration | P3: Days to Contract End | Q3: Insurance | R3: COI Requirement | S3: GL Aggregate Limits | T3: GL per Occurrence | U3: Workers Compensation | V3: Employers Liability | W3: Umbrella Aggregate | X3: Umbrella per Occurrence | Y3: Cyber Aggregate | Z3: Cyber per Occurrence | AA3: Professional Liability (E&O) | AB3: Property in Transit | AC3: Employee Theft of Client Property | AD3: Auto Insurance per Occurrence | AE3: R.A.G. Status | AF3: Notes
B4: {=_xlfn._xlws.FILTER(ALL_02FEB2024[],ALL_02FEB2024[Contract Type]&ALL_02FEB2024[General Liability Insurance]=('Contracts Insurance'!B1&'Contracts Insurance'!B2))} -> #NAME? | C4: #NAME? | D4: #NAME? | E4: #NAME? | F4: #NAME? | G4: #NAME? | H4: #NAME? | I4: #NAME? | J4: #NAME? | K4: #NAME? | L4: #NAME? | M4: #NAME? | N4: #NAME? | O4: #NAME? | P4: #NAME? | Q4: #NAME? | R4: #NAME? | S4: #NAME? | T4: #NAME? | U4: #NAME? | V4: #NAME? | W4: #NAME? | X4: #NAME? | Y4: #NAME? | Z4: #NAME? | AA4: #NAME? | AB4: #NAME? | AC4: #NAME? | AD4: #NAME? | AE4: #NAME? | AF4: #NAME? | AG4: #NAME? | AH4: #NAME? | AI4: #NAME? | AJ4: #NAME? | AK4: #NAME? | AL4: #NAME? | AM4: #NAME? | AN4: #NAME? | AO4: #NAME? | AP4: #NAME? | AQ4: #NAME? | AR4: #NAME?
B5: #NAME? | C5: #NAME? | D5: #NAME? | E5: #NAME? | F5: #NAME? | G5: #NAME? | H5: #NAME? | I5: #NAME? | J5: #NAME? | K5: #NAME? | L5: #NAME? | M5: #NAME? | N5: #NAME? | O5: #NAME? | P5: #NAME? | Q5: #NAME? | R5: #NAME? | S5: #NAME? | T5: #NAME? | U5: #NAME? | V5: #NAME? | W5: #NAME? | X5: #NAME? | Y5: #NAME? | Z5: #NAME? | AA5: #NAME? | AB5: #NAME? | AC5: #NAME? | AD5: #NAME? | AE5: #NAME? | AF5: #NAME? | AG5: #NAME? | AH5: #NAME? | AI5: #NAME? | AJ5: #NAME? | AK5: #NAME? | AL5: #NAME? | AM5: #NAME? | AN5: #NAME? | AO5: #NAME? | AP5: #NAME? | AQ5: #NAME? | AR5: #NAME?
B6: #NAME? | C6: #NAME? | D6: #NAME? | E6: #NAME? | F6: #NAME? | G6: #NAME? | H6: #NAME? | I6: #NAME? | J6: #NAME? | K6: #NAME? | L6: #NAME? | M6: #NAME? | N6: #NAME? | O6: #NAME? | P6: #NAME? | Q6: #NAME? | R6: #NAME? | S6: #NAME? | T6: #NAME? | U6: #NAME? | V6: #NAME? | W6: #NAME? | X6: #NAME? | Y6: #NAME? | Z6: #NAME? | AA6: #NAME? | AB6: #NAME? | AC6: #NAME? | AD6: #NAME? | AE6: #NAME? | AF6: #NAME? | AG6: #NAME? | AH6: #NAME? | AI6: #NAME? | AJ6: #NAME? | AK6: #NAME? | AL6: #NAME? | AM6: #NAME? | AN6: #NAME? | AO6: #NAME? | AP6: #NAME? | AQ6: #NAME? | AR6: #NAME?
B7: #NAME? | C7: #NAME? | D7: #NAME? | E7: #NAME? | F7: #NAME? | G7: #NAME? | H7: #NAME? | I7: #NAME? | J7: #NAME? | K7: #NAME? | L7: #NAME? | M7: #NAME? | N7: #NAME? | O7: #NAME? | P7: #NAME? | Q7: #NAME? | R7: #NAME? | S7: #NAME? | T7: #NAME? | U7: #NAME? | V7: #NAME? | W7: #NAME? | X7: #NAME? | Y7: #NAME? | Z7: #NAME? | AA7: #NAME? | AB7: #NAME? | AC7: #NAME? | AD7: #NAME? | AE7: #NAME? | AF7: #NAME? | AG7: #NAME? | AH7: #NAME? | AI7: #NAME? | AJ7: #NAME? | AK7: #NAME? | AL7: #NAME? | AM7: #NAME? | AN7: #NAME? | AO7: #NAME? | AP7: #NAME? | AQ7: #NAME? | AR7: #NAME?
B8: #NAME? | C8: #NAME? | D8: #NAME? | E8: #NAME? | F8: #NAME? | G8: #NAME? | H8: #NAME? | I8: #NAME? | J8: #NAME? | K8: #NAME? | L8: #NAME? | M8: #NAME? | N8: #NAME? | O8: #NAME? | P8: #NAME? | Q8: #NAME? | R8: #NAME? | S8: #NAME? | T8: #NAME? | U8: #NAME? | V8: #NAME? | W8: #NAME? | X8: #NAME? | Y8: #NAME? | Z8: #NAME? | AA8: #NAME? | AB8: #NAME? | AC8: #NAME? | AD8: #NAME? | AE8: #NAME? | AF8: #NAME? | AG8: #NAME? | AH8: #NAME? | AI8: #NAME? | AJ8: #NAME? | AK8: #NAME? | AL8: #NAME? | AM8: #NAME? | AN8: #NAME? | AO8: #NAME? | AP8: #NAME? | AQ8: #NAME? | AR8: #NAME?
B9: #NAME? | C9: #NAME? | D9: #NAME? | E9: #NAME? | F9: #NAME? | G9: #NAME? | H9: #NAME? | I9: #NAME? | J9: #NAME? | K9: #NAME? | L9: #NAME? | M9: #NAME? | N9: #NAME? | O9: #NAME? | P9: #NAME? | Q9: #NAME? | R9: #NAME? | S9: #NAME? | T9: #NAME? | U9: #NAME? | V9: #NAME? | W9: #NAME? | X9: #NAME? | Y9: #NAME? | Z9: #NAME? | AA9: #NAME? | AB9: #NAME? | AC9: #NAME? | AD9: #NAME? | AE9: #NAME? | AF9: #NAME? | AG9: #NAME? | AH9: #NAME? | AI9: #NAME? | AJ9: #NAME? | AK9: #NAME? | AL9: #NAME? | AM9: #NAME? | AN9: #NAME? | AO9: #NAME? | AP9: #NAME? | AQ9: #NAME? | AR9: #NAME?
B10: #NAME? | C10: #NAME? | D10: #NAME? | E10: #NAME? | F10: #NAME? | G10: #NAME? | H10: #NAME? | I10: #NAME? | J10: #NAME? | K10: #NAME? | L10: #NAME? | M10: #NAME? | N10: #NAME? | O10: #NAME? | P10: #NAME? | Q10: #NAME? | R10: #NAME? | S10: #NAME? | T10: #NAME? | U10: #NAME? | V10: #NAME? | W10: #NAME? | X10: #NAME? | Y10: #NAME? | Z10: #NAME? | AA10: #NAME? | AB10: #NAME? | AC10: #NAME? | AD10: #NAME? | AE10: #NAME? | AF10: #NAME? | AG10: #NAME? | AH10: #NAME? | AI10: #NAME? | AJ10: #NAME? | AK10: #NAME? | AL10: #NAME? | AM10: #NAME? | AN10: #NAME? | AO10: #NAME? | AP10: #NAME? | AQ10: #NAME? | AR10: #NAME?
B11: #NAME? | C11: #NAME? | D11: #NAME? | E11: #NAME? | F11: #NAME? | G11: #NAME? | H11: #NAME? | I11: #NAME? | J11: #NAME? | K11: #NAME? | L11: #NAME? | M11: #NAME? | N11: #NAME? | O11: #NAME? | P11: #NAME? | Q11: #NAME? | R11: #NAME? | S11: #NAME? | T11: #NAME? | U11: #NAME? | V11: #NAME? | W11: #NAME? | X11: #NAME? | Y11: #NAME? | Z11: #NAME? | AA11: #NAME? | AB11: #NAME? | AC11: #NAME? | AD11: #NAME? | AE11: #NAME? | AF11: #NAME? | AG11: #NAME? | AH11: #NAME? | AI11: #NAME? | AJ11: #NAME? | AK11: #NAME? | AL11: #NAME? | AM11: #NAME? | AN11: #NAME? | AO11: #NAME? | AP11: #NAME? | AQ11: #NAME? | AR11: #NAME?
B12: #NAME? | C12: #NAME? | D12: #NAME? | E12: #NAME? | F12: #NAME? | G12: #NAME? | H12: #NAME? | I12: #NAME? | J12: #NAME? | K12: #NAME? | L12: #NAME? | M12: #NAME? | N12: #NAME? | O12: #NAME? | P12: #NAME? | Q12: #NAME? | R12: #NAME? | S12: #NAME? | T12: #NAME? | U12: #NAME? | V12: #NAME? | W12: #NAME? | X12: #NAME? | Y12: #NAME? | Z12: #NAME? | AA12: #NAME? | AB12: #NAME? | AC12: #NAME? | AD12: #NAME? | AE12: #NAME? | AF12: #NAME? | AG12: #NAME? | AH12: #NAME? | AI12: #NAME? | AJ12: #NAME? | AK12: #NAME? | AL12: #NAME? | AM12: #NAME? | AN12: #NAME? | AO12: #NAME? | AP12: #NAME? | AQ12: #NAME? | AR12: #NAME?
B13: #NAME? | C13: #NAME? | D13: #NAME? | E13: #NAME? | F13: #NAME? | G13: #NAME? | H13: #NAME? | I13: #NAME? | J13: #NAME? | K13: #NAME? | L13: #NAME? | M13: #NAME? | N13: #NAME? | O13: #NAME? | P13: #NAME? | Q13: #NAME? | R13: #NAME? | S13: #NAME? | T13: #NAME? | U13: #NAME? | V13: #NAME? | W13: #NAME? | X13: #NAME? | Y13: #NAME? | Z13: #NAME? | AA13: #NAME? | AB13: #NAME? | AC13: #NAME? | AD13: #NAME? | AE13: #NAME? | AF13: #NAME? | AG13: #NAME? | AH13: #NAME? | AI13: #NAME? | AJ13: #NAME? | AK13: #NAME? | AL13: #NAME? | AM13: #NAME? | AN13: #NAME? | AO13: #NAME? | AP13: #NAME? | AQ13: #NAME? | AR13: #NAME?
B14: #NAME? | C14: #NAME? | D14: #NAME? | E14: #NAME? | F14: #NAME? | G14: #NAME? | H14: #NAME? | I14: #NAME? | J14: #NAME? | K14: #NAME? | L14: #NAME? | M14: #NAME? | N14: #NAME? | O14: #NAME? | P14: #NAME? | Q14: #NAME? | R14: #NAME? | S14: #NAME? | T14: #NAME? | U14: #NAME? | V14: #NAME? | W14: #NAME? | X14: #NAME? | Y14: #NAME? | Z14: #NAME? | AA14: #NAME? | AB14: #NAME? | AC14: #NAME? | AD14: #NAME? | AE14: #NAME? | AF14: #NAME? | AG14: #NAME? | AH14: #NAME? | AI14: #NAME? | AJ14: #NAME? | AK14: #NAME? | AL14: #NAME? | AM14: #NAME? | AN14: #NAME? | AO14: #NAME? | AP14: #NAME? | AQ14: #NAME? | AR14: #NAME?
B15: #NAME? | C15: #NAME? | D15: #NAME? | E15: #NAME? | F15: #NAME? | G15: #NAME? | H15: #NAME? | I15: #NAME? | J15: #NAME? | K15: #NAME? | L15: #NAME? | M15: #NAME? | N15: #NAME? | O15: #NAME? | P15: #NAME? | Q15: #NAME? | R15: #NAME? | S15: #NAME? | T15: #NAME? | U15: #NAME? | V15: #NAME? | W15: #NAME? | X15: #NAME? | Y15: #NAME? | Z15: #NAME? | AA15: #NAME? | AB15: #NAME? | AC15: #NAME? | AD15: #NAME? | AE15: #NAME? | AF15: #NAME? | AG15: #NAME? | AH15: #NAME? | AI15: #NAME? | AJ15: #NAME? | AK15: #NAME? | AL15: #NAME? | AM15: #NAME? | AN15: #NAME? | AO15: #NAME? | AP15: #NAME? | AQ15: #NAME? | AR15: #NAME?
B16: #NAME? | C16: #NAME? | D16: #NAME? | E16: #NAME? | F16: #NAME? | G16: #NAME? | H16: #NAME? | I16: #NAME? | J16: #NAME? | K16: #NAME? | L16: #NAME? | M16: #NAME? | N16: #NAME? | O16: #NAME? | P16: #NAME? | Q16: #NAME? | R16: #NAME? | S16: #NAME? | T16: #NAME? | U16: #NAME? | V16: #NAME? | W16: #NAME? | X16: #NAME? | Y16: #NAME? | Z16: #NAME? | AA16: #NAME? | AB16: #NAME? | AC16: #NAME? | AD16: #NAME? | AE16: #NAME? | AF16: #NAME? | AG16: #NAME? | AH16: #NAME? | AI16: #NAME? | AJ16: #NAME? | AK16: #NAME? | AL16: #NAME? | AM16: #NAME? | AN16: #NAME? | AO16: #NAME? | AP16: #NAME? | AQ16: #NAME? | AR16: #NAME?
... B19: #NAME? | C19: #NAME? | D19: #NAME? | E19: #NAME? | F19: #NAME? | G19: #NAME? | H19: #NAME? | I19: #NAME? | J19: #NAME? | K19: #NAME? | L19: #NAME? | M19: #NAME? | N19: #NAME? | O19: #NAME? | P19: #NAME? | Q19: #NAME? | R19: #NAME? | S19: #NAME? | T19: #NAME? | U19: #NAME? | V19: #NAME? | W19: #NAME? | X19: #NAME? | Y19: #NAME? | Z19: #NAME? | AA19: #NAME? | AB19: #NAME? | AC19: #NAME? | AD19: #NAME? | AE19: #NAME? | AF19: #NAME? | AG19: #NAME? | AH19: #NAME? | AI19: #NAME? | AJ19: #NAME? | AK19: #NAME? | AL19: #NAME? | AM19: #NAME? | AN19: #NAME? | AO19: #NAME? | AP19: #NAME? | AQ19: #NAME? | AR19: #NAME?

Sheet Insurance
B2: Business | C2: Carrier | D2: Policy # | E2: Deductable | F2: Aggregate Limits | G2: Per Occurrence | H2: Effective Date | I2: Expiration Date | J2: Premiums | K2: Notes
B3: VNA Cyber Liability
B4: VNA GL | C4: Truck Insurance Exchange (Farmers) | D4: 606302693 | F4: 4000000 | G4: 2000000 | H4: 45206 | I4: 45572 | J4: $880.00/Year | K4: EMLI? 1m policy is seprate from the GL
B5: VNA Auto Liability | C5: Truck Insurance Exchange (Farmers) | D5: 606302693 | F5: 2000000 | H5: 45206 | I5: 45572 | J5: *Included with GL
B6: VNA E&O/Professional Liability Insurance/Tech Packages | C6: CFC Underwritting Limited - Lloyd's of London | D6: ESM0739753019 | E6: 15000 | F6: 3000000 | H6: 45160 | I6: 45527 | J6: $34,000/Year
B7: VNA Umbrella/Excess Liability | C7: Truck Insurance Exchange (Farmers) | D7: 606302693 | G7: 5000000 | H7: 45206 | I7: 45572 | J7: *Included with GL
B8: VNA Workers Comp | C8: American Zurich Insurance Company (PayChex) | D8: WC 12-68-329-02 | G8: 2000000 | J8: *Included with PayChex | K8: Disease each employee: $2,000,000.00 | Disease Policy Limit: $2,000,000.00
B9: VT Cyber Liability
B10: VT GL | C10: Westchester - Chubbs Company | D10: F15695481004 | F10: 2000000 | H10: 44978 | I10: 45341 | J10: $3,077.00/Year | K10: Will GL move up to 5m with E&O
B11: VT Auto Liability | C11: Westchester - Chubbs Company | D11: F15695481004 | F11: 1000000 | H11: 44978 | I11: 45342 | J11: *Included with GL
B12: VT E&O/Professional Liability Insurance | C12: Westchester - Chubbs Company | D12: F15695481004 | F12: 1000000 | G12: 1000000 | H12: 44978 | I12: 45343 | J12: *Included with GL | K12: We are approved for 5M as of 9/11/23 -effective date s/b Friday 9/15
B13: VT Umbrella/Excess Liability | F13: 5000000 | K13: We do have
B14: VT Workers Comp | C14: The Standard Fire Insurance Company | D14: UB3T997035 | G14: 100000 | H14: 44682 | I14: 45047 | J14: $15.00/Month | K14: Next Insurance - Disease each employee: $100,000.00 | Disease Policy Limit: $500,000.00
F16: OCS/VNA - need to change to VT

Sheet SOW Insurance Info
A1: Insurance Info for Client's MSA
B2: Description | C2: VNA Current | D2: VT Current
A3: Comml General Liability | B3: Protects your business from claims that it caused bodily injuries or damage to another person's property | C3: =Insurance!F4 -> 4000000 | D3: =Insurance!F10 -> 2000000
A4: Professional Liability | B4: Professional liability insurance (PLI) protects professionals such as accountants, lawyers, and physicians against negligence and other claims initiated by their clients. Professionals with expertise in a specific area require this type of insurance because general liability insurance policies do not offer protection against claims arising from negligence, malpractice, mistakes, or misrepresentation. | C4: =Insurance!F6 -> 3000000 | D4: =Insurance!F12 -> 1000000 | E4: E&O and Professional Liability are the same - cyber falls under
A5: Cyber Liability | B5: Cyber liability insurance, also called cyber security insurance, protects small businesses from the high costs of a data breach or malicious software attack. It covers expenses such as customer notification, credit monitoring, legal fees, and fines. | C5: =Insurance!F6 -> 3000000 | D5: =Insurance!F12 -> 1000000
A6: Automobile Liability
A7: Employer's Liability | B7: Employer’s liability insurance protects your business when an employee sues over a work injury or illness. It's a key policy since almost one in five small businesses will face employee litigation.
A8: Umbrella / Excess Liability | B8: Umbrella insurance is extra insurance that provides protection beyond existing limits and coverages of other policies. Excess liability insurance is coverage provided for the big, unexpected events that can have potentially catastrophic results on your business – from auto accidents to products liability claims. | C8: =Insurance!G7 -> 5000000 | D8: =Insurance!F13 -> 5000000
A9: Workers Comp | B9: Workers' compensation pays for benefits like medical care to treat employees who are injured or become ill because of their jobs. | C9: =Insurance!G8 -> 2000000 | D9: =Insurance!G14 -> 100000
A10: Commercial Crime | B10: Provides protection from financial losses related to business-related crime, including theft by employees, forgery, robbery.

Sheet Scrum Open Contracts
A1: Client | B1: Project Name | C1: Description | D1: Budget Cost | E1: Budget Hours | F1: Notes | G1: Project Cycle | H1: Status
A2: iTradeNetwork, Inc. | B2: [ODA] ODA Database Support | C2: Viscosity will provide professional support services for migrating and upgrading databases on the ODA_x000D_ before the January 9, 2021, go-live date. | D2: 8000 | E2: 40 | G2: Monthly | H2: Closed
A3: @NGCSI | B3: [TIME] Field Timesheets | C3: NATURAL GAS COMPRESSION SYSTEMS, INC. _x000D_ WEEKLY TIME SHEET | G3: Weekly | H3: Closed
A4: @NGCSI | B4: [BRAZ] Brazos County | C4: Brazos County Acquisition (demo, do not use) | D4: 1000 | E4: 10 | G4: Biweekly | H4: Closed
A5: ABC Financial | B5: [APX.RB] APEX -CHANGE ORDER - UNDO/ROLLBACK FUNCTION | C5: Provide Change Order for new Undo/Rollback Function identified by the technical team during a walkthrough | D5: 11960 | E5: 92 | F5: Change Order to APEX Implementation | G5: Monthly | H5: Closed
A6: ABC Financial | B6: [RLBCK] APEX Implementation - Roll Back Change Order | C6: Provide Change Order for new Undo/Rollback Function identified by the technical team during a walkthrough. | D6: 11960 | E6: 92 | G6: Monthly | H6: Closed
A7: ABC Financial | B7: [INF] Informatica - CLOSED-DO NOT USE | C7: Viscosity will provide services, in phases, to help Client deploy, migrate and configure Informatica for the EDW environment. | D7: 194600 | E7: 1112 | F7: PO21-15786 | G7: Monthly | H7: Closed
A8: ABC Financial | B8: [*FBIOP] FBI Performance and Optimization | C8: Viscosity North America, Inc. (“Viscosity”) will perform performance improvement and optimizations to Client’s Fitness BI (“FBI”) database and reporting system. | D8: 229600 | E8: 1312 | F8: PO22-22218 | G8: Monthly | H8: Open
A9: ABC Financial | B9: [*PROSV] ABC - Professional Services | C9: Professional Services for ABC. These hours will be utilized for – Break-Fix, Performance tuning, Troubleshooting, Informatica support, SNOW ticket support and other Database Administration lead tasks. | F9: New - PO21-20556 - 430 hours (Nov 2021). _x000D_ Old POs - both 20 hours:_x000D_ PO#: PO20-13708Date: 2020-09-22_x000D_ PO#: PO20-13420Date: 2020-08-27 | G9: Monthly | H9: Open
A10: ABC Financial | B10: [EDW ] EDW Assessment - CLOSED-DO NOT USE | C10: CLOSED | G10: Monthly | H10: Closed
A11: ABC Financial | B11: [*DTUPG] DataTrack 19c Upgrade - CLOSED-DO NOT USE | C11: Upgrade Data Tracker databases to Oracle Database 19c for utilizing Golden Gate, SPA and RAT. Production and Non-Production | D11: 148400 | E11: 848 | F11: NEW - PO22-22192-300 hours - extension hours to finish, eff Jan 2022._x000D_ OLD - PO21-17233-548 hours - exhausted in Jan 2022 | G11: Monthly | H11: Closed
A12: ABC Financial | B12: [MGDSVC] ABC - Remote EDW Monitoring and Support | C12: Viscosity will provide remote managed support services to Client per the Scope & Services section of the SOW. Scope is limited to EDW daily job monitoring, minor ticket support & basic troubleshooting | D12: 160920 | E12: 2664 | F12: Off-shore monitoring support consultants @ $55/hr_x000D_ USA technical account management @ $175/hr_x000D_ (see SOW for details)_x000D_ https://viscositynorthamerica.sharepoint.com/:b:/s/VNA-Sales/ETJGnMxKt1JKl7MT9bB8z | G12: Monthly | H12: Open
A13: ABC Financial | B13: [FBI] Fitness BI Assessment - CLOSED-DO NOT USE | C13: Viscosity will assess the Fitness BI (FBI) database and reporting architecture to determine if the environment is suitable for performance, scalability and reliability to house the enterprise data war | D13: 25200 | E13: 144 | F13: PO21-19989 | G13: Custom | H13: Closed
A14: ABC Financial | B14: [APEX] APEX Implementation | C14: Consultant will provide UI/UX design, architecture and implementation of APEX for a front end, GUI system_x000D_ for users of the A&D processes. | D14: 132980 | E14: 930 | F14: Total PO: 138,180.00_x000D_ 1 90 Hrs @130.00 11,700_x000D_ 2 80 Hrs @175.00 14,000_x000D_ 3 80 Hrs @175.00 14,000_x000D_ 4 104 Hrs @175.00 18,200_x000D_ 5 456 Hrs @175 59280_x000D_ 6 120 Hrs @175 21000 | G14: Custom | H14: Closed
A15: ABC Financial | B15: [DBALD] DBA Lead Fill - CLOSED-DO NOT USE | C15: CLOSED_x000D_ - PO hours fully used after October 2021 invoicing. Moving DBA Lead fill bucket under 'Professional Services' project. | D15: 178500 | E15: 1020 | F15: PO hours fully used after October 2021 invoicing._x000D_ Original SOW of 520, new SOW of 500 beginning Aug 2021;_x000D_ PO21-16446 and PO21-19035 | G15: Custom | H15: Closed
A16: ABC Financial | B16: [EDWDBU] Oracle Database 19c / EDW Upgrade - CLOSED-DO NOT USE | C16: CLOSED_x000D_ - Old Project - database upgrades for Client’s EDW databases to_x000D_ Oracle Database 19c | D16: 105700 | E16: 604 | F16: PO21-15504_x000D_ _x000D_ Old project - but had some hours left on PO as of end of May 2021 | G16: Custom | H16: Closed
A17: ACGI | B17: [APCAL] APEX Calendar System | G17: Biweekly | H17: Closed
A18: ACGI | B18: [] On Demand Consulting | G18: Monthly | H18: Closed
A19: Airport Terminal Services | B19: [Tax] Tax Consulting | D19: 8750 | E19: 50 | G19: Biweekly | H19: Closed
A20: Airport Terminal Services | B20: [ERP] Oracle ERP Managed Services | C20: 30 hours per month_x000D_ $ 4500 per month | E20: 30 | G20: Monthly | H20: Open
A21: Airport Terminal Services | B21: [ATS] Oracle HCM Managed Services | C21: 10 hours per month $ 1500 per month | E21: 10 | G21: Monthly | H21: Closed
A22: America First Credit Union | B22: [] ODA Imaging | D22: 9000 | G22: Monthly | H22: Closed
A23: American Family Ass. of Kentucky | B23: [CONVR] Oracle Conversion | D23: 28600 | E23: 355 | G23: Biweekly | H23: Closed
A24: American Heart Association | B24: [Inform] AHA Informatica | C24: $175/hour for 60 hours max. | D24: 175 | E24: 60 | G24: Monthly | H24: Closed
A25: American Heart Association | B25: [POC] Shareplex POC | G25: Monthly | H25: Closed
A26: American Heart Association | B26: [MS] DBA Managed Services | G26: Monthly | H26: Open
A27: Apache Industrial Services | B27: [SALES] Sales Cloud Implementation | D27: 36750 | E27: 270 | F27: Invoices Due Upon Receipt. MSA nor SOW show billing cycle. | G27: Biweekly | H27: Closed
A28: Apache Industrial Services | B28: [PROD] Production Support | C28: Production Support and Enhancements for the Apache Sales Cloud Implementation. | G28: Monthly | H28: Closed
A29: Arkansas Office of Courts | B29: [Migrat] Migration Court Management System to Oracle Cloud lnfrastructure | C29: VNA will provide to provide Oracle Cloud lnfrastructure (OCl) Planning, Provisioning, and Post Migration Support_x000D_ services for their Court Management system. | D29: 39600 | E29: 240 | G29: Monthly | H29: Closed
A30: Arthur Rutenberg Homes | B30: [DB SS] Database Support Services | D30: 7000 | E30: 40 | G30: Monthly | H30: Closed
A31: Arthur Rutenberg Homes | B31: [ODA] Performance Tuning and ODA Maintenance | D31: 19240 | G31: Monthly | H31: Closed
A32: Asarco | B32: [2021] Development and Apex Support SOW | C32: Upon completion of this statement of work (SOW), Consultant will supply an APEX Subject Matter Expert to support its design and user experience effort. | D32: 6000 | E32: 40 | G32: Monthly | H32: Closed
A33: Asarco | B33: [ASDBE] Legacy Database Extraction Assessment | C33: Assess best way of extracting the data out of a legacy SQLBase database supporting a PeopleSoft installation. Provide recommendations on another system to migrate the database and replicate reports. | E33: 50 | G33: Custom | H33: Closed
A34: Asarco | B34: [] Support Hours for Oracle and Apex | C34: Future Support Hours - If they use ANY | D34: 3000 | G34: Custom | H34: Closed
A35: BMW | B35: [] APEX Training- 2020 | C35: Training for Eric and Michael | D35: 15000 | G35: Monthly | H35: Closed
A36: BMW | B36: [TRN.21] BMW SQL/APEX TRAINING.2021 | C36: (2) SQL Training Sessions: 1 day (8 hours each) - two (1 day) 8 hour sessions - 16 hours _x000D_ (2) Intro to APEX Training Sessions: 3 days (24 hours each) - so two (3 day) 8-hour sessions = 48 hours | D36: 30000 | E36: 30000 | F36: BMW PO ALSO IN FOLDER: Sales2.0/Contracts/BMW/TRAINING | G36: Custom | H36: Closed
A37: BMW | B37: [TRN22] BMW - BMW SQL/APEX TRAINING.2022 | C37: Consultant will deliver a workshop on Oracle APEX to Client that includes:_x000D_ _x000D_ 1 - 8-Hour SQL Training Session | D37: 15000 | E37: 32 | F37: PO is for 1 SQL 1 Day (8 Hours) and 1 APEX - 24 | G37: Custom | H37: Planning
A38: BMW | B38: [SUPDSH] Supplier KPI Dashboard | C38: Upon completion of this statement of work (SOW), Consultant and Client deliver a working APEX application on Client’s environment by integrating data for display into a Dashboard | D38: 25650 | E38: 190 | G38: Biweekly | H38: Closed
A39: Bezzotech | B39: [BZP] Praxair Forms | E39: 50 | F39: increased to 50 hours budget, do not bill Gerardo because he is not a US citizen, all billing should use Jerry Ward instead of Gerardo | G39: Weekly | H39: Closed
A40: Bot Construction Limited | B40: [APEX] Oracle APEX Timekeeping | D40: 37800 | E40: 280 | G40: Monthly | H40: Closed
A41: Brierley + Partners | B41: [EBS] Oracle EBS and Project Management | C41: Brierley is considering new application(s) to assist in making the monthly closing process move faster. Currently it takes 20+ days to close. | F41: Main contact for this project are John Pedini – jpedini@brierley.com and Phillip Wallace - pwallace@brierley.com | G41: Monthly | H41: Closed
A42: CCG POC | B42: [] CCG POC | G42: Monthly | H42: Closed
A43: COE | B43: [APEX] APEX Support | D43: 3825 | E43: 30 | F43: Contract expires 10/22/2022 (3 year term) | G43: Monthly | H43: Open
A44: COE | B44: [] PE Points Implementation | D44: 11250 | E44: 90 | G44: Monthly | H44: Closed
A45: COE | B45: [COE] COE | D45: 100300 | E45: 920 | G45: Daily | H45: Closed
A46: COE | B46: [MS] Database Managed Services | G46: Monthly | H46: Open
A47: COE | B47: [Enhanc] Empower Enhancements 2020 | D47: 32250 | E47: 250 | G47: Monthly | H47: Closed
A48: COE | B48: [MS-NEW] Managed Services | C48: VNA will provide MS to client 24 hours,7 days per week and 365 days per year. | D48: 21000 | E48: 5 | G48: Monthly | H48: Closed
A49: COE | B49: [] COE Empower Security Documentation | D49: 16800 | E49: 96 | G49: Monthly | H49: Closed
A50: CONCENTRA HEALTH SERVICES | B50: [OFMIG] Oracle Financials Migration | D50: 21760 | E50: 40 | G50: Custom | H50: Closed
A51: Caidan Management Company | B51: [ODAX7] X7 Installation | G51: Monthly | H51: Closed
A52: Caidan Management Company | B52: [] ODA Patching | F52: Payments by Caidan shall be payable_x000D_ within thirty (30) days following receipt of Viscosity’s complete and accurate invoice. | G52: Monthly | H52: Closed
A53: Caidan Management Company | B53: [ODA As] Database +ODA Assessment | C53: 1 week | G53: Monthly | H53: Closed
A54: Capital Title of Texas | B54: [CRM] Capital Sales CRM | C54: Design, build, and deliver a working Oracle APEX + Autonomous application on Client’s environment. | D54: 249000 | E54: 1660 | G54: Custom | H54: Closed
A55: Capital Title of Texas | B55: [CRMSQL] CRM SQL Server Migration Support | C55: Support CTOT for their CRM SQL server migration from their current SQL 2012 Server to a new SQL 2016 Server as well as the move of their RamQuest production SQL database to a new SQL 2019 server. | D55: 9600 | E55: 48 | G55: Custom | H55: Closed
A56: Circuit of the Americas, LLC | B56: [Assess] COTA Assessment | G56: Monthly | H56: Closed
A57: Circuit of the Americas, LLC | B57: [APEX] COTA Event Management System | C57: COTA's FRED Event Management System | D57: 198000 | E57: 1200 | G57: Biweekly | H57: Closed
A58: City of Orlando | B58: [JDEOCI] JDE Data Migration and Reporting | C58: Migrate existing JDE application’s data from AS400 to OAW/Produce Reports to access data and Ad Hoc tool for same. | D58: 85800 | E58: 520 | F58: Pending PO, ETC 08/05 | G58: Custom | H58: Closed
A59: Clay Lacy Aviation | B59: [CLAPOC] Quoting System POC | G59: Monthly | H59: Closed
A60: Clay Lacy Aviation | B60: [CLAEVA] Quoting System Evaluation | D60: 2000 | G60: Monthly | H60: Closed
A61: ClubCorp | B61: [MS] DBA Managed Services | G61: Monthly | H61: Closed
A62: College of American Pathologists | B62: [ODA] ODA DB Migration | C62: Planning,Pre-Migration Documentation,Non-Production Database Migration and Documentation -_x000D_ Migration of Non-Production Databases | D62: 254880 | G62: Monthly | H62: Closed
A63: College of American Pathologists | B63: [ODA] Oracle DB Migration to ODA | D63: 2560 | E63: 16 | G63: Monthly | H63: Closed
A64: College of American Pathologists | B64: [] ODA Setup | C64: DataGuard Replication, Fault Injection testing, and UAT, Prod Standby deployment - 320 hours | G64: Monthly | H64: Closed
A65: Computex Technology Solutions | B65: [TopBld] TopBuild License Review | C65: Viscosity will provide professional services for TopBuild (Client) to perform a license review of their current footprint for their e-biz ste, application and database tier. | D65: 19200 | E65: 96 | F65: VNA subcontract thru Computex- work with cust on license renewals and review: Contract, Renewal Invoices, CSI inventory | G65: Monthly | H65: Closed
A66: Computex Technology Solutions | B66: [DRSEBS] Dresser EBS Migration | C66: Consultant will migrate client’s Oracle eBusiness Suite application and database currently residing on target entity (on-premises) application server and database server Dresser’s | D66: 298500 | E66: 1300 | F66: Computex's client is Dresser- we are subcontracting THROUGH Computex. | G66: Monthly | H66: Open
A67: Connect Your Care LLC | B67: [DGuard] Provision and Setup Oracle Active Data Guard in OCI Phoenix | D67: 19000 | G67: Monthly | H67: Closed
A68: Connect Your Care LLC | B68: [POC] Oracle Cloud Proof of Value and Migration/Support | D68: 112944 | G68: Monthly | H68: Closed
A69: DCI | B69: [DCI] DCI | G69: Monthly | H69: Closed
A70: DENDREON PHARMACEUTICALS, LLC | B70: [SOA] SOA System Assessment | G70: Monthly | H70: Closed
A71: Dallas Independent School District | B71: [BOS3] BOS Phase-3 | C71: Upon completion of this statement of work (SOW), Consultant and Client deliver a design, documentation, updated, and working application of the BOS budget management system. | D71: 95700 | E71: 660 | G71: Monthly | H71: Open
A72: Dallas Independent School District | B72: [BAS] BAUI Assessment | C72: Richard Straggas_x000D_ Executive Director Budget Services/SRFM_x000D_ 9400 North Central Expressway, Suite 500 _x000D_ Dallas, Texas 75231_x000D_ Work: (972) 925-3787_x000D_ Cell: 415-819-4200 | D72: 13775 | E72: 95 | G72: Monthly | H72: Closed
A73: Dallas Independent School District | B73: [LIC] License Assessment: | C73: Detail usage reports and deployment/remediation_x000D_ recommendation_x000D_ License Remediation: Includes deployment and installation of Oracle software options_x000D_ (DB Vault, DB Audit, Life Cycle Mgt Packs) | D73: 42000 | E73: 240 | F73: Rate:_x000D_ $175/hr. All inclusive._x000D_ Total Amount: $42,000 not to exceed_x000D_ Number of Hours:_x000D_ 240 Total | G73: Monthly | H73: Closed
A74: Dallas Independent School District | B74: [APEX] DISD APEX Support May/Jun 2020 | C74: Rate per month is $1,662.50, which entitles them to 10 hours a month. If they exceed, the rate will be $175 / hr. | E74: 10 | G74: Monthly | H74: Closed
A75: Dallas Independent School District | B75: [LCASMT] License Assessment - 2022 | C75: Perform a license review of their current footprint for their E-Business Suite, application, and, and database tier. | D75: 25200 | E75: 144 | F75: Effective April 02/22- PO Dated - 29-MAR-2022_x000D_ License review- 60 hours_x000D_ Env Audit- 40 hours_x000D_ Documentation - 20 hours_x000D_ PM - 24 hours | G75: Custom | H75: Open
A76: Dallas Independent School District | B76: [BOS] BOS Managed Services | C76: Scope and Tasks:_x000D_ The scope and requirements are categorized into these phases:_x000D_ 1. Support Hours (100 hours per Quarter)_x000D_ 2. Overage and Out-of-Scope Support | D76: 21000 | E76: 100 | F76: Billing is quarterly- Updated for October 2021- to go from 14K to 21K/150 Hours | G76: Custom | H76: Open
A77: Dallas Independent School District | B77: [80-SUP] General APEX Support - PO 835313 | C77: This agreement has a bucket of 80 hours as directed by the Client. Additional hours will be requested and authorized by the Client by means of an executed Change Order or additional SOW. | D77: 11600 | E77: 80 | F77: Attached the PO link. the SOW is located in the Dropbox Viscosity Sales 2.0/DISD/Contracts/DISD APEX Support SOW May - June 2021.v4_x000D_ _x000D_ PO is in the PO folder | G77: Monthly | H77: Closed
